Workbook
Name a: #REF!
Name aa: #REF!
Name b: #REF!
Name bbb: #REF!
Name ki: [1]电器仓!#REF!
Name t_Schema: #REF!
Name uti: #REF!
Name 百货收入成本表: #REF!
Name 成本: #REF!
Name 成本倒算: #REF!
Name 橱柜: [2]电器仓!#REF!
Name 戴奥: #REF!
Name 倒算: [3]电器仓!#REF!
Name 诶哟: [4]电器仓!#REF!
Name 儿童: #REF!
Name 费用警示: [5]汇总表!$U$6:$U$9
Name 核算项目___供应商_A___供应商: #REF!
Name 核算项目分类总账: #REF!
Name 核算项目分类总账: #REF!
Name 核算项目分类总账: #REF!
Name 核算项目分类总账: #REF!
Name 核算项目分类总账: #REF!
Name 核算项目明细账: #REF!
Name 核算项目余额表: #REF!
Name 会计分录序时簿: #REF!
Name 就死: #REF!
Name 科目: #REF!
Name 科目: #REF!
Name 科目: #REF!
Name 科目: #REF!
Name 科目: #REF!
Name 科目余额表: #REF!
Name 客户___E_厨衣工程部_: #REF!
Name 明细: #REF!
Name 明细分类账: #REF!
Name 生产领料序时簿: [6]生产领料序时簿!$A$1:$P$12156
Name 是: [7]电器仓!#REF!
Name 说的: #REF!
Name 卫浴柜身车间: [4]电器仓!#REF!
Name 我的: #REF!
Name 无: [8]电器仓!#REF!
Name 销售出库序时簿: [9]电器仓!#REF!
Name 销售订单序时簿: #REF!
Name 衣柜: [8]电器仓!#REF!
Name 增长类型: '[10]2013年费用明细'!$AA$3:$AA$8
Name 装: #REF!
Name 总表: #REF!
Name 总分类账: #REF!

Sheet 经营明细（集团取数）
A1: 2019年橱柜营销线经营情况明细表 | V1: 返回目录
U2: 单位：万元
A3: 部门 | B3: 项目 | C3: 口径 | D3: 类别 | E3: 本月 | F3: 1月 | G3: 2月 | H3: 3月 | I3: 4月 | J3: 5月 | K3: 6月 | L3: 7月 | M3: 8月 | N3: 9月 | O3: 10月 | P3: 11月 | Q3: 12月 | R3: 本年累计 | S3: 上年同期 | T3: 上年全年 | U3: 增长率
A4: 橱柜经销一部 | B4: 收入 | C4: 按产品 | D4: 柜门 | E4: ='4.经营实际明细S'!E4 -> 3262.746 | F4: ='4.经营实际明细S'!F4 -> 882.7972 | G4: ='4.经营实际明细S'!G4 -> 218.0495 | H4: ='4.经营实际明细S'!H4 -> 1458.3992 | I4: ='4.经营实际明细S'!I4 -> 2038.8118 | J4: ='4.经营实际明细S'!J4 -> 2848.1602 | K4: ='4.经营实际明细S'!K4 -> 3262.746 | L4: ='4.经营实际明细S'!L4 -> 0 | ... Q4: ='4.经营实际明细S'!Q4 -> 0 | R4: =SUM(F4:Q4) -> 10708.964 | S4: =基数汇总!S1204 -> 0 | T4: =基数汇总!R1204 -> 0 | U4: =IF(S4>0,R4/S4-1,"") | V4: =E4=M4 -> FALSE | W4: 收入
D5: 台面 | E5: ='4.经营实际明细S'!E5 -> 1827.0219 | F5: ='4.经营实际明细S'!F5 -> 494.974 | G5: ='4.经营实际明细S'!G5 -> 24.6101 | H5: ='4.经营实际明细S'!H5 -> 947.2568 | I5: ='4.经营实际明细S'!I5 -> 1219.9439 | J5: ='4.经营实际明细S'!J5 -> 1624.3654 | K5: ='4.经营实际明细S'!K5 -> 1827.0219 | L5: ='4.经营实际明细S'!L5 -> 0 | ... Q5: ='4.经营实际明细S'!Q5 -> 0 | R5: =SUM(F5:Q5) -> 6138.1721 | S5: =基数汇总!S1205 -> 0 | T5: =基数汇总!R1205 -> 0 | U5: =IF(S5>0,R5/S5-1,"") | V5: =E5=M5 -> FALSE | W5: 收入
D6: OEM烟灶 | E6: ='4.经营实际明细S'!E6 -> 1065.5691 | F6: ='4.经营实际明细S'!F6 -> 150.52394 | G6: ='4.经营实际明细S'!G6 -> 27.740952 | H6: ='4.经营实际明细S'!H6 -> 517.11127 | I6: ='4.经营实际明细S'!I6 -> 650.52488 | J6: ='4.经营实际明细S'!J6 -> 1301.9301 | K6: ='4.经营实际明细S'!K6 -> 1065.5691 | L6: ='4.经营实际明细S'!L6 -> 0 | ... Q6: ='4.经营实际明细S'!Q6 -> 0 | R6: =SUM(F6:Q6) -> 3713.4002 | S6: =基数汇总!S1206 -> 0 | T6: =基数汇总!R1206 -> 0 | U6: =IF(S6>0,R6/S6-1,"") | V6: =E6=M6 -> FALSE | W6: 收入
D7: OEM其他 | E7: ='4.经营实际明细S'!E7-#REF! -> #REF! | F7: ='4.经营实际明细S'!F7-#REF! -> #REF! | G7: ='4.经营实际明细S'!G7-#REF! -> #REF! | H7: ='4.经营实际明细S'!H7-#REF! -> #REF! | I7: ='4.经营实际明细S'!I7-#REF! -> #REF! | J7: ='4.经营实际明细S'!J7-#REF! -> #REF! | K7: ='4.经营实际明细S'!K7-#REF! -> #REF! | L7: ='4.经营实际明细S'!L7-#REF! -> #REF! | ... T7: ='4.经营实际明细S'!T7-#REF! -> #REF! | U7: =IF(S7>0,R7/S7-1,"") -> #REF! | V7: =E7=M7 -> #REF! | W7: 收入
D8: 自制烟灶 | E8: ='4.经营实际明细S'!E8 -> 496.16044 | F8: ='4.经营实际明细S'!F8 -> 109.2042 | G8: ='4.经营实际明细S'!G8 -> 3.1485 | H8: ='4.经营实际明细S'!H8 -> 243.75079 | I8: ='4.经营实际明细S'!I8 -> 375.42012 | J8: ='4.经营实际明细S'!J8 -> 679.01294 | K8: ='4.经营实际明细S'!K8 -> 496.16044 | L8: ='4.经营实际明细S'!L8 -> 0 | ... Q8: ='4.经营实际明细S'!Q8 -> 0 | R8: =SUM(F8:Q8) -> 1906.697 | S8: =基数汇总!S1208 -> 0 | T8: =基数汇总!R1208 -> 0 | U8: =IF(S8>0,R8/S8-1,"") | V8: =E8=M8 -> FALSE | W8: 收入
D9: 其他加收 | E9: ='4.经营实际明细S'!E11 -> 13.7832 | F9: ='4.经营实际明细S'!F11 -> 1.1902 | G9: ='4.经营实际明细S'!G11 -> 0.18 | H9: ='4.经营实际明细S'!H11 -> 1.2159 | I9: ='4.经营实际明细S'!I11 -> 2.5061 | J9: ='4.经营实际明细S'!J11 -> 3.3347 | K9: ='4.经营实际明细S'!K11 -> 13.7832 | L9: ='4.经营实际明细S'!L11 -> 0 | ... Q9: ='4.经营实际明细S'!Q11 -> 0 | R9: =SUM(F9:Q9) -> 22.2101 | S9: =基数汇总!S1209 -> 0 | T9: =基数汇总!R1209 -> 0 | U9: =IF(S9>0,R9/S9-1,"") | V9: =E9=M9 -> FALSE | W9: 收入
C10: 按订单类型 | D10: 常规单 | E10: ='4.经营实际明细S'!E12-#REF! -> #REF! | F10: ='4.经营实际明细S'!F12-#REF! -> #REF! | G10: ='4.经营实际明细S'!G12-#REF! -> #REF! | H10: ='4.经营实际明细S'!H12-#REF! -> #REF! | I10: ='4.经营实际明细S'!I12-#REF! -> #REF! | J10: ='4.经营实际明细S'!J12-#REF! -> #REF! | K10: ='4.经营实际明细S'!K12-#REF! -> #REF! | L10: ='4.经营实际明细S'!L12-#REF! -> #REF! | ... T10: ='4.经营实际明细S'!T12-#REF! -> #REF! | U10: =IF(S10>0,R10/S10-1,"") -> #REF! | V10: =E10=M10 -> #REF! | W10: 收入
D11: 家装单 | E11: ='4.经营实际明细S'!E13 -> 756.7222 | F11: ='4.经营实际明细S'!F13 -> 142.4542 | G11: ='4.经营实际明细S'!G13 -> 2.6275 | H11: ='4.经营实际明细S'!H13 -> 279.4453 | I11: ='4.经营实际明细S'!I13 -> 417.3637 | J11: ='4.经营实际明细S'!J13 -> 546.0461 | K11: ='4.经营实际明细S'!K13 -> 756.7222 | L11: ='4.经营实际明细S'!L13 -> 0 | ... Q11: ='4.经营实际明细S'!Q13 -> 0 | R11: =SUM(F11:Q11) -> 2144.659 | S11: =基数汇总!S1211 -> 0 | T11: =基数汇总!R1211 -> 0 | U11: =IF(S11>0,R11/S11-1,"") | V11: =E11=M11 -> FALSE | W11: 收入
D12: 直供单 | E12: ='4.经营实际明细S'!E14 -> 1226.1848 | F12: ='4.经营实际明细S'!F14 -> 195.3872 | G12: ='4.经营实际明细S'!G14 -> 10.7569 | H12: ='4.经营实际明细S'!H14 -> 409.9069 | I12: ='4.经营实际明细S'!I14 -> 487.7633 | J12: ='4.经营实际明细S'!J14 -> 933.5302 | K12: ='4.经营实际明细S'!K14 -> 1226.1848 | L12: ='4.经营实际明细S'!L14 -> 0 | ... Q12: ='4.经营实际明细S'!Q14 -> 0 | R12: =SUM(F12:Q12) -> 3263.5293 | S12: =基数汇总!S1212 -> 0 | T12: =基数汇总!R1212 -> 0 | U12: =IF(S12>0,R12/S12-1,"") | V12: =E12=M12 -> FALSE | W12: 收入
D13: 网销单 | E13: ='4.经营实际明细S'!E15 -> 0 | F13: ='4.经营实际明细S'!F15 -> 0 | G13: ='4.经营实际明细S'!G15 -> 0 | H13: ='4.经营实际明细S'!H15 -> 0 | I13: ='4.经营实际明细S'!I15 -> 0 | J13: ='4.经营实际明细S'!J15 -> 0 | K13: ='4.经营实际明细S'!K15 -> 0 | L13: ='4.经营实际明细S'!L15 -> 0 | ... Q13: ='4.经营实际明细S'!Q15 -> 0 | R13: =SUM(F13:Q13) -> 0 | S13: =基数汇总!S1213 -> 0 | T13: =基数汇总!R1213 -> 0 | U13: =IF(S13>0,R13/S13-1,"") | V13: =E13=M13 -> TRUE | W13: 收入
D14: 星居单 | E14: ='4.经营实际明细S'!E16 -> 65.4746 | F14: ='4.经营实际明细S'!F16 -> 11.9667 | G14: ='4.经营实际明细S'!G16 -> 0.0175 | H14: ='4.经营实际明细S'!H16 -> 28.7805 | I14: ='4.经营实际明细S'!I16 -> 43.0319 | J14: ='4.经营实际明细S'!J16 -> 57.0708 | K14: ='4.经营实际明细S'!K16 -> 65.4746 | L14: ='4.经营实际明细S'!L16 -> 0 | ... Q14: ='4.经营实际明细S'!Q16 -> 0 | R14: =SUM(F14:Q14) -> 206.342 | S14: =基数汇总!S1214 -> 0 | T14: =基数汇总!R1214 -> 0 | U14: =IF(S14>0,R14/S14-1,"") | V14: =E14=M14 -> FALSE | W14: 收入
D15: 微居单 | E15: ='4.经营实际明细S'!E17 -> 3.6442 | F15: ='4.经营实际明细S'!F17 -> 6.8726 | G15: ='4.经营实际明细S'!G17 -> 2.5441 | H15: ='4.经营实际明细S'!H17 -> 4.1213 | I15: ='4.经营实际明细S'!I17 -> -0.036 | J15: ='4.经营实际明细S'!J17 -> 5.7267 | K15: ='4.经营实际明细S'!K17 -> 3.6442 | L15: ='4.经营实际明细S'!L17 -> 0 | ... Q15: ='4.经营实际明细S'!Q17 -> 0 | R15: =SUM(F15:Q15) -> 22.8729 | S15: =基数汇总!S1215 -> 0 | T15: =基数汇总!R1215 -> 0 | U15: =IF(S15>0,R15/S15-1,"") | V15: =E15=M15 -> FALSE | W15: 收入
C16: 按合同类型 | D16: 普通单 | E16: ='4.经营实际明细S'!E18-#REF! -> #REF! | F16: ='4.经营实际明细S'!F18-#REF! -> #REF! | G16: ='4.经营实际明细S'!G18-#REF! -> #REF! | H16: ='4.经营实际明细S'!H18-#REF! -> #REF! | I16: ='4.经营实际明细S'!I18-#REF! -> #REF! | J16: ='4.经营实际明细S'!J18-#REF! -> #REF! | K16: ='4.经营实际明细S'!K18-#REF! -> #REF! | L16: ='4.经营实际明细S'!L18-#REF! -> #REF! | ... T16: ='4.经营实际明细S'!T18-#REF! -> #REF! | U16: =IF(S16>0,R16/S16-1,"") -> #REF! | V16: =E16=M16 -> #REF! | W16: 收入
D17: 样品单 | E17: ='4.经营实际明细S'!E19 -> 1169.2153 | F17: ='4.经营实际明细S'!F19 -> 185.22204 | G17: ='4.经营实际明细S'!G19 -> 133.08394 | H17: ='4.经营实际明细S'!H19 -> 1725.8406 | I17: ='4.经营实际明细S'!I19 -> 648.00794 | J17: ='4.经营实际明细S'!J19 -> 1064.5288 | K17: ='4.经营实际明细S'!K19 -> 1169.2153 | L17: ='4.经营实际明细S'!L19 -> 0 | ... Q17: ='4.经营实际明细S'!Q19 -> 0 | R17: =SUM(F17:Q17) -> 4925.8987 | S17: =基数汇总!S1217 -> 0 | T17: =基数汇总!R1217 -> 0 | U17: =IF(S17>0,R17/S17-1,"") | V17: =E17=M17 -> FALSE | W17: 收入
D18: 遗留单 | E18: ='4.经营实际明细S'!E20 -> 58.8518 | F18: ='4.经营实际明细S'!F20 -> 0 | G18: ='4.经营实际明细S'!G20 -> 56.5677 | H18: ='4.经营实际明细S'!H20 -> 38.6051 | I18: ='4.经营实际明细S'!I20 -> 69.7847 | J18: ='4.经营实际明细S'!J20 -> 48.8862 | K18: ='4.经营实际明细S'!K20 -> 58.8518 | L18: ='4.经营实际明细S'!L20 -> 0 | ... Q18: ='4.经营实际明细S'!Q20 -> 0 | R18: =SUM(F18:Q18) -> 272.6955 | S18: =基数汇总!S1218 -> 0 | T18: =基数汇总!R1218 -> 0 | U18: =IF(S18>0,R18/S18-1,"") | V18: =E18=M18 -> FALSE | W18: 收入
B19: 成本 | C19: 按产品 | D19: 柜门 | E19: ='4.经营实际明细S'!E21 -> 2348.8346 | F19: ='4.经营实际明细S'!F21 -> 613.94664 | G19: ='4.经营实际明细S'!G21 -> 197.39169 | H19: ='4.经营实际明细S'!H21 -> 1040.4021 | I19: ='4.经营实际明细S'!I21 -> 1466.1016 | J19: ='4.经营实际明细S'!J21 -> 2036.8079 | K19: ='4.经营实际明细S'!K21 -> 2348.8346 | L19: ='4.经营实际明细S'!L21 -> 0 | ... Q19: ='4.经营实际明细S'!Q21 -> 0 | R19: =SUM(F19:Q19) -> 7703.4845 | S19: =基数汇总!S1219 -> 0 | T19: =基数汇总!R1219 -> 0 | U19: =IF(S19>0,R19/S19-1,"") | V19: =E19=M19 -> FALSE | W19: 成本
D20: 台面 | E20: ='4.经营实际明细S'!E22 -> 1380.4815 | F20: ='4.经营实际明细S'!F22 -> 341.47993 | G20: ='4.经营实际明细S'!G22 -> 20.251868 | H20: ='4.经营实际明细S'!H22 -> 657.64611 | I20: ='4.经营实际明细S'!I22 -> 830.99665 | J20: ='4.经营实际明细S'!J22 -> 1118.9076 | K20: ='4.经营实际明细S'!K22 -> 1380.4815 | L20: ='4.经营实际明细S'!L22 -> 0 | ... Q20: ='4.经营实际明细S'!Q22 -> 0 | R20: =SUM(F20:Q20) -> 4349.7636 | S20: =基数汇总!S1220 -> 0 | T20: =基数汇总!R1220 -> 0 | U20: =IF(S20>0,R20/S20-1,"") | V20: =E20=M20 -> FALSE | W20: 成本
D21: OEM烟灶 | E21: ='4.经营实际明细S'!E23 -> 619.02649 | F21: ='4.经营实际明细S'!F23 -> 90.785403 | G21: ='4.经营实际明细S'!G23 -> 18.001939 | H21: ='4.经营实际明细S'!H23 -> 395.85953 | I21: ='4.经营实际明细S'!I23 -> 414.35336 | J21: ='4.经营实际明细S'!J23 -> 749.7923 | K21: ='4.经营实际明细S'!K23 -> 619.02649 | L21: ='4.经营实际明细S'!L23 -> 0 | ... Q21: ='4.经营实际明细S'!Q23 -> 0 | R21: =SUM(F21:Q21) -> 2287.819 | S21: =基数汇总!S1221 -> 0 | T21: =基数汇总!R1221 -> 0 | U21: =IF(S21>0,R21/S21-1,"") | V21: =E21=M21 -> FALSE | W21: 成本
D22: OEM其他 | E22: ='4.经营实际明细S'!E24-#REF! -> #REF! | F22: ='4.经营实际明细S'!F24-#REF! -> #REF! | G22: ='4.经营实际明细S'!G24-#REF! -> #REF! | H22: ='4.经营实际明细S'!H24-#REF! -> #REF! | I22: ='4.经营实际明细S'!I24-#REF! -> #REF! | J22: ='4.经营实际明细S'!J24-#REF! -> #REF! | K22: ='4.经营实际明细S'!K24-#REF! -> #REF! | L22: ='4.经营实际明细S'!L24-#REF! -> #REF! | ... T22: ='4.经营实际明细S'!T24-#REF! -> #REF! | U22: =IF(S22>0,R22/S22-1,"") -> #REF! | V22: =E22=M22 -> #REF! | W22: 成本
D23: 自制烟灶 | E23: ='4.经营实际明细S'!E25 -> 243.10799 | F23: ='4.经营实际明细S'!F25 -> 58.5815 | G23: ='4.经营实际明细S'!G25 -> 1.5616 | H23: ='4.经营实际明细S'!H25 -> 127.86267 | I23: ='4.经营实际明细S'!I25 -> 190.12967 | J23: ='4.经营实际明细S'!J25 -> 335.96328 | K23: ='4.经营实际明细S'!K25 -> 243.10799 | L23: ='4.经营实际明细S'!L25 -> 0 | ... Q23: ='4.经营实际明细S'!Q25 -> 0 | R23: =SUM(F23:Q23) -> 957.2067 | S23: =基数汇总!S1223 -> 0 | T23: =基数汇总!R1223 -> 0 | U23: =IF(S23>0,R23/S23-1,"") | V23: =E23=M23 -> FALSE | W23: 成本
D24: 其他加收 | E24: ='4.经营实际明细S'!E28 -> 0 | F24: ='4.经营实际明细S'!F28 -> 0 | G24: ='4.经营实际明细S'!G28 -> 0 | H24: ='4.经营实际明细S'!H28 -> 0 | I24: ='4.经营实际明细S'!I28 -> 0 | J24: ='4.经营实际明细S'!J28 -> 0 | K24: ='4.经营实际明细S'!K28 -> 0 | L24: ='4.经营实际明细S'!L28 -> 0 | ... Q24: ='4.经营实际明细S'!Q28 -> 0 | R24: =SUM(F24:Q24) -> 0 | S24: =基数汇总!S1224 -> 0 | T24: =基数汇总!R1224 -> 0 | U24: =IF(S24>0,R24/S24-1,"") | V24: =E24=M24 -> TRUE | W24: 成本
C25: 按订单类型 | D25: 常规单 | E25: ='4.经营实际明细S'!E29-#REF! -> #REF! | F25: ='4.经营实际明细S'!F29-#REF! -> #REF! | G25: ='4.经营实际明细S'!G29-#REF! -> #REF! | H25: ='4.经营实际明细S'!H29-#REF! -> #REF! | I25: ='4.经营实际明细S'!I29-#REF! -> #REF! | J25: ='4.经营实际明细S'!J29-#REF! -> #REF! | K25: ='4.经营实际明细S'!K29-#REF! -> #REF! | L25: ='4.经营实际明细S'!L29-#REF! -> #REF! | ... T25: ='4.经营实际明细S'!T29-#REF! -> #REF! | U25: =IF(S25>0,R25/S25-1,"") -> #REF! | V25: =E25=M25 -> #REF! | W25: 成本
D26: 家装单 | E26: ='4.经营实际明细S'!E30 -> 598.43627 | F26: ='4.经营实际明细S'!F30 -> 99.684994 | G26: ='4.经营实际明细S'!G30 -> 1.7068388 | H26: ='4.经营实际明细S'!H30 -> 200.65863 | I26: ='4.经营实际明细S'!I30 -> 312.59058 | J26: ='4.经营实际明细S'!J30 -> 394.11776 | K26: ='4.经营实际明细S'!K30 -> 598.43627 | L26: ='4.经营实际明细S'!L30 -> 0 | ... Q26: ='4.经营实际明细S'!Q30 -> 0 | R26: =SUM(F26:Q26) -> 1607.1951 | S26: =基数汇总!S1226 -> 0 | T26: =基数汇总!R1226 -> 0 | U26: =IF(S26>0,R26/S26-1,"") | V26: =E26=M26 -> FALSE | W26: 成本
D27: 直供单 | E27: ='4.经营实际明细S'!E31 -> 994.85471 | F27: ='4.经营实际明细S'!F31 -> 130.78289 | G27: ='4.经营实际明细S'!G31 -> 7.8426844 | H27: ='4.经营实际明细S'!H31 -> 278.66127 | I27: ='4.经营实际明细S'!I31 -> 334.75083 | J27: ='4.经营实际明细S'!J31 -> 618.00693 | K27: ='4.经营实际明细S'!K31 -> 994.85471 | L27: ='4.经营实际明细S'!L31 -> 0 | ... Q27: ='4.经营实际明细S'!Q31 -> 0 | R27: =SUM(F27:Q27) -> 2364.8993 | S27: =基数汇总!S1227 -> 0 | T27: =基数汇总!R1227 -> 0 | U27: =IF(S27>0,R27/S27-1,"") | V27: =E27=M27 -> FALSE | W27: 成本
D28: 网销单 | E28: ='4.经营实际明细S'!E32 -> 0 | F28: ='4.经营实际明细S'!F32 -> 0 | G28: ='4.经营实际明细S'!G32 -> 0 | H28: ='4.经营实际明细S'!H32 -> 0 | I28: ='4.经营实际明细S'!I32 -> 0 | J28: ='4.经营实际明细S'!J32 -> 0 | K28: ='4.经营实际明细S'!K32 -> 0 | L28: ='4.经营实际明细S'!L32 -> 0 | ... Q28: ='4.经营实际明细S'!Q32 -> 0 | R28: =SUM(F28:Q28) -> 0 | S28: =基数汇总!S1228 -> 0 | T28: =基数汇总!R1228 -> 0 | U28: =IF(S28>0,R28/S28-1,"") | V28: =E28=M28 -> TRUE | W28: 成本
D29: 星居单 | E29: ='4.经营实际明细S'!E33 -> 45.214408 | F29: ='4.经营实际明细S'!F33 -> 7.9154301 | G29: ='4.经营实际明细S'!G33 -> 0.01292724 | H29: ='4.经营实际明细S'!H33 -> 19.249475 | I29: ='4.经营实际明细S'!I33 -> 29.079337 | J29: ='4.经营实际明细S'!J33 -> 38.93063 | K29: ='4.经营实际明细S'!K33 -> 45.214408 | L29: ='4.经营实际明细S'!L33 -> 0 | ... Q29: ='4.经营实际明细S'!Q33 -> 0 | R29: =SUM(F29:Q29) -> 140.40221 | S29: =基数汇总!S1229 -> 0 | T29: =基数汇总!R1229 -> 0 | U29: =IF(S29>0,R29/S29-1,"") | V29: =E29=M29 -> FALSE | W29: 成本
D30: 微居单 | E30: ='4.经营实际明细S'!E34 -> 2.8126861 | F30: ='4.经营实际明细S'!F34 -> 5.3655678 | G30: ='4.经营实际明细S'!G34 -> 2.0829591 | H30: ='4.经营实际明细S'!H34 -> 3.2597156 | I30: ='4.经营实际明细S'!I34 -> -0.028950529 | J30: ='4.经营实际明细S'!J34 -> 4.6718265 | K30: ='4.经营实际明细S'!K34 -> 2.8126861 | L30: ='4.经营实际明细S'!L34 -> 0 | ... Q30: ='4.经营实际明细S'!Q34 -> 0 | R30: =SUM(F30:Q30) -> 18.163805 | S30: =基数汇总!S1230 -> 0 | T30: =基数汇总!R1230 -> 0 | U30: =IF(S30>0,R30/S30-1,"") | V30: =E30=M30 -> FALSE | W30: 成本
C31: 按合同类型 | D31: 普通单 | E31: ='4.经营实际明细S'!E35-#REF! -> #REF! | F31: ='4.经营实际明细S'!F35-#REF! -> #REF! | G31: ='4.经营实际明细S'!G35-#REF! -> #REF! | H31: ='4.经营实际明细S'!H35-#REF! -> #REF! | I31: ='4.经营实际明细S'!I35-#REF! -> #REF! | J31: ='4.经营实际明细S'!J35-#REF! -> #REF! | K31: ='4.经营实际明细S'!K35-#REF! -> #REF! | L31: ='4.经营实际明细S'!L35-#REF! -> #REF! | ... T31: ='4.经营实际明细S'!T35-#REF! -> #REF! | U31: =IF(S31>0,R31/S31-1,"") -> #REF! | V31: =E31=M31 -> #REF! | W31: 成本
D32: 样品单 | E32: ='4.经营实际明细S'!E36 -> 880.00395 | F32: ='4.经营实际明细S'!F36 -> 144.38394 | G32: ='4.经营实际明细S'!G36 -> 129.55535 | H32: ='4.经营实际明细S'!H36 -> 1203.9785 | I32: ='4.经营实际明细S'!I36 -> 486.52707 | J32: ='4.经营实际明细S'!J36 -> 794.07675 | K32: ='4.经营实际明细S'!K36 -> 880.00395 | L32: ='4.经营实际明细S'!L36 -> 0 | ... Q32: ='4.经营实际明细S'!Q36 -> 0 | R32: =SUM(F32:Q32) -> 3638.5255 | S32: =基数汇总!S1232 -> 0 | T32: =基数汇总!R1232 -> 0 | U32: =IF(S32>0,R32/S32-1,"") | V32: =E32=M32 -> FALSE | W32: 成本
D33: 遗留单 | E33: ='4.经营实际明细S'!E37 -> 45.550782 | F33: ='4.经营实际明细S'!F37 -> 9.182839 | G33: ='4.经营实际明细S'!G37 -> 38.825615 | H33: ='4.经营实际明细S'!H37 -> 30.237687 | I33: ='4.经营实际明细S'!I37 -> 44.508878 | J33: ='4.经营实际明细S'!J37 -> 37.845278 | K33: ='4.经营实际明细S'!K37 -> 45.550782 | L33: ='4.经营实际明细S'!L37 -> 0 | ... Q33: ='4.经营实际明细S'!Q37 -> 0 | R33: =SUM(F33:Q33) -> 206.15108 | S33: =基数汇总!S1233 -> 0 | T33: =基数汇总!R1233 -> 0 | U33: =IF(S33>0,R33/S33-1,"") | V33: =E33=M33 -> FALSE | W33: 成本
B34: 毛利 | C34: 按产品 | D34: 柜门 | E34: ='4.经营实际明细S'!E38 -> 913.91144 | F34: ='4.经营实际明细S'!F38 -> 268.85056 | G34: ='4.经营实际明细S'!G38 -> 20.657814 | H34: ='4.经营实际明细S'!H38 -> 417.9971 | I34: ='4.经营实际明细S'!I38 -> 572.71017 | J34: ='4.经营实际明细S'!J38 -> 811.35228 | K34: ='4.经营实际明细S'!K38 -> 913.91144 | L34: ='4.经营实际明细S'!L38 -> 0 | ... Q34: ='4.经营实际明细S'!Q38 -> 0 | R34: =SUM(F34:Q34) -> 3005.4794 | S34: =基数汇总!S1234 -> 0 | T34: =基数汇总!R1234 -> 0 | U34: =IF(S34>0,R34/S34-1,"") | V34: =E34=M34 -> FALSE | W34: 毛利
D35: 台面 | E35: ='4.经营实际明细S'!E39 -> 446.54042 | F35: ='4.经营实际明细S'!F39 -> 153.49407 | G35: ='4.经营实际明细S'!G39 -> 4.358232 | H35: ='4.经营实际明细S'!H39 -> 289.61069 | I35: ='4.经营实际明细S'!I39 -> 388.94725 | J35: ='4.经营实际明细S'!J39 -> 505.45781 | K35: ='4.经营实际明细S'!K39 -> 446.54042 | L35: ='4.经营实际明细S'!L39 -> 0 | ... Q35: ='4.经营实际明细S'!Q39 -> 0 | R35: =SUM(F35:Q35) -> 1788.4085 | S35: =基数汇总!S1235 -> 0 | T35: =基数汇总!R1235 -> 0 | U35: =IF(S35>0,R35/S35-1,"") | V35: =E35=M35 -> FALSE | W35: 毛利
D36: OEM烟灶 | E36: ='4.经营实际明细S'!E40 -> 446.54259 | F36: ='4.经营实际明细S'!F40 -> 59.738539 | G36: ='4.经营实际明细S'!G40 -> 9.739013 | H36: ='4.经营实际明细S'!H40 -> 121.25174 | I36: ='4.经营实际明细S'!I40 -> 236.17152 | J36: ='4.经营实际明细S'!J40 -> 552.13777 | K36: ='4.经营实际明细S'!K40 -> 446.54259 | L36: ='4.经营实际明细S'!L40 -> 0 | ... Q36: ='4.经营实际明细S'!Q40 -> 0 | R36: =SUM(F36:Q36) -> 1425.5812 | S36: =基数汇总!S1236 -> 0 | T36: =基数汇总!R1236 -> 0 | U36: =IF(S36>0,R36/S36-1,"") | V36: =E36=M36 -> FALSE | W36: 毛利
D37: OEM其他 | E37: ='4.经营实际明细S'!E41-#REF! -> #REF! | F37: ='4.经营实际明细S'!F41-#REF! -> #REF! | G37: ='4.经营实际明细S'!G41-#REF! -> #REF! | H37: ='4.经营实际明细S'!H41-#REF! -> #REF! | I37: ='4.经营实际明细S'!I41-#REF! -> #REF! | J37: ='4.经营实际明细S'!J41-#REF! -> #REF! | K37: ='4.经营实际明细S'!K41-#REF! -> #REF! | L37: ='4.经营实际明细S'!L41-#REF! -> #REF! | ... T37: ='4.经营实际明细S'!T41-#REF! -> #REF! | U37: =IF(S37>0,R37/S37-1,"") -> #REF! | V37: =E37=M37 -> #REF! | W37: 毛利
D38: 自制烟灶 | E38: ='4.经营实际明细S'!E42 -> 253.05245 | F38: ='4.经营实际明细S'!F42 -> 50.6227 | G38: ='4.经营实际明细S'!G42 -> 1.5869 | H38: ='4.经营实际明细S'!H42 -> 115.88813 | I38: ='4.经营实际明细S'!I42 -> 185.29046 | J38: ='4.经营实际明细S'!J42 -> 343.04967 | K38: ='4.经营实际明细S'!K42 -> 253.05245 | L38: ='4.经营实际明细S'!L42 -> 0 | ... Q38: ='4.经营实际明细S'!Q42 -> 0 | R38: =SUM(F38:Q38) -> 949.4903 | S38: =基数汇总!S1238 -> 0 | T38: =基数汇总!R1238 -> 223.83993 | U38: =IF(S38>0,R38/S38-1,"") | V38: =E38=M38 -> FALSE | W38: 毛利
D39: 其他加收 | E39: ='4.经营实际明细S'!E45 -> 13.7832 | F39: ='4.经营实际明细S'!F45 -> 1.1902 | G39: ='4.经营实际明细S'!G45 -> 0.18 | H39: ='4.经营实际明细S'!H45 -> 1.2159 | I39: ='4.经营实际明细S'!I45 -> 2.5061 | J39: ='4.经营实际明细S'!J45 -> 3.3347 | K39: ='4.经营实际明细S'!K45 -> 13.7832 | L39: ='4.经营实际明细S'!L45 -> 0 | ... Q39: ='4.经营实际明细S'!Q45 -> 0 | R39: =SUM(F39:Q39) -> 22.2101 | S39: =基数汇总!S1239 -> 0 | T39: =基数汇总!R1239 -> 132.05217 | U39: =IF(S39>0,R39/S39-1,"") | V39: =E39=M39 -> FALSE | W39: 毛利
C40: 按订单类型 | D40: 常规单 | E40: ='4.经营实际明细S'!E46-#REF! -> #REF! | F40: ='4.经营实际明细S'!F46-#REF! -> #REF! | G40: ='4.经营实际明细S'!G46-#REF! -> #REF! | H40: ='4.经营实际明细S'!H46-#REF! -> #REF! | I40: ='4.经营实际明细S'!I46-#REF! -> #REF! | J40: ='4.经营实际明细S'!J46-#REF! -> #REF! | K40: ='4.经营实际明细S'!K46-#REF! -> #REF! | L40: ='4.经营实际明细S'!L46-#REF! -> #REF! | ... T40: ='4.经营实际明细S'!T46-#REF! -> #REF! | U40: =IF(S40>0,R40/S40-1,"") -> #REF! | V40: =E40=M40 -> #REF! | W40: 毛利
D41: 家装单 | E41: ='4.经营实际明细S'!E47 -> 158.28593 | F41: ='4.经营实际明细S'!F47 -> 42.769206 | G41: ='4.经营实际明细S'!G47 -> 0.92066123 | H41: ='4.经营实际明细S'!H47 -> 78.786672 | I41: ='4.经营实际明细S'!I47 -> 104.77312 | J41: ='4.经营实际明细S'!J47 -> 151.92834 | K41: ='4.经营实际明细S'!K47 -> 158.28593 | L41: ='4.经营实际明细S'!L47 -> 0 | ... Q41: ='4.经营实际明细S'!Q47 -> 0 | R41: =SUM(F41:Q41) -> 537.46393 | S41: =基数汇总!S1241 -> 0 | T41: =基数汇总!R1241 -> 0 | U41: =IF(S41>0,R41/S41-1,"") | V41: =E41=M41 -> FALSE | W41: 毛利
D42: 直供单 | E42: ='4.经营实际明细S'!E48 -> 231.33009 | F42: ='4.经营实际明细S'!F48 -> 64.604311 | G42: ='4.经营实际明细S'!G48 -> 2.9142156 | H42: ='4.经营实际明细S'!H48 -> 131.24563 | I42: ='4.经营实际明细S'!I48 -> 153.01247 | J42: ='4.经营实际明细S'!J48 -> 315.52327 | K42: ='4.经营实际明细S'!K48 -> 231.33009 | L42: ='4.经营实际明细S'!L48 -> 0 | ... Q42: ='4.经营实际明细S'!Q48 -> 0 | R42: =SUM(F42:Q42) -> 898.62998 | S42: =基数汇总!S1242 -> 0 | T42: =基数汇总!R1242 -> 0 | U42: =IF(S42>0,R42/S42-1,"") | V42: =E42=M42 -> FALSE | W42: 毛利
D43: 网销单 | E43: ='4.经营实际明细S'!E49 -> 0 | F43: ='4.经营实际明细S'!F49 -> 0 | G43: ='4.经营实际明细S'!G49 -> 0 | H43: ='4.经营实际明细S'!H49 -> 0 | I43: ='4.经营实际明细S'!I49 -> 0 | J43: ='4.经营实际明细S'!J49 -> 0 | K43: ='4.经营实际明细S'!K49 -> 0 | L43: ='4.经营实际明细S'!L49 -> 0 | ... Q43: ='4.经营实际明细S'!Q49 -> 0 | R43: =SUM(F43:Q43) -> 0 | S43: =基数汇总!S1243 -> 0 | T43: =基数汇总!R1243 -> 0 | U43: =IF(S43>0,R43/S43-1,"") | V43: =E43=M43 -> TRUE | W43: 毛利
D44: 星居单 | E44: ='4.经营实际明细S'!E50 -> 20.260192 | F44: ='4.经营实际明细S'!F50 -> 4.0512699 | G44: ='4.经营实际明细S'!G50 -> 0.0045727596 | H44: ='4.经营实际明细S'!H50 -> 9.5310249 | I44: ='4.经营实际明细S'!I50 -> 13.952563 | J44: ='4.经营实际明细S'!J50 -> 18.14017 | K44: ='4.经营实际明细S'!K50 -> 20.260192 | L44: ='4.经营实际明细S'!L50 -> 0 | ... Q44: ='4.经营实际明细S'!Q50 -> 0 | R44: =SUM(F44:Q44) -> 65.939792 | S44: =基数汇总!S1244 -> 0 | T44: =基数汇总!R1244 -> 208.63875 | U44: =IF(S44>0,R44/S44-1,"") | V44: =E44=M44 -> FALSE | W44: 毛利
D45: 微居单 | E45: ='4.经营实际明细S'!E51 -> 0.83151394 | F45: ='4.经营实际明细S'!F51 -> 1.5070322 | G45: ='4.经营实际明细S'!G51 -> 0.46114087 | H45: ='4.经营实际明细S'!H51 -> 0.86158438 | I45: ='4.经营实际明细S'!I51 -> -0.0070494712 | J45: ='4.经营实际明细S'!J51 -> 1.0548735 | K45: ='4.经营实际明细S'!K51 -> 0.83151394 | L45: ='4.经营实际明细S'!L51 -> 0 | ... Q45: ='4.经营实际明细S'!Q51 -> 0 | R45: =SUM(F45:Q45) -> 4.7090954 | S45: =基数汇总!S1245 -> 0 | T45: =基数汇总!R1245 -> 41.284181 | U45: =IF(S45>0,R45/S45-1,"") | V45: =E45=M45 -> FALSE | W45: 毛利
C46: 按合同类型 | D46: 普通单 | E46: ='4.经营实际明细S'!E52-#REF! -> #REF! | F46: ='4.经营实际明细S'!F52-#REF! -> #REF! | G46: ='4.经营实际明细S'!G52-#REF! -> #REF! | H46: ='4.经营实际明细S'!H52-#REF! -> #REF! | I46: ='4.经营实际明细S'!I52-#REF! -> #REF! | J46: ='4.经营实际明细S'!J52-#REF! -> #REF! | K46: ='4.经营实际明细S'!K52-#REF! -> #REF! | L46: ='4.经营实际明细S'!L52-#REF! -> #REF! | ... T46: ='4.经营实际明细S'!T52-#REF! -> #REF! | U46: =IF(S46>0,R46/S46-1,"") -> #REF! | V46: =E46=M46 -> #REF! | W46: 毛利
D47: 样品单 | E47: ='4.经营实际明细S'!E53 -> 289.21134 | F47: ='4.经营实际明细S'!F53 -> 40.838096 | G47: ='4.经营实际明细S'!G53 -> 3.5285928 | H47: ='4.经营实际明细S'!H53 -> 521.86213 | I47: ='4.经营实际明细S'!I53 -> 161.48087 | J47: ='4.经营实际明细S'!J53 -> 270.45209 | K47: ='4.经营实际明细S'!K53 -> 289.21134 | L47: ='4.经营实际明细S'!L53 -> 0 | ... Q47: ='4.经营实际明细S'!Q53 -> 0 | R47: =SUM(F47:Q47) -> 1287.3731 | S47: =基数汇总!S1247 -> 0 | T47: =基数汇总!R1247 -> 0.0035627191 | U47: =IF(S47>0,R47/S47-1,"") | V47: =E47=M47 -> FALSE | W47: 毛利
D48: 遗留单 | E48: ='4.经营实际明细S'!E54 -> 13.301018 | F48: ='4.经营实际明细S'!F54 -> -9.182839 | G48: ='4.经营实际明细S'!G54 -> 17.742085 | H48: ='4.经营实际明细S'!H54 -> 8.3674128 | I48: ='4.经营实际明细S'!I54 -> 25.275822 | J48: ='4.经营实际明细S'!J54 -> 11.040922 | K48: ='4.经营实际明细S'!K54 -> 13.301018 | L48: ='4.经营实际明细S'!L54 -> 0 | ... Q48: ='4.经营实际明细S'!Q54 -> 0 | R48: =SUM(F48:Q48) -> 66.544422 | S48: =基数汇总!S1248 -> 0 | T48: =基数汇总!R1248 -> 1.5528302 | U48: =IF(S48>0,R48/S48-1,"") | V48: =E48=M48 -> FALSE | W48: 毛利
B49: 收入 | E49: ='4.经营实际明细S'!E55-#REF! -> #REF! | F49: ='4.经营实际明细S'!F55-#REF! -> #REF! | G49: ='4.经营实际明细S'!G55-#REF! -> #REF! | H49: ='4.经营实际明细S'!H55-#REF! -> #REF! | I49: ='4.经营实际明细S'!I55-#REF! -> #REF! | J49: ='4.经营实际明细S'!J55-#REF! -> #REF! | K49: ='4.经营实际明细S'!K55-#REF! -> #REF! | L49: ='4.经营实际明细S'!L55-#REF! -> #REF! | ... T49: ='4.经营实际明细S'!T55-#REF! -> #REF! | U49: =IF(S49>0,R49/S49-1,"") -> #REF! | V49: =E49=M49 -> #REF!
B50: 成本 | E50: ='4.经营实际明细S'!E56-#REF! -> #REF! | F50: ='4.经营实际明细S'!F56-#REF! -> #REF! | G50: ='4.经营实际明细S'!G56-#REF! -> #REF! | H50: ='4.经营实际明细S'!H56-#REF! -> #REF! | I50: ='4.经营实际明细S'!I56-#REF! -> #REF! | J50: ='4.经营实际明细S'!J56-#REF! -> #REF! | K50: ='4.经营实际明细S'!K56-#REF! -> #REF! | L50: ='4.经营实际明细S'!L56-#REF! -> #REF! | ... T50: ='4.经营实际明细S'!T56-#REF! -> #REF! | U50: =IF(S50>0,R50/S50-1,"") -> #REF! | V50: =E50=M50 -> #REF!
B51: 费用 | E51: ='4.经营实际明细S'!E57 -> 1050.6702 | F51: ='4.经营实际明细S'!F57 -> 205.89897 | G51: ='4.经营实际明细S'!G57 -> 119.8971 | H51: ='4.经营实际明细S'!H57 -> 493.88353 | I51: ='4.经营实际明细S'!I57 -> 632.18659 | J51: ='4.经营实际明细S'!J57 -> 1081.353 | K51: ='4.经营实际明细S'!K57 -> 1050.6702 | L51: ='4.经营实际明细S'!L57 -> 0 | ... Q51: ='4.经营实际明细S'!Q57 -> 0 | R51: =SUM(F51:Q51) -> 3583.8893 | S51: =基数汇总!S1251 -> 0 | T51: =基数汇总!R1251 -> 26.814454 | U51: =IF(S51>0,R51/S51-1,"") | V51: =E51=M51 -> FALSE
B52: 利润 | E52: =E49-E50-E51 -> #REF! | F52: =F49-F50-F51 -> #REF! | G52: =G49-G50-G51 -> #REF! | H52: =H49-H50-H51 -> #REF! | I52: =I49-I50-I51 -> #REF! | J52: =J49-J50-J51 -> #REF! | K52: =K49-K50-K51 -> #REF! | L52: =L49-L50-L51 -> #REF! | ... Q52: =Q49-Q50-Q51 -> #REF! | R52: =SUM(F52:Q52) -> #REF! | S52: =基数汇总!S1252 -> 0 | T52: =基数汇总!R1252 -> 3.4568117 | U52: =IF(S52>0,R52/S52-1,"") | V52: =E52=M52 -> #REF!
B53: 毛利率 | E53: =IF(E49>0,(E49-E50)/E49,"") -> #REF! | F53: =IF(F49>0,(F49-F50)/F49,"") -> #REF! | G53: =IF(G49>0,(G49-G50)/G49,"") -> #REF! | H53: =IF(H49>0,(H49-H50)/H49,"") -> #REF! | I53: =IF(I49>0,(I49-I50)/I49,"") -> #REF! | J53: =IF(J49>0,(J49-J50)/J49,"") -> #REF! | K53: =IF(K49>0,(K49-K50)/K49,"") -> #REF! | L53: =IF(L49>0,(L49-L50)/L49,"") -> #REF! | ... R53: =IF(R49>0,(R49-R50)/R49,"") -> #REF! | S53: =基数汇总!S1253 -> 0 | T53: =基数汇总!R1253 -> 0 | U53: =IF(R53<>0,R53-S53,"") -> #REF! | V53: =E53=M53 -> #REF!
B54: 费用率 | E54: =IF(E49>0,E51/E49,"") -> #REF! | F54: =IF(F49>0,F51/F49,"") -> #REF! | G54: =IF(G49>0,G51/G49,"") -> #REF! | H54: =IF(H49>0,H51/H49,"") -> #REF! | I54: =IF(I49>0,I51/I49,"") -> #REF! | J54: =IF(J49>0,J51/J49,"") -> #REF! | K54: =IF(K49>0,K51/K49,"") -> #REF! | L54: =IF(L49>0,L51/L49,"") -> #REF! | ... R54: =IF(R49>0,R51/R49,"") -> #REF! | S54: =基数汇总!S1254 -> 0 | T54: =基数汇总!R1254 -> 0 | U54: =IF(R54<>0,R54-S54,"") -> #REF! | V54: =E54=M54 -> #REF!
B55: 净利率 | E55: =IF(E49>0,E52/E49,"") -> #REF! | F55: =IF(F49>0,F52/F49,"") -> #REF! | G55: =IF(G49>0,G52/G49,"") -> #REF! | H55: =IF(H49>0,H52/H49,"") -> #REF! | I55: =IF(I49>0,I52/I49,"") -> #REF! | J55: =IF(J49>0,J52/J49,"") -> #REF! | K55: =IF(K49>0,K52/K49,"") -> #REF! | L55: =IF(L49>0,L52/L49,"") -> #REF! | ... R55: =IF(R49>0,R52/R49,"") -> #REF! | S55: =基数汇总!S1255 -> 0 | T55: =基数汇总!R1255 -> 0 | U55: =IF(R55<>0,R55-S55,"") -> #REF! | V55: =E55=M55 -> #REF!
A56: 橱柜经销二部 | B56: 收入 | C56: 按产品 | D56: 柜门 | E56: ='4.经营实际明细S'!E62 -> 2668.946 | F56: ='4.经营实际明细S'!F62 -> 532.1554 | G56: ='4.经营实际明细S'!G62 -> 278.992 | H56: ='4.经营实际明细S'!H62 -> 1229.6861 | I56: ='4.经营实际明细S'!I62 -> 1578.8273 | J56: ='4.经营实际明细S'!J62 -> 2315.6144 | K56: ='4.经营实际明细S'!K62 -> 2668.946 | L56: ='4.经营实际明细S'!L62 -> 0 | ... Q56: ='4.经营实际明细S'!Q62 -> 0 | R56: =SUM(F56:Q56) -> 8604.2212 | S56: =基数汇总!S1256 -> 0 | T56: =基数汇总!R1256 -> 0 | U56: =IF(S56>0,R56/S56-1,"") | V56: =E56=M56 -> FALSE | W56: 收入
D57: 台面 | E57: ='4.经营实际明细S'!E63 -> 1570.8782 | F57: ='4.经营实际明细S'!F63 -> 367.9927 | G57: ='4.经营实际明细S'!G63 -> 117.7673 | H57: ='4.经营实际明细S'!H63 -> 659.2127 | I57: ='4.经营实际明细S'!I63 -> 935.4922 | J57: ='4.经营实际明细S'!J63 -> 1316.6179 | K57: ='4.经营实际明细S'!K63 -> 1570.8782 | L57: ='4.经营实际明细S'!L63 -> 0 | ... Q57: ='4.经营实际明细S'!Q63 -> 0 | R57: =SUM(F57:Q57) -> 4967.961 | S57: =基数汇总!S1257 -> 0 | T57: =基数汇总!R1257 -> 0 | U57: =IF(S57>0,R57/S57-1,"") | V57: =E57=M57 -> FALSE | W57: 收入
D58: OEM烟灶 | E58: ='4.经营实际明细S'!E64 -> 959.10163 | F58: ='4.经营实际明细S'!F64 -> 129.76469 | G58: ='4.经营实际明细S'!G64 -> 36.06865 | H58: ='4.经营实际明细S'!H64 -> 264.38843 | I58: ='4.经营实际明细S'!I64 -> 389.81057 | J58: ='4.经营实际明细S'!J64 -> 1120.993 | K58: ='4.经营实际明细S'!K64 -> 959.10163 | L58: ='4.经营实际明细S'!L64 -> 0 | ... Q58: ='4.经营实际明细S'!Q64 -> 0 | R58: =SUM(F58:Q58) -> 2900.1269 | S58: =基数汇总!S1258 -> 0 | T58: =基数汇总!R1258 -> 0 | U58: =IF(S58>0,R58/S58-1,"") | V58: =E58=M58 -> FALSE | W58: 收入
D59: OEM其他 | E59: ='4.经营实际明细S'!E65-#REF! -> #REF! | F59: ='4.经营实际明细S'!F65-#REF! -> #REF! | G59: ='4.经营实际明细S'!G65-#REF! -> #REF! | H59: ='4.经营实际明细S'!H65-#REF! -> #REF! | I59: ='4.经营实际明细S'!I65-#REF! -> #REF! | J59: ='4.经营实际明细S'!J65-#REF! -> #REF! | K59: ='4.经营实际明细S'!K65-#REF! -> #REF! | L59: ='4.经营实际明细S'!L65-#REF! -> #REF! | ... T59: ='4.经营实际明细S'!T65-#REF! -> #REF! | U59: =IF(S59>0,R59/S59-1,"") -> #REF! | V59: =E59=M59 -> #REF! | W59: 收入
D60: 自制烟灶 | E60: ='4.经营实际明细S'!E66 -> 461.43511 | F60: ='4.经营实际明细S'!F66 -> 170.2523 | G60: ='4.经营实际明细S'!G66 -> 39.2131 | H60: ='4.经营实际明细S'!H66 -> 174.37625 | I60: ='4.经营实际明细S'!I66 -> 270.01981 | J60: ='4.经营实际明细S'!J66 -> 850.01298 | K60: ='4.经营实际明细S'!K66 -> 461.43511 | L60: ='4.经营实际明细S'!L66 -> 0 | ... Q60: ='4.经营实际明细S'!Q66 -> 0 | R60: =SUM(F60:Q60) -> 1965.3096 | S60: =基数汇总!S1260 -> 0 | T60: =基数汇总!R1260 -> 0 | U60: =IF(S60>0,R60/S60-1,"") | V60: =E60=M60 -> FALSE | W60: 收入
D61: 其他加收 | E61: ='4.经营实际明细S'!E69 -> 0.5987 | F61: ='4.经营实际明细S'!F69 -> 0.5147 | G61: ='4.经营实际明细S'!G69 -> 0.04 | H61: ='4.经营实际明细S'!H69 -> 0.6201 | I61: ='4.经营实际明细S'!I69 -> 0.4137 | J61: ='4.经营实际明细S'!J69 -> 0.6651 | K61: ='4.经营实际明细S'!K69 -> 0.5987 | L61: ='4.经营实际明细S'!L69 -> 0 | ... Q61: ='4.经营实际明细S'!Q69 -> 0 | R61: =SUM(F61:Q61) -> 2.8523 | S61: =基数汇总!S1261 -> 0 | T61: =基数汇总!R1261 -> 0 | U61: =IF(S61>0,R61/S61-1,"") | V61: =E61=M61 -> FALSE | W61: 收入
C62: 按订单类型 | D62: 常规单 | E62: ='4.经营实际明细S'!E70-#REF! -> #REF! | F62: ='4.经营实际明细S'!F70-#REF! -> #REF! | G62: ='4.经营实际明细S'!G70-#REF! -> #REF! | H62: ='4.经营实际明细S'!H70-#REF! -> #REF! | I62: ='4.经营实际明细S'!I70-#REF! -> #REF! | J62: ='4.经营实际明细S'!J70-#REF! -> #REF! | K62: ='4.经营实际明细S'!K70-#REF! -> #REF! | L62: ='4.经营实际明细S'!L70-#REF! -> #REF! | ... T62: ='4.经营实际明细S'!T70-#REF! -> #REF! | U62: =IF(S62>0,R62/S62-1,"") -> #REF! | V62: =E62=M62 -> #REF! | W62: 收入
D63: 家装单 | E63: ='4.经营实际明细S'!E71 -> 806.8066 | F63: ='4.经营实际明细S'!F71 -> 170.1867 | G63: ='4.经营实际明细S'!G71 -> 36.3121 | H63: ='4.经营实际明细S'!H71 -> 293.1203 | I63: ='4.经营实际明细S'!I71 -> 396.2519 | J63: ='4.经营实际明细S'!J71 -> 642.6283 | K63: ='4.经营实际明细S'!K71 -> 806.8066 | L63: ='4.经营实际明细S'!L71 -> 0 | ... Q63: ='4.经营实际明细S'!Q71 -> 0 | R63: =SUM(F63:Q63) -> 2345.3059 | S63: =基数汇总!S1263 -> 0 | T63: =基数汇总!R1263 -> 0 | U63: =IF(S63>0,R63/S63-1,"") | V63: =E63=M63 -> FALSE | W63: 收入
D64: 直供单 | E64: ='4.经营实际明细S'!E72 -> 1520.3701 | F64: ='4.经营实际明细S'!F72 -> 205.1521 | G64: ='4.经营实际明细S'!G72 -> 58.2698 | H64: ='4.经营实际明细S'!H72 -> 403.9339 | I64: ='4.经营实际明细S'!I72 -> 509.7619 | J64: ='4.经营实际明细S'!J72 -> 1100.8139 | K64: ='4.经营实际明细S'!K72 -> 1520.3701 | L64: ='4.经营实际明细S'!L72 -> 0 | ... Q64: ='4.经营实际明细S'!Q72 -> 0 | R64: =SUM(F64:Q64) -> 3798.3017 | S64: =基数汇总!S1264 -> 0 | T64: =基数汇总!R1264 -> 0 | U64: =IF(S64>0,R64/S64-1,"") | V64: =E64=M64 -> FALSE | W64: 收入
D65: 网销单 | E65: ='4.经营实际明细S'!E73 -> 0 | F65: ='4.经营实际明细S'!F73 -> 0 | G65: ='4.经营实际明细S'!G73 -> 0 | H65: ='4.经营实际明细S'!H73 -> 0 | I65: ='4.经营实际明细S'!I73 -> 0 | J65: ='4.经营实际明细S'!J73 -> 0 | K65: ='4.经营实际明细S'!K73 -> 0 | L65: ='4.经营实际明细S'!L73 -> 0 | ... Q65: ='4.经营实际明细S'!Q73 -> 0 | R65: =SUM(F65:Q65) -> 0 | S65: =基数汇总!S1265 -> 0 | T65: =基数汇总!R1265 -> 0 | U65: =IF(S65>0,R65/S65-1,"") | V65: =E65=M65 -> TRUE | W65: 收入
D66: 星居单 | E66: ='4.经营实际明细S'!E74 -> 116.4602 | F66: ='4.经营实际明细S'!F74 -> 9.8346 | G66: ='4.经营实际明细S'!G74 -> 1.1962 | H66: ='4.经营实际明细S'!H74 -> 25.926 | I66: ='4.经营实际明细S'!I74 -> 63.2841 | J66: ='4.经营实际明细S'!J74 -> 75.8273 | K66: ='4.经营实际明细S'!K74 -> 116.4602 | L66: ='4.经营实际明细S'!L74 -> 0 | ... Q66: ='4.经营实际明细S'!Q74 -> 0 | R66: =SUM(F66:Q66) -> 292.5284 | S66: =基数汇总!S1266 -> 0 | T66: =基数汇总!R1266 -> 0 | U66: =IF(S66>0,R66/S66-1,"") | V66: =E66=M66 -> FALSE | W66: 收入
D67: 微居单 | E67: ='4.经营实际明细S'!E75 -> 8.5563 | F67: ='4.经营实际明细S'!F75 -> 0.2515 | G67: ='4.经营实际明细S'!G75 -> 0 | H67: ='4.经营实际明细S'!H75 -> 0.3315 | I67: ='4.经营实际明细S'!I75 -> 0.4383 | J67: ='4.经营实际明细S'!J75 -> 8.9668 | K67: ='4.经营实际明细S'!K75 -> 8.5563 | L67: ='4.经营实际明细S'!L75 -> 0 | ... Q67: ='4.经营实际明细S'!Q75 -> 0 | R67: =SUM(F67:Q67) -> 18.5444 | S67: =基数汇总!S1267 -> 0 | T67: =基数汇总!R1267 -> 0 | U67: =IF(S67>0,R67/S67-1,"") | V67: =E67=M67 -> FALSE | W67: 收入
C68: 按合同类型 | D68: 普通单 | E68: ='4.经营实际明细S'!E76-#REF! -> #REF! | F68: ='4.经营实际明细S'!F76-#REF! -> #REF! | G68: ='4.经营实际明细S'!G76-#REF! -> #REF! | H68: ='4.经营实际明细S'!H76-#REF! -> #REF! | I68: ='4.经营实际明细S'!I76-#REF! -> #REF! | J68: ='4.经营实际明细S'!J76-#REF! -> #REF! | K68: ='4.经营实际明细S'!K76-#REF! -> #REF! | L68: ='4.经营实际明细S'!L76-#REF! -> #REF! | ... T68: ='4.经营实际明细S'!T76-#REF! -> #REF! | U68: =IF(S68>0,R68/S68-1,"") -> #REF! | V68: =E68=M68 -> #REF! | W68: 收入
D69: 样品单 | E69: ='4.经营实际明细S'!E77 -> 762.08281 | F69: ='4.经营实际明细S'!F77 -> 53.028959 | G69: ='4.经营实际明细S'!G77 -> 150.66562 | H69: ='4.经营实际明细S'!H77 -> 1114.5458 | I69: ='4.经营实际明细S'!I77 -> 586.75306 | J69: ='4.经营实际明细S'!J77 -> 926.22227 | K69: ='4.经营实际明细S'!K77 -> 762.08281 | L69: ='4.经营实际明细S'!L77 -> 0 | ... Q69: ='4.经营实际明细S'!Q77 -> 0 | R69: =SUM(F69:Q69) -> 3593.2986 | S69: =基数汇总!S1269 -> 0 | T69: =基数汇总!R1269 -> 355.8921 | U69: =IF(S69>0,R69/S69-1,"") | V69: =E69=M69 -> FALSE | W69: 收入
D70: 遗留单 | E70: ='4.经营实际明细S'!E78 -> 46.5092 | F70: ='4.经营实际明细S'!F78 -> 0 | G70: ='4.经营实际明细S'!G78 -> 42.4847 | H70: ='4.经营实际明细S'!H78 -> 34.3638 | I70: ='4.经营实际明细S'!I78 -> 57.77 | J70: ='4.经营实际明细S'!J78 -> 42.9805 | K70: ='4.经营实际明细S'!K78 -> 46.5092 | L70: ='4.经营实际明细S'!L78 -> 0 | ... Q70: ='4.经营实际明细S'!Q78 -> 0 | R70: =SUM(F70:Q70) -> 224.1082 | S70: =基数汇总!S1270 -> 0 | T70: =基数汇总!R1270 -> 0 | U70: =IF(S70>0,R70/S70-1,"") | V70: =E70=M70 -> FALSE | W70: 收入
B71: 成本 | C71: 按产品 | D71: 柜门 | E71: ='4.经营实际明细S'!E79 -> 1918.0998 | F71: ='4.经营实际明细S'!F79 -> 373.60411 | G71: ='4.经营实际明细S'!G79 -> 234.83429 | H71: ='4.经营实际明细S'!H79 -> 884.60631 | I71: ='4.经营实际明细S'!I79 -> 1140.4245 | J71: ='4.经营实际明细S'!J79 -> 1665.0405 | K71: ='4.经营实际明细S'!K79 -> 1918.0998 | L71: ='4.经营实际明细S'!L79 -> 0 | ... Q71: ='4.经营实际明细S'!Q79 -> 0 | R71: =SUM(F71:Q71) -> 6216.6095 | S71: =基数汇总!S1271 -> 0 | T71: =基数汇总!R1271 -> 0 | U71: =IF(S71>0,R71/S71-1,"") | V71: =E71=M71 -> FALSE | W71: 成本
D72: 台面 | E72: ='4.经营实际明细S'!E80 -> 1185.0059 | F72: ='4.经营实际明细S'!F80 -> 250.61086 | G72: ='4.经营实际明细S'!G80 -> 79.814233 | H72: ='4.经营实际明细S'!H80 -> 448.42026 | I72: ='4.经营实际明细S'!I80 -> 631.628 | J72: ='4.经营实际明细S'!J80 -> 898.10058 | K72: ='4.经营实际明细S'!K80 -> 1185.0059 | L72: ='4.经营实际明细S'!L80 -> 0 | ... Q72: ='4.经营实际明细S'!Q80 -> 0 | R72: =SUM(F72:Q72) -> 3493.5798 | S72: =基数汇总!S1272 -> 0 | T72: =基数汇总!R1272 -> 0 | U72: =IF(S72>0,R72/S72-1,"") | V72: =E72=M72 -> FALSE | W72: 成本
D73: OEM烟灶 | E73: ='4.经营实际明细S'!E81 -> 548.83543 | F73: ='4.经营实际明细S'!F81 -> 79.351789 | G73: ='4.经营实际明细S'!G81 -> 18.7755 | H73: ='4.经营实际明细S'!H81 -> 191.48991 | I73: ='4.经营实际明细S'!I81 -> 243.64325 | J73: ='4.经营实际明细S'!J81 -> 704.76236 | K73: ='4.经营实际明细S'!K81 -> 548.83543 | L73: ='4.经营实际明细S'!L81 -> 0 | ... Q73: ='4.经营实际明细S'!Q81 -> 0 | R73: =SUM(F73:Q73) -> 1786.8582 | S73: =基数汇总!S1273 -> 0 | T73: =基数汇总!R1273 -> 0 | U73: =IF(S73>0,R73/S73-1,"") | V73: =E73=M73 -> FALSE | W73: 成本
D74: OEM其他 | E74: ='4.经营实际明细S'!E82-#REF! -> #REF! | F74: ='4.经营实际明细S'!F82-#REF! -> #REF! | G74: ='4.经营实际明细S'!G82-#REF! -> #REF! | H74: ='4.经营实际明细S'!H82-#REF! -> #REF! | I74: ='4.经营实际明细S'!I82-#REF! -> #REF! | J74: ='4.经营实际明细S'!J82-#REF! -> #REF! | K74: ='4.经营实际明细S'!K82-#REF! -> #REF! | L74: ='4.经营实际明细S'!L82-#REF! -> #REF! | ... T74: ='4.经营实际明细S'!T82-#REF! -> #REF! | U74: =IF(S74>0,R74/S74-1,"") -> #REF! | V74: =E74=M74 -> #REF! | W74: 成本
D75: 自制烟灶 | E75: ='4.经营实际明细S'!E83 -> 242.11169 | F75: ='4.经营实际明细S'!F83 -> 94.6149 | G75: ='4.经营实际明细S'!G83 -> 21.2561 | H75: ='4.经营实际明细S'!H83 -> 89.4739 | I75: ='4.经营实际明细S'!I83 -> 132.55495 | J75: ='4.经营实际明细S'!J83 -> 455.45883 | K75: ='4.经营实际明细S'!K83 -> 242.11169 | L75: ='4.经营实际明细S'!L83 -> 0 | ... Q75: ='4.经营实际明细S'!Q83 -> 0 | R75: =SUM(F75:Q75) -> 1035.4704 | S75: =基数汇总!S1275 -> 0 | T75: =基数汇总!R1275 -> 0 | U75: =IF(S75>0,R75/S75-1,"") | V75: =E75=M75 -> FALSE | W75: 成本
D76: 其他加收 | E76: ='4.经营实际明细S'!E86 -> 0 | F76: ='4.经营实际明细S'!F86 -> 0 | G76: ='4.经营实际明细S'!G86 -> 0 | H76: ='4.经营实际明细S'!H86 -> 0 | I76: ='4.经营实际明细S'!I86 -> 0 | J76: ='4.经营实际明细S'!J86 -> 0 | K76: ='4.经营实际明细S'!K86 -> 0 | L76: ='4.经营实际明细S'!L86 -> 0 | ... Q76: ='4.经营实际明细S'!Q86 -> 0 | R76: =SUM(F76:Q76) -> 0 | S76: =基数汇总!S1276 -> 0 | T76: =基数汇总!R1276 -> 0 | U76: =IF(S76>0,R76/S76-1,"") | V76: =E76=M76 -> TRUE | W76: 成本
C77: 按订单类型 | D77: 常规单 | E77: ='4.经营实际明细S'!E87-#REF! -> #REF! | F77: ='4.经营实际明细S'!F87-#REF! -> #REF! | G77: ='4.经营实际明细S'!G87-#REF! -> #REF! | H77: ='4.经营实际明细S'!H87-#REF! -> #REF! | I77: ='4.经营实际明细S'!I87-#REF! -> #REF! | J77: ='4.经营实际明细S'!J87-#REF! -> #REF! | K77: ='4.经营实际明细S'!K87-#REF! -> #REF! | L77: ='4.经营实际明细S'!L87-#REF! -> #REF! | ... T77: ='4.经营实际明细S'!T87-#REF! -> #REF! | U77: =IF(S77>0,R77/S77-1,"") -> #REF! | V77: =E77=M77 -> #REF! | W77: 成本
D78: 家装单 | E78: ='4.经营实际明细S'!E88 -> 633.14427 | F78: ='4.经营实际明细S'!F88 -> 121.50217 | G78: ='4.经营实际明细S'!G88 -> 25.539012 | H78: ='4.经营实际明细S'!H88 -> 209.60945 | I78: ='4.经营实际明细S'!I88 -> 295.41728 | J78: ='4.经营实际明细S'!J88 -> 466.6094 | K78: ='4.经营实际明细S'!K88 -> 633.14427 | L78: ='4.经营实际明细S'!L88 -> 0 | ... Q78: ='4.经营实际明细S'!Q88 -> 0 | R78: =SUM(F78:Q78) -> 1751.8216 | S78: =基数汇总!S1278 -> 0 | T78: =基数汇总!R1278 -> 0 | U78: =IF(S78>0,R78/S78-1,"") | V78: =E78=M78 -> FALSE | W78: 成本
D79: 直供单 | E79: ='4.经营实际明细S'!E89 -> 1231.382 | F79: ='4.经营实际明细S'!F89 -> 138.48434 | G79: ='4.经营实际明细S'!G89 -> 39.005874 | H79: ='4.经营实际明细S'!H89 -> 274.42479 | I79: ='4.经营实际明细S'!I89 -> 350.7828 | J79: ='4.经营实际明细S'!J89 -> 755.44966 | K79: ='4.经营实际明细S'!K89 -> 1231.382 | L79: ='4.经营实际明细S'!L89 -> 0 | ... Q79: ='4.经营实际明细S'!Q89 -> 0 | R79: =SUM(F79:Q79) -> 2789.5294 | S79: =基数汇总!S1279 -> 0 | T79: =基数汇总!R1279 -> 0 | U79: =IF(S79>0,R79/S79-1,"") | V79: =E79=M79 -> FALSE | W79: 成本
D80: 网销单 | E80: ='4.经营实际明细S'!E90 -> 0 | F80: ='4.经营实际明细S'!F90 -> 0 | G80: ='4.经营实际明细S'!G90 -> 0 | H80: ='4.经营实际明细S'!H90 -> 0 | I80: ='4.经营实际明细S'!I90 -> 0 | J80: ='4.经营实际明细S'!J90 -> 0 | K80: ='4.经营实际明细S'!K90 -> 0 | L80: ='4.经营实际明细S'!L90 -> 0 | ... Q80: ='4.经营实际明细S'!Q90 -> 0 | R80: =SUM(F80:Q80) -> 0 | S80: =基数汇总!S1280 -> 0 | T80: =基数汇总!R1280 -> 0 | U80: =IF(S80>0,R80/S80-1,"") | V80: =E80=M80 -> TRUE | W80: 成本
D81: 星居单 | E81: ='4.经营实际明细S'!E91 -> 80.920148 | F81: ='4.经营实际明细S'!F91 -> 6.4673057 | G81: ='4.经营实际明细S'!G91 -> 0.7714651 | H81: ='4.经营实际明细S'!H91 -> 17.163711 | I81: ='4.经营实际明细S'!I91 -> 41.637061 | J81: ='4.经营实际明细S'!J91 -> 53.039674 | K81: ='4.经营实际明细S'!K91 -> 80.920148 | L81: ='4.经营实际明细S'!L91 -> 0 | ... Q81: ='4.经营实际明细S'!Q91 -> 0 | R81: =SUM(F81:Q81) -> 199.99936 | S81: =基数汇总!S1281 -> 0 | T81: =基数汇总!R1281 -> 0 | U81: =IF(S81>0,R81/S81-1,"") | V81: =E81=M81 -> FALSE | W81: 成本
D82: 微居单 | E82: ='4.经营实际明细S'!E92 -> 6.9647238 | F82: ='4.经营实际明细S'!F92 -> 0.17990005 | G82: ='4.经营实际明细S'!G92 -> 0 | H82: ='4.经营实际明细S'!H92 -> 0.087567583 | I82: ='4.经营实际明细S'!I92 -> 0.32930011 | J82: ='4.经营实际明细S'!J92 -> 6.5666286 | K82: ='4.经营实际明细S'!K92 -> 6.9647238 | L82: ='4.经营实际明细S'!L92 -> 0 | ... Q82: ='4.经营实际明细S'!Q92 -> 0 | R82: =SUM(F82:Q82) -> 14.12812 | S82: =基数汇总!S1282 -> 0 | T82: =基数汇总!R1282 -> 0 | U82: =IF(S82>0,R82/S82-1,"") | V82: =E82=M82 -> FALSE | W82: 成本
C83: 按合同类型 | D83: 普通单 | E83: ='4.经营实际明细S'!E93-#REF! -> #REF! | F83: ='4.经营实际明细S'!F93-#REF! -> #REF! | G83: ='4.经营实际明细S'!G93-#REF! -> #REF! | H83: ='4.经营实际明细S'!H93-#REF! -> #REF! | I83: ='4.经营实际明细S'!I93-#REF! -> #REF! | J83: ='4.经营实际明细S'!J93-#REF! -> #REF! | K83: ='4.经营实际明细S'!K93-#REF! -> #REF! | L83: ='4.经营实际明细S'!L93-#REF! -> #REF! | ... T83: ='4.经营实际明细S'!T93-#REF! -> #REF! | U83: =IF(S83>0,R83/S83-1,"") -> #REF! | V83: =E83=M83 -> #REF! | W83: 成本
D84: 样品单 | E84: ='4.经营实际明细S'!E94 -> 571.543 | F84: ='4.经营实际明细S'!F94 -> 38.941423 | G84: ='4.经营实际明细S'!G94 -> 144.41537 | H84: ='4.经营实际明细S'!H94 -> 762.16148 | I84: ='4.经营实际明细S'!I94 -> 435.62828 | J84: ='4.经营实际明细S'!J94 -> 704.19697 | K84: ='4.经营实际明细S'!K94 -> 571.543 | L84: ='4.经营实际明细S'!L94 -> 0 | ... Q84: ='4.经营实际明细S'!Q94 -> 0 | R84: =SUM(F84:Q84) -> 2656.8865 | S84: =基数汇总!S1284 -> 0 | T84: =基数汇总!R1284 -> 0 | U84: =IF(S84>0,R84/S84-1,"") | V84: =E84=M84 -> FALSE | W84: 成本
D85: 遗留单 | E85: ='4.经营实际明细S'!E95 -> 36.071277 | F85: ='4.经营实际明细S'!F95 -> 7.04873 | G85: ='4.经营实际明细S'!G95 -> 22.880422 | H85: ='4.经营实际明细S'!H95 -> 31.773359 | I85: ='4.经营实际明细S'!I95 -> 35.701074 | J85: ='4.经营实际明细S'!J95 -> 32.683497 | K85: ='4.经营实际明细S'!K95 -> 36.071277 | L85: ='4.经营实际明细S'!L95 -> 0 | ... Q85: ='4.经营实际明细S'!Q95 -> 0 | R85: =SUM(F85:Q85) -> 166.15836 | S85: =基数汇总!S1285 -> 0 | T85: =基数汇总!R1285 -> 0 | U85: =IF(S85>0,R85/S85-1,"") | V85: =E85=M85 -> FALSE | W85: 成本
B86: 毛利 | C86: 按产品 | D86: 柜门 | E86: ='4.经营实际明细S'!E96 -> 750.84617 | F86: ='4.经营实际明细S'!F96 -> 158.55129 | G86: ='4.经营实际明细S'!G96 -> 44.15771 | H86: ='4.经营实际明细S'!H96 -> 345.07979 | I86: ='4.经营实际明细S'!I96 -> 438.40285 | J86: ='4.经营实际明细S'!J96 -> 650.57385 | K86: ='4.经营实际明细S'!K96 -> 750.84617 | L86: ='4.经营实际明细S'!L96 -> 0 | ... Q86: ='4.经营实际明细S'!Q96 -> 0 | R86: =SUM(F86:Q86) -> 2387.6117 | S86: =基数汇总!S1286 -> 0 | T86: =基数汇总!R1286 -> 0 | U86: =IF(S86>0,R86/S86-1,"") | V86: =E86=M86 -> FALSE | W86: 毛利
D87: 台面 | E87: ='4.经营实际明细S'!E97 -> 385.87235 | F87: ='4.经营实际明细S'!F97 -> 117.38184 | G87: ='4.经营实际明细S'!G97 -> 37.953067 | H87: ='4.经营实际明细S'!H97 -> 210.79244 | I87: ='4.经营实际明细S'!I97 -> 303.8642 | J87: ='4.经营实际明细S'!J97 -> 418.51732 | K87: ='4.经营实际明细S'!K97 -> 385.87235 | L87: ='4.经营实际明细S'!L97 -> 0 | ... Q87: ='4.经营实际明细S'!Q97 -> 0 | R87: =SUM(F87:Q87) -> 1474.3812 | S87: =基数汇总!S1287 -> 0 | T87: =基数汇总!R1287 -> 0 | U87: =IF(S87>0,R87/S87-1,"") | V87: =E87=M87 -> FALSE | W87: 毛利
D88: OEM烟灶 | E88: ='4.经营实际明细S'!E98 -> 410.2662 | F88: ='4.经营实际明细S'!F98 -> 50.412902 | G88: ='4.经营实际明细S'!G98 -> 17.29315 | H88: ='4.经营实际明细S'!H98 -> 72.898522 | I88: ='4.经营实际明细S'!I98 -> 146.16732 | J88: ='4.经营实际明细S'!J98 -> 416.23061 | K88: ='4.经营实际明细S'!K98 -> 410.2662 | L88: ='4.经营实际明细S'!L98 -> 0 | ... Q88: ='4.经营实际明细S'!Q98 -> 0 | R88: =SUM(F88:Q88) -> 1113.2687 | S88: =基数汇总!S1288 -> 0 | T88: =基数汇总!R1288 -> 0 | U88: =IF(S88>0,R88/S88-1,"") | V88: =E88=M88 -> FALSE | W88: 毛利
D89: OEM其他 | E89: ='4.经营实际明细S'!E99-#REF! -> #REF! | F89: ='4.经营实际明细S'!F99-#REF! -> #REF! | G89: ='4.经营实际明细S'!G99-#REF! -> #REF! | H89: ='4.经营实际明细S'!H99-#REF! -> #REF! | I89: ='4.经营实际明细S'!I99-#REF! -> #REF! | J89: ='4.经营实际明细S'!J99-#REF! -> #REF! | K89: ='4.经营实际明细S'!K99-#REF! -> #REF! | L89: ='4.经营实际明细S'!L99-#REF! -> #REF! | ... T89: ='4.经营实际明细S'!T99-#REF! -> #REF! | U89: =IF(S89>0,R89/S89-1,"") -> #REF! | V89: =E89=M89 -> #REF! | W89: 毛利
D90: 自制烟灶 | E90: ='4.经营实际明细S'!E100 -> 219.32342 | F90: ='4.经营实际明细S'!F100 -> 75.6374 | G90: ='4.经营实际明细S'!G100 -> 17.957 | H90: ='4.经营实际明细S'!H100 -> 84.90235 | I90: ='4.经营实际明细S'!I100 -> 137.46486 | J90: ='4.经营实际明细S'!J100 -> 394.55415 | K90: ='4.经营实际明细S'!K100 -> 219.32342 | L90: ='4.经营实际明细S'!L100 -> 0 | ... Q90: ='4.经营实际明细S'!Q100 -> 0 | R90: =SUM(F90:Q90) -> 929.83918 | S90: =基数汇总!S1290 -> 0 | T90: =基数汇总!R1290 -> 0 | U90: =IF(S90>0,R90/S90-1,"") | V90: =E90=M90 -> FALSE | W90: 毛利
D91: 其他加收 | E91: ='4.经营实际明细S'!E103 -> 0.5987 | F91: ='4.经营实际明细S'!F103 -> 0.5147 | G91: ='4.经营实际明细S'!G103 -> 0.04 | H91: ='4.经营实际明细S'!H103 -> 0.6201 | I91: ='4.经营实际明细S'!I103 -> 0.4137 | J91: ='4.经营实际明细S'!J103 -> 0.6651 | K91: ='4.经营实际明细S'!K103 -> 0.5987 | L91: ='4.经营实际明细S'!L103 -> 0 | ... Q91: ='4.经营实际明细S'!Q103 -> 0 | R91: =SUM(F91:Q91) -> 2.8523 | S91: =基数汇总!S1291 -> 0 | T91: =基数汇总!R1291 -> 146.66517 | U91: =IF(S91>0,R91/S91-1,"") | V91: =E91=M91 -> FALSE | W91: 毛利
C92: 按订单类型 | D92: 常规单 | E92: ='4.经营实际明细S'!E104-#REF! -> #REF! | F92: ='4.经营实际明细S'!F104-#REF! -> #REF! | G92: ='4.经营实际明细S'!G104-#REF! -> #REF! | H92: ='4.经营实际明细S'!H104-#REF! -> #REF! | I92: ='4.经营实际明细S'!I104-#REF! -> #REF! | J92: ='4.经营实际明细S'!J104-#REF! -> #REF! | K92: ='4.经营实际明细S'!K104-#REF! -> #REF! | L92: ='4.经营实际明细S'!L104-#REF! -> #REF! | ... T92: ='4.经营实际明细S'!T104-#REF! -> #REF! | U92: =IF(S92>0,R92/S92-1,"") -> #REF! | V92: =E92=M92 -> #REF! | W92: 毛利
D93: 家装单 | E93: ='4.经营实际明细S'!E105 -> 173.66233 | F93: ='4.经营实际明细S'!F105 -> 48.684529 | G93: ='4.经营实际明细S'!G105 -> 10.773088 | H93: ='4.经营实际明细S'!H105 -> 83.510852 | I93: ='4.经营实际明细S'!I105 -> 100.83462 | J93: ='4.经营实际明细S'!J105 -> 176.0189 | K93: ='4.经营实际明细S'!K105 -> 173.66233 | L93: ='4.经营实际明细S'!L105 -> 0 | ... Q93: ='4.经营实际明细S'!Q105 -> 0 | R93: =SUM(F93:Q93) -> 593.48432 | S93: =基数汇总!S1293 -> 0 | T93: =基数汇总!R1293 -> 0 | U93: =IF(S93>0,R93/S93-1,"") | V93: =E93=M93 -> FALSE | W93: 毛利
D94: 直供单 | E94: ='4.经营实际明细S'!E106 -> 288.98815 | F94: ='4.经营实际明细S'!F106 -> 66.667762 | G94: ='4.经营实际明细S'!G106 -> 19.263926 | H94: ='4.经营实际明细S'!H106 -> 129.50911 | I94: ='4.经营实际明细S'!I106 -> 158.9791 | J94: ='4.经营实际明细S'!J106 -> 345.36424 | K94: ='4.经营实际明细S'!K106 -> 288.98815 | L94: ='4.经营实际明细S'!L106 -> 0 | ... Q94: ='4.经营实际明细S'!Q106 -> 0 | R94: =SUM(F94:Q94) -> 1008.7723 | S94: =基数汇总!S1294 -> 0 | T94: =基数汇总!R1294 -> 0 | U94: =IF(S94>0,R94/S94-1,"") | V94: =E94=M94 -> FALSE | W94: 毛利
D95: 网销单 | E95: ='4.经营实际明细S'!E107 -> 0 | F95: ='4.经营实际明细S'!F107 -> 0 | G95: ='4.经营实际明细S'!G107 -> 0 | H95: ='4.经营实际明细S'!H107 -> 0 | I95: ='4.经营实际明细S'!I107 -> 0 | J95: ='4.经营实际明细S'!J107 -> 0 | K95: ='4.经营实际明细S'!K107 -> 0 | L95: ='4.经营实际明细S'!L107 -> 0 | ... Q95: ='4.经营实际明细S'!Q107 -> 0 | R95: =SUM(F95:Q95) -> 0 | S95: =基数汇总!S1295 -> 0 | T95: =基数汇总!R1295 -> 0 | U95: =IF(S95>0,R95/S95-1,"") | V95: =E95=M95 -> TRUE | W95: 毛利
D96: 星居单 | E96: ='4.经营实际明细S'!E108 -> 35.540052 | F96: ='4.经营实际明细S'!F108 -> 3.3672943 | G96: ='4.经营实际明细S'!G108 -> 0.4247349 | H96: ='4.经营实际明细S'!H108 -> 8.7622889 | I96: ='4.经营实际明细S'!I108 -> 21.647039 | J96: ='4.经营实际明细S'!J108 -> 22.787626 | K96: ='4.经营实际明细S'!K108 -> 35.540052 | L96: ='4.经营实际明细S'!L108 -> 0 | ... Q96: ='4.经营实际明细S'!Q108 -> 0 | R96: =SUM(F96:Q96) -> 92.529035 | S96: =基数汇总!S1296 -> 0 | T96: =基数汇总!R1296 -> 0 | U96: =IF(S96>0,R96/S96-1,"") | V96: =E96=M96 -> FALSE | W96: 毛利
D97: 微居单 | E97: ='4.经营实际明细S'!E109 -> 1.5915762 | F97: ='4.经营实际明细S'!F109 -> 0.071599952 | G97: ='4.经营实际明细S'!G109 -> 0 | H97: ='4.经营实际明细S'!H109 -> 0.24393242 | I97: ='4.经营实际明细S'!I109 -> 0.10899989 | J97: ='4.经营实际明细S'!J109 -> 2.4001714 | K97: ='4.经营实际明细S'!K109 -> 1.5915762 | L97: ='4.经营实际明细S'!L109 -> 0 | ... Q97: ='4.经营实际明细S'!Q109 -> 0 | R97: =SUM(F97:Q97) -> 4.4162798 | S97: =基数汇总!S1297 -> 0 | T97: =基数汇总!R1297 -> 142.74679 | U97: =IF(S97>0,R97/S97-1,"") | V97: =E97=M97 -> FALSE | W97: 毛利
C98: 按合同类型 | D98: 普通单 | E98: ='4.经营实际明细S'!E110-#REF! -> #REF! | F98: ='4.经营实际明细S'!F110-#REF! -> #REF! | G98: ='4.经营实际明细S'!G110-#REF! -> #REF! | H98: ='4.经营实际明细S'!H110-#REF! -> #REF! | I98: ='4.经营实际明细S'!I110-#REF! -> #REF! | J98: ='4.经营实际明细S'!J110-#REF! -> #REF! | K98: ='4.经营实际明细S'!K110-#REF! -> #REF! | L98: ='4.经营实际明细S'!L110-#REF! -> #REF! | ... T98: ='4.经营实际明细S'!T110-#REF! -> #REF! | U98: =IF(S98>0,R98/S98-1,"") -> #REF! | V98: =E98=M98 -> #REF! | W98: 毛利
D99: 样品单 | E99: ='4.经营实际明细S'!E111 -> 190.53981 | F99: ='4.经营实际明细S'!F111 -> 14.087536 | G99: ='4.经营实际明细S'!G111 -> 6.2502467 | H99: ='4.经营实际明细S'!H111 -> 352.38436 | I99: ='4.经营实际明细S'!I111 -> 151.12479 | J99: ='4.经营实际明细S'!J111 -> 222.0253 | K99: ='4.经营实际明细S'!K111 -> 190.53981 | L99: ='4.经营实际明细S'!L111 -> 0 | ... Q99: ='4.经营实际明细S'!Q111 -> 0 | R99: =SUM(F99:Q99) -> 936.41204 | S99: =基数汇总!S1299 -> 0 | T99: =基数汇总!R1299 -> 60.829181 | U99: =IF(S99>0,R99/S99-1,"") | V99: =E99=M99 -> FALSE | W99: 毛利
D100: 遗留单 | E100: ='4.经营实际明细S'!E112 -> 10.437923 | F100: ='4.经营实际明细S'!F112 -> -7.04873 | G100: ='4.经营实际明细S'!G112 -> 19.604278 | H100: ='4.经营实际明细S'!H112 -> 2.5904406 | I100: ='4.经营实际明细S'!I112 -> 22.068926 | J100: ='4.经营实际明细S'!J112 -> 10.297003 | K100: ='4.经营实际明细S'!K112 -> 10.437923 | L100: ='4.经营实际明细S'!L112 -> 0 | ... Q100: ='4.经营实际明细S'!Q112 -> 0 | R100: =SUM(F100:Q100) -> 57.94984 | S100: =基数汇总!S1300 -> 0 | T100: =基数汇总!R1300 -> 0.0064749928 | U100: =IF(S100>0,R100/S100-1,"") | V100: =E100=M100 -> FALSE | W100: 毛利
...

Sheet 本年累计S(集团取数)
A1: 2019年橱柜营销线本年累计报表 | V1: 返回目录 | W1: 研发中心费用分摊 | X1: 分摊率 | Y1: 分摊额
R2: 单位：万元 | X2: 0.0008 | Y2: =X2*E454 -> #REF! | Z2: =Y2*10000 -> #REF!
A3: 部门 | B3: 项目 | C3: 口径 | D3: 类别 | E3: 本月 | F3: 1月 | G3: 2月 | H3: 3月 | I3: 4月 | J3: 5月 | K3: 6月 | L3: 7月 | M3: 8月 | N3: 9月 | O3: 10月 | P3: 11月 | Q3: 12月 | R3: 本年累计 | S3: 上年同期 | T3: 上年全年 | U3: 增长率
A4: 橱柜经销一部 | B4: 收入 | C4: 按产品 | D4: 柜门 | E4: =#REF! -> #REF! | F4: 882.7972 | G4: =E4 -> #REF! | R4: =SUM(F4:Q4) -> #REF! | S4: =基数汇总!S5 -> 8008.3663 | T4: =基数汇总!R5 -> 19479.117 | U4: =IF(S4>0,R4/S4-1,"") -> #REF! | V4: =E4=M4 -> #REF!
D5: 台面 | E5: =#REF! -> #REF! | F5: 494.974 | G5: =E5 -> #REF! | R5: =SUM(F5:Q5) -> #REF! | S5: =基数汇总!S6 -> 4772.9023 | T5: =基数汇总!R6 -> 8126.7205 | U5: =IF(S5>0,R5/S5-1,"") -> #REF! | V5: =E5=M5 -> #REF!
D6: OEM烟灶 | E6: =#REF! -> #REF! | F6: 150.52394 | G6: =E6 -> #REF! | R6: =SUM(F6:Q6) -> #REF! | S6: =基数汇总!S7 -> 5848.0713 | T6: =基数汇总!R7 -> 13642.732 | U6: =IF(S6>0,R6/S6-1,"") -> #REF! | V6: =E6=M6 -> #REF!
D7: OEM其他 | E7: =#REF! -> #REF! | F7: 304.39522 | G7: =E7 -> #REF! | R7: =SUM(F7:Q7) -> #REF! | S7: =基数汇总!S8 -> 2422.6895 | T7: =基数汇总!R8 -> 6179.2907 | U7: =IF(S7>0,R7/S7-1,"") -> #REF! | V7: =E7=M7 -> #REF!
D8: 自制烟灶 | E8: =#REF! -> #REF! | F8: 109.2042 | G8: =E8 -> #REF! | R8: =SUM(F8:Q8) -> #REF! | S8: =基数汇总!S9 -> 19.3668 | T8: =基数汇总!R9 -> 43.6799 | U8: =IF(S8>0,R8/S8-1,"") -> #REF! | V8: =E8=M8 -> #REF!
D9: 其他加收 | E9: =#REF! -> #REF! | F9: 1.1902 | G9: =E9 -> #REF! | R9: =SUM(F9:Q9) -> #REF! | S9: =基数汇总!S10 -> 27296.78 | T9: =基数汇总!R10 -> 63081.624 | U9: =IF(S9>0,R9/S9-1,"") -> #REF! | V9: =E9=M9 -> #REF!
C10: 按订单类型 | D10: 常规单 | E10: =#REF! -> #REF! | F10: 1586.4041 | G10: =E10 -> #REF! | R10: =SUM(F10:Q10) -> #REF! | S10: =基数汇总!S11 -> 2410.2793 | T10: =基数汇总!R11 -> 5820.3908 | U10: =IF(S10>0,R10/S10-1,"") -> #REF! | V10: =E10=M10 -> #REF!
D11: 家装单 | E11: =#REF! -> #REF! | F11: 142.4542 | G11: =E11 -> #REF! | R11: =SUM(F11:Q11) -> #REF! | S11: =基数汇总!S12 -> 5188.4703 | T11: =基数汇总!R12 -> 13052.772 | U11: =IF(S11>0,R11/S11-1,"") -> #REF! | V11: =E11=M11 -> #REF!
D12: 直供单 | E12: =#REF! -> #REF! | F12: 195.3872 | G12: =E12 -> #REF! | R12: =SUM(F12:Q12) -> #REF! | S12: =基数汇总!S13 -> 2.8317 | T12: =基数汇总!R13 -> 2.8317 | U12: =IF(S12>0,R12/S12-1,"") -> #REF! | V12: =E12=M12 -> #REF!
D13: 网销单 | E13: =#REF! -> #REF! | F13: 0 | G13: =E13 -> #REF! | R13: =SUM(F13:Q13) -> #REF! | S13: =基数汇总!S14 -> 84.3052 | T13: =基数汇总!R14 -> 487.9132 | U13: =IF(S13>0,R13/S13-1,"") -> #REF! | V13: =E13=M13 -> #REF!
D14: 星居单 | E14: =#REF! -> #REF! | F14: 11.9667 | G14: =E14 -> #REF! | R14: =SUM(F14:Q14) -> #REF! | S14: =基数汇总!S15 -> 1.2518 | T14: =基数汇总!R15 -> 31.3682 | U14: =IF(S14>0,R14/S14-1,"") -> #REF! | V14: =E14=M14 -> #REF!
D15: 微居单 | E15: =#REF! -> #REF! | F15: 6.8726 | G15: =E15 -> #REF! | R15: =SUM(F15:Q15) -> #REF! | S15: =基数汇总!S16 -> 30665.388 | T15: =基数汇总!R16 -> 72663.356 | U15: =IF(S15>0,R15/S15-1,"") -> #REF! | V15: =E15=M15 -> #REF!
C16: 按合同类型 | D16: 普通单 | E16: =#REF! -> #REF! | F16: 1757.8627 | G16: =E16 -> #REF! | R16: =SUM(F16:Q16) -> #REF! | S16: =基数汇总!S17 -> 3964.233 | T16: =基数汇总!R17 -> 9004.57 | U16: =IF(S16>0,R16/S16-1,"") -> #REF! | V16: =E16=M16 -> #REF!
D17: 样品单 | E17: =#REF! -> #REF! | F17: 185.22204 | G17: =E17 -> #REF! | R17: =SUM(F17:Q17) -> #REF! | S17: =基数汇总!S18 -> 354.2968 | T17: =基数汇总!R18 -> 808.9736 | U17: =IF(S17>0,R17/S17-1,"") -> #REF! | V17: =E17=M17 -> #REF!
D18: 遗留单 | E18: =#REF! -> #REF! | F18: 0 | G18: =E18 -> #REF! | R18: =SUM(F18:Q18) -> #REF! | S18: =基数汇总!S19 -> 10238.253 | T18: =基数汇总!R19 -> 25159.912 | U18: =IF(S18>0,R18/S18-1,"") -> #REF! | V18: =E18=M18 -> #REF!
B19: 成本 | C19: 按产品 | D19: 柜门 | E19: =#REF! -> #REF! | F19: 766.52129 | G19: =E19 -> #REF! | R19: =SUM(F19:Q19) -> #REF! | S19: =基数汇总!S20 -> 5893.369 | T19: =基数汇总!R20 -> 14003.794 | U19: =IF(S19>0,R19/S19-1,"") -> #REF! | V19: =E19=M19 -> #REF!
D20: 台面 | E20: =#REF! -> #REF! | F20: 424.7822 | G20: =E20 -> #REF! | R20: =SUM(F20:Q20) -> #REF! | S20: =基数汇总!S21 -> 3136.8449 | T20: =基数汇总!R21 -> 5425.4738 | U20: =IF(S20>0,R20/S20-1,"") -> #REF! | V20: =E20=M20 -> #REF!
D21: OEM烟灶 | E21: =#REF! -> #REF! | F21: 90.785403 | G21: =E21 -> #REF! | R21: =SUM(F21:Q21) -> #REF! | S21: =基数汇总!S22 -> 3433.1215 | T21: =基数汇总!R22 -> 8348.9275 | U21: =IF(S21>0,R21/S21-1,"") -> #REF! | V21: =E21=M21 -> #REF!
D22: OEM其他 | E22: =#REF! -> #REF! | F22: 183.52541 | G22: =E22 -> #REF! | R22: =SUM(F22:Q22) -> #REF! | S22: =基数汇总!S23 -> 1337.6848 | T22: =基数汇总!R23 -> 3464.7832 | U22: =IF(S22>0,R22/S22-1,"") -> #REF! | V22: =E22=M22 -> #REF!
D23: 自制烟灶 | E23: =#REF! -> #REF! | F23: 58.5815 | G23: =E23 -> #REF! | R23: =SUM(F23:Q23) -> #REF! | S23: =基数汇总!S24 -> 0 | T23: =基数汇总!R24 -> 0 | U23: =IF(S23>0,R23/S23-1,"") | V23: =E23=M23 -> #REF!
D24: 其他加收 | E24: =#REF! -> #REF! | F24: 0 | G24: =E24 -> #REF! | R24: =SUM(F24:Q24) -> #REF! | S24: =基数汇总!S25 -> 17980.048 | T24: =基数汇总!R25 -> 41649.545 | U24: =IF(S24>0,R24/S24-1,"") -> #REF! | V24: =E24=M24 -> #REF!
C25: 按订单类型 | D25: 常规单 | E25: =#REF! -> #REF! | F25: 1215.9836 | G25: =E25 -> #REF! | R25: =SUM(F25:Q25) -> #REF! | S25: =基数汇总!S26 -> 2065.6359 | T25: =基数汇总!R26 -> 4768.7604 | U25: =IF(S25>0,R25/S25-1,"") -> #REF! | V25: =E25=M25 -> #REF!
D26: 家装单 | E26: =#REF! -> #REF! | F26: 123.92445 | G26: =E26 -> #REF! | R26: =SUM(F26:Q26) -> #REF! | S26: =基数汇总!S27 -> 3924.6917 | T26: =基数汇总!R27 -> 9595.2209 | U26: =IF(S26>0,R26/S26-1,"") -> #REF! | V26: =E26=M26 -> #REF!
D27: 直供单 | E27: =#REF! -> #REF! | F27: 167.44724 | G27: =E27 -> #REF! | R27: =SUM(F27:Q27) -> #REF! | S27: =基数汇总!S28 -> 2.1537271 | T27: =基数汇总!R28 -> 2.1537271 | U27: =IF(S27>0,R27/S27-1,"") -> #REF! | V27: =E27=M27 -> #REF!
D28: 网销单 | E28: =#REF! -> #REF! | F28: 0 | G28: =E28 -> #REF! | R28: =SUM(F28:Q28) -> #REF! | S28: =基数汇总!S29 -> 65.722569 | T28: =基数汇总!R29 -> 362.30406 | U28: =IF(S28>0,R28/S28-1,"") -> #REF! | V28: =E28=M28 -> #REF!
D29: 星居单 | E29: =#REF! -> #REF! | F29: 10.204182 | G29: =E29 -> #REF! | R29: =SUM(F29:Q29) -> #REF! | S29: =基数汇总!S30 -> 1.0219387 | T29: =基数汇总!R30 -> 24.905507 | U29: =IF(S29>0,R29/S29-1,"") -> #REF! | V29: =E29=M29 -> #REF!
D30: 微居单 | E30: =#REF! -> #REF! | F30: 6.6363377 | G30: =E30 -> #REF! | R30: =SUM(F30:Q30) -> #REF! | S30: =基数汇总!S31 -> 20741.544 | T30: =基数汇总!R31 -> 49011.837 | U30: =IF(S30>0,R30/S30-1,"") -> #REF! | V30: =E30=M30 -> #REF!
C31: 按合同类型 | D31: 普通单 | E31: =#REF! -> #REF! | F31: 1352.0501 | G31: =E31 -> #REF! | R31: =SUM(F31:Q31) -> #REF! | S31: =基数汇总!S32 -> 2999.7662 | T31: =基数汇总!R32 -> 6699.8069 | U31: =IF(S31>0,R31/S31-1,"") -> #REF! | V31: =E31=M31 -> #REF!
D32: 样品单 | E32: =#REF! -> #REF! | F32: 162.96283 | G32: =E32 -> #REF! | R32: =SUM(F32:Q32) -> #REF! | S32: =基数汇总!S33 -> 297.96354 | T32: =基数汇总!R33 -> 691.24638 | U32: =IF(S32>0,R32/S32-1,"") -> #REF! | V32: =E32=M32 -> #REF!
D33: 遗留单 | E33: =#REF! -> #REF! | F33: 9.182839 | G33: =E33 -> #REF! | R33: =SUM(F33:Q33) -> #REF! | S33: =基数汇总!S34 -> 3674.2684 | T33: =基数汇总!R34 -> 9837.228 | U33: =IF(S33>0,R33/S33-1,"") -> #REF! | V33: =E33=M33 -> #REF!
B34: 毛利 | C34: 按产品 | D34: 柜门 | E34: =#REF! -> #REF! | F34: 116.27591 | G34: =E34 -> #REF! | R34: =SUM(F34:Q34) -> #REF! | S34: =基数汇总!S35 -> 2114.9973 | T34: =基数汇总!R35 -> 5475.3232 | U34: =IF(S34>0,R34/S34-1,"") -> #REF! | V34: =E34=M34 -> #REF!
D35: 台面 | E35: =#REF! -> #REF! | F35: 70.191796 | G35: =E35 -> #REF! | R35: =SUM(F35:Q35) -> #REF! | S35: =基数汇总!S36 -> 1636.0574 | T35: =基数汇总!R36 -> 2701.2466 | U35: =IF(S35>0,R35/S35-1,"") -> #REF! | V35: =E35=M35 -> #REF!
D36: OEM烟灶 | E36: =#REF! -> #REF! | F36: 59.738539 | G36: =E36 -> #REF! | R36: =SUM(F36:Q36) -> #REF! | S36: =基数汇总!S37 -> 2414.9498 | T36: =基数汇总!R37 -> 5293.8046 | U36: =IF(S36>0,R36/S36-1,"") -> #REF! | V36: =E36=M36 -> #REF!
D37: OEM其他 | E37: =#REF! -> #REF! | F37: 120.86981 | G37: =E37 -> #REF! | R37: =SUM(F37:Q37) -> #REF! | S37: =基数汇总!S38 -> 1085.0047 | T37: =基数汇总!R38 -> 2714.5076 | U37: =IF(S37>0,R37/S37-1,"") -> #REF! | V37: =E37=M37 -> #REF!
D38: 自制烟灶 | E38: =#REF! -> #REF! | F38: 50.6227 | G38: =E38 -> #REF! | R38: =SUM(F38:Q38) -> #REF! | S38: =基数汇总!S39 -> 19.3668 | T38: =基数汇总!R39 -> 43.6799 | U38: =IF(S38>0,R38/S38-1,"") -> #REF! | V38: =E38=M38 -> #REF!
D39: 其他加收 | E39: =#REF! -> #REF! | F39: 1.1902 | G39: =E39 -> #REF! | R39: =SUM(F39:Q39) -> #REF! | S39: =基数汇总!S40 -> 9316.7319 | T39: =基数汇总!R40 -> 21432.078 | U39: =IF(S39>0,R39/S39-1,"") -> #REF! | V39: =E39=M39 -> #REF!
C40: 按订单类型 | D40: 常规单 | E40: =#REF! -> #REF! | F40: 370.42047 | G40: =E40 -> #REF! | R40: =SUM(F40:Q40) -> #REF! | S40: =基数汇总!S41 -> 344.64339 | T40: =基数汇总!R41 -> 1051.6304 | U40: =IF(S40>0,R40/S40-1,"") -> #REF! | V40: =E40=M40 -> #REF!
D41: 家装单 | E41: =#REF! -> #REF! | F41: 18.529747 | G41: =E41 -> #REF! | R41: =SUM(F41:Q41) -> #REF! | S41: =基数汇总!S42 -> 1263.7786 | T41: =基数汇总!R42 -> 3457.5513 | U41: =IF(S41>0,R41/S41-1,"") -> #REF! | V41: =E41=M41 -> #REF!
D42: 直供单 | E42: =#REF! -> #REF! | F42: 27.939959 | G42: =E42 -> #REF! | R42: =SUM(F42:Q42) -> #REF! | S42: =基数汇总!S43 -> 0.67797286 | T42: =基数汇总!R43 -> 0.67797286 | U42: =IF(S42>0,R42/S42-1,"") -> #REF! | V42: =E42=M42 -> #REF!
D43: 网销单 | E43: =#REF! -> #REF! | F43: 0 | G43: =E43 -> #REF! | R43: =SUM(F43:Q43) -> #REF! | S43: =基数汇总!S44 -> 18.582631 | T43: =基数汇总!R44 -> 125.60914 | U43: =IF(S43>0,R43/S43-1,"") -> #REF! | V43: =E43=M43 -> #REF!
D44: 星居单 | E44: =#REF! -> #REF! | F44: 1.7625182 | G44: =E44 -> #REF! | R44: =SUM(F44:Q44) -> #REF! | S44: =基数汇总!S45 -> 0.22986129 | T44: =基数汇总!R45 -> 6.4626926 | U44: =IF(S44>0,R44/S44-1,"") -> #REF! | V44: =E44=M44 -> #REF!
D45: 微居单 | E45: =#REF! -> #REF! | F45: 0.23626226 | G45: =E45 -> #REF! | R45: =SUM(F45:Q45) -> #REF! | S45: =基数汇总!S46 -> 9923.8443 | T45: =基数汇总!R46 -> 23651.52 | U45: =IF(S45>0,R45/S45-1,"") -> #REF! | V45: =E45=M45 -> #REF!
C46: 按合同类型 | D46: 普通单 | E46: =#REF! -> #REF! | F46: 405.81258 | G46: =E46 -> #REF! | R46: =SUM(F46:Q46) -> #REF! | S46: =基数汇总!S47 -> 964.46677 | T46: =基数汇总!R47 -> 2304.7631 | U46: =IF(S46>0,R46/S46-1,"") -> #REF! | V46: =E46=M46 -> #REF!
D47: 样品单 | E47: =#REF! -> #REF! | F47: 22.259213 | G47: =E47 -> #REF! | R47: =SUM(F47:Q47) -> #REF! | S47: =基数汇总!S48 -> 56.333258 | T47: =基数汇总!R48 -> 117.72722 | U47: =IF(S47>0,R47/S47-1,"") -> #REF! | V47: =E47=M47 -> #REF!
D48: 遗留单 | E48: =#REF! -> #REF! | F48: -9.182839 | G48: =E48 -> #REF! | R48: =SUM(F48:Q48) -> #REF! | S48: =基数汇总!S49 -> 34983.918 | T48: =基数汇总!R49 -> 82468.68 | U48: =IF(S48>0,R48/S48-1,"") -> #REF! | V48: =E48=M48 -> #REF!
B49: 收入 | E49: =SUM(E4:E9) -> #REF! | F49: 1943.0848 | G49: =E49 -> #REF! | R49: =SUM(F49:Q49) -> #REF! | S49: =基数汇总!S50 -> 24039.274 | T49: =基数汇总!R50 -> 56402.89 | U49: =IF(S49>0,R49/S49-1,"") -> #REF! | V49: =E49=M49 -> #REF!
B50: 成本 | E50: =SUM(E19:E24) -> #REF! | F50: 1524.1958 | G50: =E50 -> #REF! | R50: =SUM(F50:Q50) -> #REF! | S50: =基数汇总!S51 -> 10944.644 | T50: =基数汇总!R51 -> 26065.79 | U50: =IF(S50>0,R50/S50-1,"") -> #REF! | V50: =E50=M50 -> #REF!
B51: 费用 | E51: =#REF! -> #REF! | F51: 205.89897 | G51: =E51 -> #REF! | R51: =SUM(F51:Q51) -> #REF! | S51: =基数汇总!S52 -> 4200.8272 | T51: =基数汇总!R52 -> 11075.081 | U51: =IF(S51>0,R51/S51-1,"") -> #REF! | V51: =E51=M51 -> #REF!
B52: 利润 | E52: =E49-E50-E51 -> #REF! | F52: 212.98999 | G52: =E52 -> #REF! | R52: =SUM(F52:Q52) -> #REF! | S52: =基数汇总!S53 -> 6743.8171 | T52: =基数汇总!R53 -> 14990.709 | U52: =IF(S52>0,R52/S52-1,"") -> #REF! | V52: =E52=M52 -> #REF!
B53: 毛利率 | E53: =IF(E49>0,(E49-E50)/E49,"") -> #REF! | F53: 0.21557935 | G53: =E53 -> #REF! | R53: =IF(R49>0,(R49-R50)/R49,"") -> #REF! | S53: =基数汇总!S54 -> 0.31284787 | T53: =基数汇总!R54 -> 0.31606896 | U53: =IF(R53<>"",R53-S53,"") -> #REF! | V53: =E53=M53 -> #REF!
B54: 费用率 | E54: =IF(E49>0,E51/E49,"") -> #REF! | F54: 0.10596499 | G54: =E54 -> #REF! | R54: =IF(R49>0,R51/R49,"") -> #REF! | S54: =基数汇总!S55 -> 0.12007881 | T54: =基数汇总!R55 -> 0.13429439 | U54: =IF(R54<>"",R54-S54,"") -> #REF! | V54: =E54=M54 -> #REF!
B55: 净利率 | E55: =IF(E49>0,E52/E49,"") -> #REF! | F55: 0.10961436 | G55: =E55 -> #REF! | R55: =IF(R49>0,R52/R49,"") -> #REF! | S55: =基数汇总!S56 -> 0.19276906 | T55: =基数汇总!R56 -> 0.18177457 | U55: =IF(R55<>"",R55-S55,"") -> #REF! | V55: =E55=M55 -> #REF!
A56: 橱柜经销二部 | B56: 收入 | C56: 按产品 | D56: 柜门 | E56: =#REF! -> #REF! | F56: 532.1554 | G56: =E56 -> #REF! | R56: =SUM(F56:Q56) -> #REF! | S56: =基数汇总!S57 -> 11223.367 | T56: =基数汇总!R57 -> 28283.1 | U56: =IF(S56>0,R56/S56-1,"") -> #REF! | V56: =E56=M56 -> #REF!
D57: 台面 | E57: =#REF! -> #REF! | F57: 367.9927 | G57: =E57 -> #REF! | R57: =SUM(F57:Q57) -> #REF! | S57: =基数汇总!S58 -> 6591.3229 | T57: =基数汇总!R58 -> 16172.284 | U57: =IF(S57>0,R57/S57-1,"") -> #REF! | V57: =E57=M57 -> #REF!
D58: OEM烟灶 | E58: =#REF! -> #REF! | F58: 129.76469 | G58: =E58 -> #REF! | R58: =SUM(F58:Q58) -> #REF! | S58: =基数汇总!S59 -> 4222.5525 | T58: =基数汇总!R59 -> 7578.8729 | U58: =IF(S58>0,R58/S58-1,"") -> #REF! | V58: =E58=M58 -> #REF!
D59: OEM其他 | E59: =#REF! -> #REF! | F59: 300.23258 | G59: =E59 -> #REF! | R59: =SUM(F59:Q59) -> #REF! | S59: =基数汇总!S60 -> 4898.5106 | T59: =基数汇总!R60 -> 11640.672 | U59: =IF(S59>0,R59/S59-1,"") -> #REF! | V59: =E59=M59 -> #REF!
D60: 自制烟灶 | E60: =#REF! -> #REF! | F60: 170.2523 | G60: =E60 -> #REF! | R60: =SUM(F60:Q60) -> #REF! | S60: =基数汇总!S61 -> 2757.7158 | T60: =基数汇总!R61 -> 6760.0797 | U60: =IF(S60>0,R60/S60-1,"") -> #REF! | V60: =E60=M60 -> #REF!
D61: 其他加收 | E61: =#REF! -> #REF! | F61: 0.5147 | G61: =E61 -> #REF! | R61: =SUM(F61:Q61) -> #REF! | S61: =基数汇总!S62 -> 5.2224 | T61: =基数汇总!R62 -> 17.2299 | U61: =IF(S61>0,R61/S61-1,"") -> #REF! | V61: =E61=M61 -> #REF!
C62: 按订单类型 | D62: 常规单 | E62: =#REF! -> #REF! | F62: 1115.4875 | G62: =E62 -> #REF! | R62: =SUM(F62:Q62) -> #REF! | S62: =基数汇总!S63 -> 21375.975 | T62: =基数汇总!R63 -> 50677.549 | U62: =IF(S62>0,R62/S62-1,"") -> #REF! | V62: =E62=M62 -> #REF!
D63: 家装单 | E63: =#REF! -> #REF! | F63: 170.1867 | G63: =E63 -> #REF! | R63: =SUM(F63:Q63) -> #REF! | S63: =基数汇总!S64 -> 2471.5285 | T63: =基数汇总!R64 -> 5782.8302 | U63: =IF(S63>0,R63/S63-1,"") -> #REF! | V63: =E63=M63 -> #REF!
D64: 直供单 | E64: =#REF! -> #REF! | F64: 205.1521 | G64: =E64 -> #REF! | R64: =SUM(F64:Q64) -> #REF! | S64: =基数汇总!S65 -> 5764.3887 | T64: =基数汇总!R65 -> 13493.112 | U64: =IF(S64>0,R64/S64-1,"") -> #REF! | V64: =E64=M64 -> #REF!
D65: 网销单 | E65: =#REF! -> #REF! | F65: 0 | G65: =E65 -> #REF! | R65: =SUM(F65:Q65) -> #REF! | S65: =基数汇总!S66 -> 0 | T65: =基数汇总!R66 -> 0 | U65: =IF(S65>0,R65/S65-1,"") | V65: =E65=M65 -> #REF!
D66: 星居单 | E66: =#REF! -> #REF! | F66: 9.8346 | G66: =E66 -> #REF! | R66: =SUM(F66:Q66) -> #REF! | S66: =基数汇总!S67 -> 86.7991 | T66: =基数汇总!R67 -> 483.0533 | U66: =IF(S66>0,R66/S66-1,"") -> #REF! | V66: =E66=M66 -> #REF!
D67: 微居单 | E67: =#REF! -> #REF! | F67: 0.2515 | G67: =E67 -> #REF! | R67: =SUM(F67:Q67) -> #REF! | S67: =基数汇总!S68 -> 0 | T67: =基数汇总!R68 -> 15.6639 | U67: =IF(S67>0,R67/S67-1,"") | V67: =E67=M67 -> #REF!
C68: 按合同类型 | D68: 普通单 | E68: =#REF! -> #REF! | F68: 1447.8834 | G68: =E68 -> #REF! | R68: =SUM(F68:Q68) -> #REF! | S68: =基数汇总!S69 -> 25734.895 | T68: =基数汇总!R69 -> 60646.011 | U68: =IF(S68>0,R68/S68-1,"") -> #REF! | V68: =E68=M68 -> #REF!
D69: 样品单 | E69: =#REF! -> #REF! | F69: 53.028959 | G69: =E69 -> #REF! | R69: =SUM(F69:Q69) -> #REF! | S69: =基数汇总!S70 -> 3677.6334 | T69: =基数汇总!R70 -> 9155.7894 | U69: =IF(S69>0,R69/S69-1,"") -> #REF! | V69: =E69=M69 -> #REF!
D70: 遗留单 | E70: =#REF! -> #REF! | F70: 0 | G70: =E70 -> #REF! | R70: =SUM(F70:Q70) -> #REF! | S70: =基数汇总!S71 -> 286.1621 | T70: =基数汇总!R71 -> 650.4085 | U70: =IF(S70>0,R70/S70-1,"") -> #REF! | V70: =E70=M70 -> #REF!
B71: 成本 | C71: 按产品 | D71: 柜门 | E71: =#REF! -> #REF! | F71: 461.72347 | G71: =E71 -> #REF! | R71: =SUM(F71:Q71) -> #REF! | S71: =基数汇总!S72 -> 8259.2927 | T71: =基数汇总!R72 -> 20333.093 | U71: =IF(S71>0,R71/S71-1,"") -> #REF! | V71: =E71=M71 -> #REF!
D72: 台面 | E72: =#REF! -> #REF! | F72: 316.59849 | G72: =E72 -> #REF! | R72: =SUM(F72:Q72) -> #REF! | S72: =基数汇总!S73 -> 4850.5646 | T72: =基数汇总!R73 -> 11626.468 | U72: =IF(S72>0,R72/S72-1,"") -> #REF! | V72: =E72=M72 -> #REF!
D73: OEM烟灶 | E73: =#REF! -> #REF! | F73: 79.351789 | G73: =E73 -> #REF! | R73: =SUM(F73:Q73) -> #REF! | S73: =基数汇总!S74 -> 2702.9891 | T73: =基数汇总!R74 -> 4957.3177 | U73: =IF(S73>0,R73/S73-1,"") -> #REF! | V73: =E73=M73 -> #REF!
D74: OEM其他 | E74: =#REF! -> #REF! | F74: 180.06978 | G74: =E74 -> #REF! | R74: =SUM(F74:Q74) -> #REF! | S74: =基数汇总!S75 -> 2983.2134 | T74: =基数汇总!R75 -> 7303.4615 | U74: =IF(S74>0,R74/S74-1,"") -> #REF! | V74: =E74=M74 -> #REF!
D75: 自制烟灶 | E75: =#REF! -> #REF! | F75: 94.6149 | G75: =E75 -> #REF! | R75: =SUM(F75:Q75) -> #REF! | S75: =基数汇总!S76 -> 1512.857 | T75: =基数汇总!R76 -> 3758.1817 | U75: =IF(S75>0,R75/S75-1,"") -> #REF! | V75: =E75=M75 -> #REF!
D76: 其他加收 | E76: =#REF! -> #REF! | F76: 0 | G76: =E76 -> #REF! | R76: =SUM(F76:Q76) -> #REF! | S76: =基数汇总!S77 -> 0 | T76: =基数汇总!R77 -> 0 | U76: =IF(S76>0,R76/S76-1,"") | V76: =E76=M76 -> #REF!
C77: 按订单类型 | D77: 常规单 | E77: =#REF! -> #REF! | F77: 798.99401 | G77: =E77 -> #REF! | R77: =SUM(F77:Q77) -> #REF! | S77: =基数汇总!S78 -> 13851.882 | T77: =基数汇总!R78 -> 33094.627 | U77: =IF(S77>0,R77/S77-1,"") -> #REF! | V77: =E77=M77 -> #REF!
D78: 家装单 | E78: =#REF! -> #REF! | F78: 147.56832 | G78: =E78 -> #REF! | R78: =SUM(F78:Q78) -> #REF! | S78: =基数汇总!S79 -> 2097.9717 | T78: =基数汇总!R79 -> 4717.0341 | U78: =IF(S78>0,R78/S78-1,"") -> #REF! | V78: =E78=M78 -> #REF!
D79: 直供单 | E79: =#REF! -> #REF! | F79: 175.38892 | G79: =E79 -> #REF! | R79: =SUM(F79:Q79) -> #REF! | S79: =基数汇总!S80 -> 4291.4091 | T79: =基数汇总!R80 -> 9799.2117 | U79: =IF(S79>0,R79/S79-1,"") -> #REF! | V79: =E79=M79 -> #REF!
D80: 网销单 | E80: =#REF! -> #REF! | F80: 0 | G80: =E80 -> #REF! | R80: =SUM(F80:Q80) -> #REF! | S80: =基数汇总!S81 -> 0 | T80: =基数汇总!R81 -> 0 | U80: =IF(S80>0,R80/S80-1,"") | V80: =E80=M80 -> #REF!
D81: 星居单 | E81: =#REF! -> #REF! | F81: 10.190838 | G81: =E81 -> #REF! | R81: =SUM(F81:Q81) -> #REF! | S81: =基数汇总!S82 -> 67.653972 | T81: =基数汇总!R82 -> 355.08684 | U81: =IF(S81>0,R81/S81-1,"") -> #REF! | V81: =E81=M81 -> #REF!
D82: 微居单 | E82: =#REF! -> #REF! | F82: 0.21634668 | G82: =E82 -> #REF! | R82: =SUM(F82:Q82) -> #REF! | S82: =基数汇总!S83 -> 0 | T82: =基数汇总!R83 -> 12.562178 | U82: =IF(S82>0,R82/S82-1,"") | V82: =E82=M82 -> #REF!
C83: 按合同类型 | D83: 普通单 | E83: =#REF! -> #REF! | F83: 1081.476 | G83: =E83 -> #REF! | R83: =SUM(F83:Q83) -> #REF! | S83: =基数汇总!S84 -> 17315.996 | T83: =基数汇总!R84 -> 40651.221 | U83: =IF(S83>0,R83/S83-1,"") -> #REF! | V83: =E83=M83 -> #REF!
D84: 样品单 | E84: =#REF! -> #REF! | F84: 43.833739 | G84: =E84 -> #REF! | R84: =SUM(F84:Q84) -> #REF! | S84: =基数汇总!S85 -> 2767.8878 | T84: =基数汇总!R85 -> 6803.5168 | U84: =IF(S84>0,R84/S84-1,"") -> #REF! | V84: =E84=M84 -> #REF!
D85: 遗留单 | E85: =#REF! -> #REF! | F85: 7.04873 | G85: =E85 -> #REF! | R85: =SUM(F85:Q85) -> #REF! | S85: =基数汇总!S86 -> 225.03284 | T85: =基数汇总!R86 -> 523.78411 | U85: =IF(S85>0,R85/S85-1,"") -> #REF! | V85: =E85=M85 -> #REF!
B86: 毛利 | C86: 按产品 | D86: 柜门 | E86: =#REF! -> #REF! | F86: 70.43193 | G86: =E86 -> #REF! | R86: =SUM(F86:Q86) -> #REF! | S86: =基数汇总!S87 -> 2964.074 | T86: =基数汇总!R87 -> 7950.0069 | U86: =IF(S86>0,R86/S86-1,"") -> #REF! | V86: =E86=M86 -> #REF!
D87: 台面 | E87: =#REF! -> #REF! | F87: 51.394211 | G87: =E87 -> #REF! | R87: =SUM(F87:Q87) -> #REF! | S87: =基数汇总!S88 -> 1740.7583 | T87: =基数汇总!R88 -> 4545.8161 | U87: =IF(S87>0,R87/S87-1,"") -> #REF! | V87: =E87=M87 -> #REF!
D88: OEM烟灶 | E88: =#REF! -> #REF! | F88: 50.412902 | G88: =E88 -> #REF! | R88: =SUM(F88:Q88) -> #REF! | S88: =基数汇总!S89 -> 1519.5634 | T88: =基数汇总!R89 -> 2621.5552 | U88: =IF(S88>0,R88/S88-1,"") -> #REF! | V88: =E88=M88 -> #REF!
D89: OEM其他 | E89: =#REF! -> #REF! | F89: 120.16279 | G89: =E89 -> #REF! | R89: =SUM(F89:Q89) -> #REF! | S89: =基数汇总!S90 -> 1915.2971 | T89: =基数汇总!R90 -> 4337.2101 | U89: =IF(S89>0,R89/S89-1,"") -> #REF! | V89: =E89=M89 -> #REF!
D90: 自制烟灶 | E90: =#REF! -> #REF! | F90: 75.6374 | G90: =E90 -> #REF! | R90: =SUM(F90:Q90) -> #REF! | S90: =基数汇总!S91 -> 1244.8588 | T90: =基数汇总!R91 -> 3001.898 | U90: =IF(S90>0,R90/S90-1,"") -> #REF! | V90: =E90=M90 -> #REF!
D91: 其他加收 | E91: =#REF! -> #REF! | F91: 0.5147 | G91: =E91 -> #REF! | R91: =SUM(F91:Q91) -> #REF! | S91: =基数汇总!S92 -> 5.2224 | T91: =基数汇总!R92 -> 17.2299 | U91: =IF(S91>0,R91/S91-1,"") -> #REF! | V91: =E91=M91 -> #REF!
C92: 按订单类型 | D92: 常规单 | E92: =#REF! -> #REF! | F92: 316.49346 | G92: =E92 -> #REF! | R92: =SUM(F92:Q92) -> #REF! | S92: =基数汇总!S93 -> 7524.0924 | T92: =基数汇总!R93 -> 17582.923 | U92: =IF(S92>0,R92/S92-1,"") -> #REF! | V92: =E92=M92 -> #REF!
D93: 家装单 | E93: =#REF! -> #REF! | F93: 22.618381 | G93: =E93 -> #REF! | R93: =SUM(F93:Q93) -> #REF! | S93: =基数汇总!S94 -> 373.55684 | T93: =基数汇总!R94 -> 1065.7961 | U93: =IF(S93>0,R93/S93-1,"") -> #REF! | V93: =E93=M93 -> #REF!
D94: 直供单 | E94: =#REF! -> #REF! | F94: 29.763179 | G94: =E94 -> #REF! | R94: =SUM(F94:Q94) -> #REF! | S94: =基数汇总!S95 -> 1472.9796 | T94: =基数汇总!R95 -> 3693.9001 | U94: =IF(S94>0,R94/S94-1,"") -> #REF! | V94: =E94=M94 -> #REF!
D95: 网销单 | E95: =#REF! -> #REF! | F95: 0 | G95: =E95 -> #REF! | R95: =SUM(F95:Q95) -> #REF! | S95: =基数汇总!S96 -> 0 | T95: =基数汇总!R96 -> 0 | U95: =IF(S95>0,R95/S95-1,"") | V95: =E95=M95 -> #REF!
D96: 星居单 | E96: =#REF! -> #REF! | F96: -0.35623809 | G96: =E96 -> #REF! | R96: =SUM(F96:Q96) -> #REF! | S96: =基数汇总!S97 -> 19.145128 | T96: =基数汇总!R97 -> 127.96646 | U96: =IF(S96>0,R96/S96-1,"") -> #REF! | V96: =E96=M96 -> #REF!
D97: 微居单 | E97: =#REF! -> #REF! | F97: 0.035153322 | G97: =E97 -> #REF! | R97: =SUM(F97:Q97) -> #REF! | S97: =基数汇总!S98 -> 0 | T97: =基数汇总!R98 -> 3.1017215 | U97: =IF(S97>0,R97/S97-1,"") | V97: =E97=M97 -> #REF!
C98: 按合同类型 | D98: 普通单 | E98: =#REF! -> #REF! | F98: 366.40745 | G98: =E98 -> #REF! | R98: =SUM(F98:Q98) -> #REF! | S98: =基数汇总!S99 -> 8418.8991 | T98: =基数汇总!R99 -> 19994.79 | U98: =IF(S98>0,R98/S98-1,"") -> #REF! | V98: =E98=M98 -> #REF!
D99: 样品单 | E99: =#REF! -> #REF! | F99: 9.1952202 | G99: =E99 -> #REF! | R99: =SUM(F99:Q99) -> #REF! | S99: =基数汇总!S100 -> 909.74564 | T99: =基数汇总!R100 -> 2352.2727 | U99: =IF(S99>0,R99/S99-1,"") -> #REF! | V99: =E99=M99 -> #REF!
D100: 遗留单 | E100: =#REF! -> #REF! | F100: -7.04873 | G100: =E100 -> #REF! | R100: =SUM(F100:Q100) -> #REF! | S100: =基数汇总!S101 -> 61.129262 | T100: =基数汇总!R101 -> 126.62439 | U100: =IF(S100>0,R100/S100-1,"") -> #REF! | V100: =E100=M100 -> #REF!
...

Sheet 制表备注
C1: B
A2: =#REF!&"橱柜营销线财务报表目录" -> #REF!
A4: 序号 | B4: 名 称 | C4: 页码 | D4: 备注 | E4: 更新1 | F4: 更新2 | G4: 更新3 | H4: 更新4 | I4: 更新5 | J4: 更新6 | K4: 更新7
A5: 1 | B5: 橱柜营销线M/N值目标完成、增长考核情况 ．．．．．．．．．．．．．．．．．．． | C5: 1 | D5: 考核 | E5: 无
A6: 2 | B6: 橱柜营销线M/N值经营简报 ．．．．．．．．．．．．．．．．．．． | C6: 1.1 | D6: 考核 | E6: 更新截止前一个月的累计数 | F6: 当月取数公式更改 | G6: 上月数据
A7: 3 | B7: 橱柜营销线考核调整汇总表．．．．．．．．．．．．．．．．．．．．． | C7: 2 | D7: 考核 | E7: 无
A8: 4 | B8: 橱柜营销线调整月度表 ．．．．．．．．．．．．．．．．．．．．．． | C8: 2.1 | D8: 考核，不发送 | E8: 工程共享 | F8: 大礼包（取百货报表） | G8: 广分专项 | H8: 电器厂共享 | I8: 整装大家居收入、厨电售服共享 | J8: 欧铂丽厨电售服专项
A9: 5 | B9: 橱柜营销线调整累计表 ．．．．．．．．．．．．．．．．．．．．．． | C9: 2.2 | D9: 考核，不发送 | E9: 无
A10: 6 | B10: 橱柜营销线实际经营情况汇总表．．．．．．．．．．．．．．．．．．．．．．．．．．．． | C10: 3 | D10: 实际表 | E10: 无
A11: 7 | B11: 橱柜营销线实际经营情况明细表．．．．．．．．．．．．．．．．．．．．．．．．．．．．． | C11: 4 | D11: 实际表 | E11: 简要分析上月取数更新 | F11: 当月取数公式更改
A12: 8 | B12: 橱柜营销线各部门费用实际总表．．．．．．．．．．．．．．．．．．．．． | C12: 5 | D12: 实际表 | E12: 无
A13: 9 | B13: 橱柜营销线各部门费用实际明细表1．．．．．．．．．．．．．．．．．．． | C13: 5.1 | D13: 实际表 | E13: 无
A14: 10 | B14: 橱柜营销线各部门费用实际明细表1．．．．．．．．．．．．．．．．．．． | C14: 5.2 | D14: 实际表 | E14: 上月实际发生额 | F14: 当月取数公式更改 | G14: 上月更新
A15: 11 | B15: 2018年橱柜营销专项费用提取及支出汇总考核表．．．．．．．．．．．．．．． | C15: 6 | D15: 考核 | E15: 无
A16: 12 | B16: 资产占用统计及各部应收账款分类汇总表．．．．．．．．．．．．．．．．．．．．．．．．．． | C16: 7 | D16: 实际表 | E16: 资产占用 | F16: 应收账款分类汇总 | G16: 应付账款
A17: 13 | B17: 橱柜营销线各部月度汇总实际表 ．．．．．．．．．．．．．．．．．．．．．． | C17: 8 | D17: 实际表 | E17: 当月取数公式更改
A18: 14 | B18: 橱柜营销线各部利润实际表 ．．．．．．．．．．．．．．．．．．．．．．．．．．．．．．．． | C18: 9 | D18: 实际表 | E18: 其他加收 | F18: 星居单、微居单数值更新 | G18: 上月合计
A19: 15 | B19: 经销部收入成本（厂部级）及专项费用计提明细实际表．．．．．．．．．．．． | C19: 10 | D19: 实际表 | E19: 经销部收入①
A20: 16 | B20: 橱柜经销部毛利率调整表．．．．．．．．．．．．．．．．．．．．．．．．．． | C20: 11 | D20: 实际表 | E20: 上月收入、成本拉公式
A21: 17 | B21: 橱柜营销线百货收入、成本明细表．．．．．．．．．．．．．．．．．．．．． | C21: 12 | D21: 实际表 | E21: 百货收入+成本 | F21: 上月数据数值填入，本月公式更改
A22: 18 | B22: 2018年橱柜营销专项费用提取及支出汇总实际表．．．．．．．．．．．．．．． | C22: 13 | D22: 实际表 | E22: 专项费用引数-支出 | F22: 当月取数公式更改 | G22: 品牌中心专项提取支付结余更新 | H22: 衣柜提取品牌中心额 | I22: 星居微居提取取数-S9
A23: 19 | B23: 费用取数 | C23: 14 | E23: 费用取数 | G23: 提取物流运费（台面、百货、橱柜收入）+橱柜厂收入分配比例 | H23: 净水器收入 | I23: 方太林内3M以及触摸茶几等产品不承担税款等费用
A24: 20 | B24: 折前及其他取数 | C24: 15 | E24: 期间、折前 | F24: 经销商会议费用，衣柜收入 | H24: 期末库存商品余额 | J24: 研发中心费用分摊计算挂账
B25: 基数汇总 | E25: 同期填“是” | F25: 更新本月

Sheet 0.报表目录
C1: B
A2: =#REF!&"橱柜营销线财务报表目录" -> #REF!
A4: 序号 | B4: 名 称 | C4: 页码 | D4: 备注
A5: 1 | B5: 橱柜营销线M/N值目标完成、增长考核情况 ．．．．．．．．．．．．．．．．．．． | C5: 1 | D5: 考核
A6: 2 | B6: 橱柜营销线M/N值经营简报 ．．．．．．．．．．．．．．．．．．． | C6: 1.1 | D6: 考核
A7: 3 | B7: 橱柜营销线考核调整汇总表．．．．．．．．．．．．．．．．．．．．． | C7: 2 | D7: 实际表
A8: 4 | B8: 橱柜营销线调整月度表 ．．．．．．．．．．．．．．．．．．．．．． | C8: 2.1 | D8: 调整表
A9: 5 | B9: 橱柜营销线调整累计表 ．．．．．．．．．．．．．．．．．．．．．． | C9: 2.2 | D9: 调整表
A10: 6 | B10: 橱柜营销线实际经营情况汇总表．．．．．．．．．．．．．．．．．．．．．．．．．．．． | C10: 3 | D10: 实际表
A11: 7 | B11: 橱柜营销线实际经营情况明细表．．．．．．．．．．．．．．．．．．．．．．．．．．．．． | C11: 4 | D11: 实际表
A12: 8 | B12: 橱柜营销线各部门费用实际总表．．．．．．．．．．．．．．．．．．．．． | C12: 5 | D12: 实际表
A13: 9 | B13: 橱柜营销线各部门费用实际明细表1．．．．．．．．．．．．．．．．．．． | C13: 5.1 | D13: 实际表
A14: 10 | B14: 橱柜营销线各部门费用实际明细表1．．．．．．．．．．．．．．．．．．． | C14: 5.2 | D14: 实际表
A15: 11 | B15: 2018年橱柜营销专项费用提取及支出汇总考核表．．．．．．．．．．．．．．． | C15: 6 | D15: 考核
A16: 12 | B16: 资产占用统计及各部应收账款分类汇总表．．．．．．．．．．．．．．．．．．．．．．．．．． | C16: 7 | D16: 考核
A17: 13 | B17: 橱柜营销线各部月度汇总实际表 ．．．．．．．．．．．．．．．．．．．．．． | C17: 8 | D17: 实际表
A18: 14 | B18: 橱柜营销线各部利润实际表 ．．．．．．．．．．．．．．．．．．．．．．．．．．．．．．．． | C18: 9 | D18: 实际表
A19: 15 | B19: 经销部收入成本（厂部级）及专项费用计提明细实际表．．．．．．．．．．．． | C19: 10 | D19: 实际表
A20: 16 | B20: 橱柜经销部毛利率调整表．．．．．．．．．．．．．．．．．．．．．．．．．． | C20: 11 | D20: 实际表
A21: 17 | B21: 橱柜营销线百货收入、成本明细表．．．．．．．．．．．．．．．．．．．．． | C21: 12 | D21: 实际表
A22: 18 | B22: 2018年橱柜营销专项费用提取及支出汇总实际表．．．．．．．．．．．．．．． | C22: 13 | D22: 实际表

Sheet 1.考核完成增长K
A1: 橱柜营销线M/N值目标完成/增长情况
A2: 表1.橱柜营销线M/N值完成汇总 | I2: （截止到2020年6月止） | Q2: 单位:万元
A3: 序号 | B3: 部门 | C3: 口径 | D3: M值指标情况 | K3: N值指标情况
D4: 本年M值累计 | E4: M值同期基数 | F4: M值增长率 | G4: M值基数 | H4: M值目标增长率 | I4: M值期望目标 | J4: M值完成率 | K4: 本年N值累计 | L4: N值同期基数 | M4: N值增长率 | N4: N值基数 | O4: N值目标增长率 | P4: N值期望目标 | Q4: N值完成率
A5: 1 | B5: 橱柜经销一部 | C5: 实际 | D5: 5798.2438 | E5: 6743.8171 | F5: -0.14021337 | G5: 14990.709 | H5: 0.0041099455 | I5: 15052.32 | J5: 0.38520599 | K5: 28052.142 | L5: 34983.918 | M5: -0.19814178 | N5: 82468.68 | O5: -0.0093089758 | P5: 81700.981 | Q5: 0.34335135
A6: 2 | B6: 橱柜经销一部 | C6: 调整 | D6: -4.1608366 | E6: -10.625036 | G6: -21.876391 | I6: -21.876391 | K6: -20.27 | L6: -56.285 | N6: -108.71 | P6: -108.71
A7: 3 | B7: 橱柜经销一部 | C7: 考核 | D7: 5794.083 | E7: 6733.1921 | F7: -0.13947458 | G7: 14968.833 | H7: 0.0041 | I7: 15030.205 | J7: 0.38549594 | K7: 28031.872 | L7: 34927.633 | M7: -0.19742995 | N7: 82359.97 | O7: -0.0093 | P7: 81594.022 | Q7: 0.34355302
A8: 4 | B8: 橱柜经销二部 | C8: 实际 | D8: 4648.8235 | E8: 5340.7969 | F8: -0.1295637 | G8: 12366.631 | H8: 0.0041099455 | I8: 12417.458 | J8: 0.37437804 | K8: 23097.513 | L8: 29698.691 | M8: -0.22227169 | N8: 70452.238 | O8: -0.0093089758 | P8: 69796.4 | Q8: 0.33092699
A9: 5 | B9: 橱柜经销二部 | C9: 调整 | D9: -7.9441921 | E9: -17.890177 | G9: -34.466063 | I9: -34.466063 | K9: -37.526 | L9: -83.035 | N9: -166.32 | P9: -166.32
A10: 6 | B10: 橱柜经销二部 | C10: 考核 | D10: 4640.8793 | E10: 5322.9067 | F10: -0.12813063 | G10: 12332.165 | H10: 0.0041 | I10: 12382.727 | J10: 0.37478652 | K10: 23059.987 | L10: 29615.656 | M10: -0.22135823 | N10: 70285.918 | O10: -0.0093 | P10: 69632.259 | Q10: 0.33116815
A11: 7 | B11: 橱柜经销三分部 | C11: 实际 | D11: 3697.6374 | E11: 4196.3637 | F11: -0.11884724 | G11: 11698.717 | H11: 0.0041099455 | I11: 11746.799 | J11: 0.31477831 | K11: 18210.534 | L11: 25711.765 | M11: -0.29174314 | N11: 64704.91 | O11: -0.0093089758 | P11: 64102.573 | Q11: 0.28408429
A12: 8 | B12: 橱柜经销三分部 | C12: 调整 | D12: -7.0720603 | E12: -6.859995 | G12: -18.413557 | I12: -18.413557 | K12: -31.782 | L12: -34.11 | N12: -87.749 | P12: -87.749
A13: 9 | B13: 橱柜经销三分部 | C13: 考核 | D13: 3690.5654 | E13: 4189.5037 | F13: -0.11909246 | G13: 11680.304 | H13: 0.0041 | I13: 11728.193 | J13: 0.31467468 | K13: 18178.752 | L13: 25677.655 | M13: -0.29204002 | N13: 64617.161 | O13: -0.0093 | P13: 64016.221 | Q13: 0.28397103
A14: 10 | B14: 橱柜经销四部 | C14: 实际 | D14: 4327.0107 | E14: 4973.6975 | F14: -0.13002134 | G14: 12782.294 | H14: 0.0041099455 | I14: 12834.828 | J14: 0.33713039 | K14: 20873.436 | L14: 26196.534 | M14: -0.20319855 | N14: 69663.005 | O14: -0.0093089758 | P14: 69014.513 | Q14: 0.30244995
A15: 11 | B15: 橱柜经销四部 | C15: 调整 | D15: -2.3570108 | E15: -6.240514 | G15: -12.680023 | I15: -12.680023 | K15: -11.11 | L15: -31.12 | N15: -60.495 | P15: -60.495
A16: 12 | B16: 橱柜经销四部 | C16: 考核 | D16: 4324.6537 | E16: 4967.457 | F16: -0.12940289 | G16: 12769.614 | H16: 0.0041 | I16: 12821.969 | J16: 0.33728467 | K16: 20862.326 | L16: 26165.414 | M16: -0.20267548 | N16: 69602.51 | O16: -0.0093 | P16: 68955.206 | Q16: 0.30254896
A17: 13 | B17: 橱柜经销五部 | C17: 实际 | D17: 5581.4423 | E17: 6497.1637 | F17: -0.14094172 | G17: 16134.395 | H17: 0.0041099455 | I17: 16200.707 | J17: 0.34451844 | K17: 28031.151 | L17: 39916.611 | M17: -0.29775725 | N17: 95253.222 | O17: -0.0093089758 | P17: 94366.512 | Q17: 0.29704553
A18: 14 | B18: 橱柜经销五部 | C18: 调整 | D18: -7.3960555 | E18: -26.393148 | G18: -60.236365 | I18: -60.236365 | K18: -34.9 | L18: -101.705 | N18: -253.2 | P18: -253.2
A19: 15 | B19: 橱柜经销五部 | C19: 考核 | D19: 5574.0462 | E19: 6470.7706 | F19: -0.13858077 | G19: 16074.159 | H19: 0.0041 | I19: 16140.063 | J19: 0.34535468 | K19: 27996.251 | L19: 39814.906 | M19: -0.29683997 | N19: 95000.022 | O19: -0.0093 | P19: 94116.522 | Q19: 0.29746372
A20: 16 | B20: 橱柜经销六部 | C20: 实际 | D20: 5625.8334 | E20: 6769.6276 | F20: -0.1689597 | G20: 16410.992 | H20: 0.0041099455 | I20: 16478.44 | J20: 0.3414057 | K20: 27376.096 | L20: 37363.067 | M20: -0.26729525 | N20: 93349.846 | O20: -0.0093089758 | P20: 92480.855 | Q20: 0.29601907
A21: 17 | B21: 橱柜经销六部 | C21: 调整 | D21: -4.3683337 | E21: -22.791248 | G21: -44.010662 | I21: -44.010662 | K21: -21.065 | L21: -112.88 | N21: -210.155 | P21: -210.155
A22: 18 | B22: 橱柜经销六部 | C22: 考核 | D22: 5621.4651 | E22: 6746.8364 | F22: -0.16679985 | G22: 16366.981 | H22: 0.0041 | I22: 16434.086 | J22: 0.34206132 | K22: 27355.031 | L22: 37250.187 | M22: -0.26564042 | N22: 93139.691 | O22: -0.0093 | P22: 92273.492 | Q22: 0.29645601
A23: 19 | B23: 厨电百货经销部-直售 | C23: 实际 | D23: 287.06527 | E23: 121.49744 | F23: 1.3627269 | G23: 510.46559 | H23: 0.0041099455 | I23: 512.56358 | J23: 0.56005787 | K23: 601.7148 | L23: 232.32547 | M23: 1.5899649 | N23: 1043.0983 | O23: -0.0093089758 | P23: 1033.3882 | Q23: 0.58227375
A24: 20 | B24: 厨电百货经销部-直售 | C24: 调整 | D24: 0 | I24: 0 | K24: 0 | L24: 0 | P24: 0
A25: 21 | B25: 厨电百货经销部-直售 | C25: 考核 | D25: 287.06527 | E25: 121.49744 | F25: 1.3627269 | G25: 510.46559 | H25: 0.0041 | I25: 512.5585 | J25: 0.56006342 | K25: 601.7148 | L25: 232.32547 | M25: 1.5899649 | N25: 1043.0983 | O25: -0.0093 | P25: 1033.3975 | Q25: 0.58226847
A26: 22 | B26: 橱柜营销利润中心合计① | C26: 实际 | D26: 29966.056 | E26: 34642.964 | F26: -0.1350031 | G26: 84894.205 | H26: 0.0041099455 | I26: 85243.115 | J26: 0.35153638 | K26: 146242.59 | L26: 194102.91 | M26: -0.2465719 | N26: 476935 | O26: -0.0093089758 | P26: 472495.22 | Q26: 0.30951125
A27: 23 | B27: 橱柜营销利润中心合计① | C27: 调整 | D27: -33.298489 | E27: -90.800118 | G27: -191.68306 | I27: -191.68306 | K27: -156.653 | L27: -419.135 | N27: -886.629 | O27: -0.0093089758 | P27: -878.37539
A28: 24 | B28: 橱柜营销利润中心合计① | C28: 考核 | D28: 29932.758 | E28: 34552.164 | F28: -0.13369368 | G28: 84702.522 | H28: 0.0041 | I28: 85049.802 | J28: 0.35194389 | K28: 146085.93 | L28: 193683.78 | M28: -0.24575028 | N28: 476048.37 | O28: -0.0093 | P28: 471621.12 | Q28: 0.30975274
A29: 25 | B29: 橱柜培训部 | C29: 实际 | D29: -223.78649 | E29: -450.1335 | G29: -1176.2379 | H29: 0.0041099455 | I29: -1181.0721 | P29: 0
A30: 26 | B30: 橱柜营销服务支持部 | C30: 实际 | D30: -176.80559 | E30: -230.67359 | G30: -495.1757 | H30: 0.0041099455 | I30: -497.21084 | P30: 0
A31: 27 | B31: 橱柜展示设计部 | C31: 实际 | D31: -300.30239 | E31: 10.255859 | F31: -30.281055 | G31: 55.524474 | H31: 0.0041099455 | I31: 55.752677 | J31: -5.3863313 | P31: 0
A32: 28 | B32: 厨电百货售后服务部 | C32: 实际 | D32: -98.585182 | E32: -180.50311 | G32: -808.58673 | H32: 0.0041099455 | I32: -811.90998 | P32: 0
A33: 29 | B33: 橱柜招商部 | C33: 实际 | D33: -492.38563 | E33: -465.6198 | G33: -1306.662 | H33: 0.0041099455 | I33: -1312.0324 | P33: 0
A34: 30 | B34: 厨电百货供应服务分部 | C34: 实际 | D34: 333.1298 | E34: 148.10653 | F34: 1.249258 | G34: -37.596115 | H34: 0.0041099455 | I34: -37.750633 | P34: 0
A35: 31 | B35: 橱柜营销数据支部 | C35: 实际 | D35: -36.603131 | E35: -41.809626 | G35: -107.95063 | H35: 0.0041099455 | I35: -108.3943 | P35: 0
A36: 32 | B36: 橱柜市场部 | C36: 实际 | D36: -199.25518 | E36: -245.95407 | G36: -624.83678 | H36: 0.0041099455 | I36: -627.40482 | P36: 0
A37: 33 | B37: 橱柜主动营销部 | C37: 实际 | D37: -72.301327 | E37: -52.505171 | G37: -180.13542 | H37: 0.0041099455 | I37: -180.87577 | P37: 0
A38: 34 | B38: 橱柜渠道拓展部 | C38: 实际 | D38: -252.27178 | E38: -359.63762 | G38: -826.2636 | H38: 0.0041099455 | I38: -829.6595 | P38: 0
A39: 35 | B39: 橱柜电商及信息化推广分部 | C39: 实际 | D39: -70.955417 | E39: -136.72458 | G39: -303.14818 | H39: 0.0041099455 | I39: -304.3941 | P39: 0
A40: 36 | B40: 厨电百货经销部 | C40: 实际 | D40: -836.7695 | E40: -540.7618 | G40: -1838.6804 | H40: 0.0041099455 | I40: -1846.2373 | P40: 0
A41: 37 | B41: 厨电百货行政支部 | C41: 实际 | D41: -43.748217 | E41: -37.888659 | G41: -98.303259 | H41: 0.0041099455 | I41: -98.70728 | P41: 0
A42: 38 | B42: 配件产品分部 | C42: 实际 | D42: -75.222829 | E42: -90.079266 | G42: -280.28533 | H42: 0.0041099455 | I42: -281.43728 | P42: 0
A43: 39 | B43: 配件产品分部 | C43: 调整 | G43: 33.791925 | I43: 33.791925 | J43: 0 | P43: 0
A44: 40 | B44: 配件产品分部 | C44: 考核 | D44: -75.222829 | E44: -90.079266 | G44: -246.4934 | I44: -246.4934 | P44: 0
A45: 41 | B45: 电器产品部 | C45: 实际 | D45: -250.59201 | E45: -237.90154 | G45: -638.0013 | H45: 0.0041099455 | I45: -640.62345 | P45: 0
A46: 42 | B46: 电器产品部 | C46: 调整 | G46: 111.86617 | I46: 111.86617 | J46: 0 | P46: 0
A47: 43 | B47: 电器产品部 | C47: 考核 | D47: -250.59201 | E47: -237.90154 | G47: -526.13513 | I47: -526.13513 | P47: 0
A48: 44 | B48: 厨电百货质量部 | C48: 实际 | D48: -156.44983 | E48: -164.71649 | G48: -431.79514 | H48: 0.0041099455 | I48: -433.56979 | P48: 0
A49: 45 | B49: 厨电百货质量部 | C49: 调整 | G49: 75.82297 | I49: 75.82297 | J49: 0 | P49: 0
A50: 46 | B50: 厨电百货质量部 | C50: 考核 | D50: -156.44983 | E50: -164.71649 | G50: -355.97217 | I50: -355.97217 | P50: 0
A51: 47 | B51: 厨电百货工艺分部 | C51: 实际 | D51: -125.05776 | E51: -105.03279 | G51: -349.26196 | H51: 0.0041099455 | I51: -350.69741 | P51: 0
A52: 48 | B52: 厨电百货工艺分部 | C52: 调整 | G52: 86.039238 | I52: 86.039238 | J52: 0 | P52: 0
A53: 49 | B53: 厨电百货工艺分部 | C53: 考核 | D53: -125.05776 | E53: -105.03279 | G53: -263.22273 | I53: -263.22273 | P53: 0
A54: 50 | B54: 橱柜营销线总经理室 | C54: 实际 | D54: -136.39419 | E54: -1296.7728 | G54: -4739.263 | H54: 0.0041099455 | I54: -4758.7411 | P54: 0
A55: 51 | B55: 橱柜职能费用合计② | C55: 实际 | D55: -3214.3567 | E55: -4478.3521 | G55: -14186.659 | H55: 0.0041099455 | I55: -14244.965 | P55: 0
A56: 52 | B56: 橱柜职能费用合计② | C56: 调整 | D56: 0 | E56: 0 | G56: 307.5203 | H56: 0 | I56: 307.5203 | J56: 0 | P56: 0
A57: 53 | B57: 橱柜职能费用合计② | C57: 考核 | D57: -3214.3567 | E57: -4478.3521 | G57: -13879.139 | H57: 0.0041099455 | I57: -13936.181 | P57: 0
A58: 54 | B58: 共享收入利润合计③ | C58: 调整 | D58: 1588.924 | E58: 967.89123 | F58: 0.64163483 | G58: 3177.2644 | I58: 3943.3029 | J58: 0.40294241 | K58: 68208.779 | L58: 76083.088 | M58: -0.10349618 | N58: 207945.75 | P58: 257508.45 | Q58: 0.26487976
A59: 55 | B59: 电器厂共享利润 | C59: 实际 | D59: 756.01656 | E59: 1023.2157 | F59: -0.26113663 | G59: 3118.9509 | I59: 3118.9509 | J59: 0.24239451
A60: 56 | B60: 研发中心费用分摊 | C60: 调整 | D60: -116.99407 | E60: -163.77523 | G60: -402.41469 | I60: -402.41469 | P60: 0
A61: 57 | B61: 考核调整项小计 | C61: 考核 | D61: 2227.9465 | E61: 1827.3317 | F61: 0.21923486 | G61: 6201.3209 | H61: 0 | I61: 6967.3594 | J61: 0.31976913 | K61: 68208.779 | L61: 76083.088 | M61: -0.10349618 | N61: 207945.75 | O61: 0 | P61: 257508.45 | Q61: 0.26487976
A62: 58 | B62: 橱柜营销事业部合计 ⑤=①+② | C62: 实际 | D62: 27507.716 | E62: 31187.828 | F62: -0.11799832 | G62: 73826.497 | H62: 0.0041099455 | I62: 74129.92 | J62: 0.37107441 | K62: 146242.59 | L62: 194102.91 | M62: -0.2465719 | N62: 476935 | O62: -0.0093089758 | P62: 472495.22 | Q62: 0.30951125
A63: 59 | B63: 橱柜零售事业部合计 ⑥=①+②+③+④ | C63: 调整 | D63: 1438.6314 | E63: 713.31588 | F63: 1.0168223 | G63: 2890.687 | I63: 2890.687 | J63: 0.49767803 | K63: 68052.126 | L63: 75663.953 | M63: -0.10060044 | N63: 207059.12 | O63: -0.0093089758 | P63: 205131.61 | Q63: 0.3317486
A64: 60 | B64: 橱柜营销事业部合计⑦ | C64: 考核 | D64: 28946.348 | E64: 31901.144 | F64: -0.092623507 | G64: 76717.184 | H64: 0.020821892 | I64: 78314.581 | J64: 0.36961633 | K64: 214294.71 | L64: 269766.86 | M64: -0.20562997 | N64: 683994.12 | O64: 0.0468 | P64: 716005.04 | Q64: 0.29929218
A65: 61 | B65: 厨电线实际 | C65: 实际 | D65: 23592.304 | E65: 29178.528 | F65: -0.19144982 | G65: 63710.032 | H65: 0.0041099455 | I65: 63971.877 | J65: 0.3687918 | K65: 58893.336 | L65: 74494.835 | M65: -0.20943062 | N65: 169450.85 | O65: -0.0093089758 | P65: 167873.43 | Q65: 0.35081987
A66: 62 | B66: 厨电线调整合计 | C66: 调整 | D66: 909.44808 | E66: 1136.9306 | F66: -0.20008479 | G66: 3785.8261 | I66: 799.73046 | J66: 1.1371932 | K66: 10438.905 | L66: 24677.21 | M66: -0.57698194 | N66: 70246.416 | P66: 70246.416 | Q66: 0.1486041
A67: 63 | B67: 厨电线合计 | C67: 考核 | D67: 24501.752 | E67: 30315.458 | F67: -0.19177366 | G67: 67495.858 | H67: 0.0041099455 | I67: 64771.607 | J67: 0.3782792 | K67: 69332.241 | L67: 99172.045 | M67: -0.30088927 | N67: 239697.26 | O67: 0.0468 | P67: 250915.09 | Q67: 0.27631754
A68: 64 | B68: 共享工程-各品类收入毛利（橱柜） | C68: 调整 | D68: 1402.194 | E68: 763.37617 | F68: 0.83683223 | G68: 2626.2265 | H68: 0.2411 | I68: 3259.4097 | J68: 0.43019875
A69: 65 | B69: 共享工程-各品类收入毛利（百货） | C69: 调整 | D69: 186.73 | E69: 204.51506 | F69: -0.086962087 | G69: 551.03797 | H69: 0.2411 | I69: 683.89322 | J69: 0.2730397
A70: 66 | B70: 工程橱柜共享（橱柜） | C70: 调整 | K70: 38481.404 | L70: 40450.272 | M70: -0.048673811 | N70: 111624.46 | O70: 0.2804 | P70: 142923.95 | Q70: 0.26924391
A71: 67 | B71: 工程橱柜共享（百货） | C71: 调整 | K71: 4280.4034 | L71: 5286.2158 | M71: -0.19027079 | N71: 14387.945 | O71: 0.2804 | P71: 18422.325 | Q71: 0.23234871
A72: 68 | B72: 整装大家居共享（橱柜） | C72: 调整 | K72: 6019.3631 | L72: 408.9499 | M72: 13.719072 | N72: 876.8851 | O72: 0.474 | P72: 1292.5286 | Q72: 4.6570443
A73: 69 | B73: 整装大家居共享（百货） | C73: 调整 | K73: 2845.4534 | L73: 5286.2158 | M73: -0.46172205 | N73: 14387.945 | O73: 0.474 | P73: 21207.831 | Q73: 0.13416994
A74: 70 | B74: 欧铂丽共享（橱柜） | C74: 调整 | K74: 6566.0228 | L74: 5383.6323 | M74: 0.2196269 | N74: 10645.246 | O74: 0.2262 | P74: 13053.2 | Q74: 0.50302015
A75: 71 | B75: 欧铂丽共享（百货） | C75: 调整 | K75: 2572.9135 | L75: 4126.4764 | M75: -0.37648656 | N75: 13657.777 | O75: 0.2262 | P75: 16747.166 | Q75: 0.15363277
A76: 72 | B76: 广分共享（橱柜） | C76: 调整 | K76: 2568.5577 | L76: 559.91693 | M76: 3.5873906 | N76: 1658.4551 | O76: 0.0401 | P76: 1724.9592 | Q76: 1.4890542
A77: 73 | B77: 广分共享（百货） | C77: 调整 | K77: 510.70092 | L77: 7987.2789 | M77: -0.93606071 | N77: 21291.985 | O77: 0.0401 | P77: 22145.794 | Q77: 0.023060854
A78: 74 | B78: 外贸共享（橱柜） | C78: 调整 | K78: 3977.8731 | L78: 3863.1072 | M78: 0.029708197 | N78: 10089.342 | O78: 0.0329 | P78: 10421.281 | Q78: 0.38170673
A79: 75 | B79: 外贸共享（百货） | C79: 调整 | K79: 386.0873 | L79: 2410.158 | M79: -0.83980831 | N79: 7407.3931 | O79: 0.0329 | P79: 7651.0963 | Q79: 0.050461697
A80: 76 | B80: 融合店其他品类收入(集成家居) | C80: 调整 | K80: 0 | L80: 213.543 | M80: -1 | N80: 1432.809 | P80: 1432.809 | Q80: 0
A81: 77 | B81: 融合店其他品类收入(木门) | C81: 调整 | K81: 0 | L81: 51.093064 | M81: -1 | N81: 227.68038 | P81: 227.68038 | Q81: 0
A82: 78 | B82: 融合店其他品类收入(卫浴) | C82: 调整 | K82: 0 | L82: 47.5365 | M82: -1 | N82: 181.2378 | P82: 181.2378 | Q82: 0
A83: 79 | B83: 融合店其他品类收入(软装) | C83: 调整 | K83: 0 | L83: 0.5093 | M83: -1 | N83: 50.597697 | P83: 50.597697 | Q83: 0
A84: 80 | B84: 融合店其他品类收入(金属门窗) | C84: 调整 | K84: 0 | L84: 0 | N84: 3.7473225 | P84: 3.7473225 | Q84: 0
A85: 81 | B85: 融合店其他品类收入(装甲门) | C85: 调整 | K85: 0 | L85: 8.182361 | M85: -1 | N85: 22.247561 | P85: 22.247561 | Q85: 0
A86: 备注： 1、厨电线收入考核口径：零售+厨电百货直售+工程共享百货收入（包含零售+独立商场）+整装大家居共享百货收入+欧铂丽共享百货收入+广分共享百货收入+外贸共享百货收入； 2、厨电线费用为厨电百货售后服务部、厨电百货供应服务部、厨电百货经销部、厨电百货行政支部、配件产品分部、电器产品部、厨电百货质量部、厨电百货工艺分部费用； 3、利润考核口径为：橱柜营销事业部实际收入-实际成本-厨电线部门费用-百货礼包-厨电产品升级减负

Sheet 1.1经营简报
A1: 橱柜营销线经营简报（2020年6月）
I2: 是 | J2: 是 | K2: 是 | L2: 是 | M2: 是 | N2: 是 | O2: 是 | P2: 是 | Q2: 是 | R2: 是 | S2: 是 | T2: 是 | U2: 是 | V2: 是 | W2: 是 | AV2: 单位：万元
A3: 项目 | C3: 1-5月累计 | F3: 当月 | I3: 1月 | L3: 2月 | O3: 3月 | R3: 4月 | U3: 5月 | X3: 6月 | AA3: 7月 | AD3: 8月 | AG3: 9月 | AJ3: 10月 | AM3: 11月 | AP3: 12月 | AS3: 本年累计 | AV3: 考核目标 | AW3: 目标差异 | AY3: 上月
C4: 实际 | D4: 调整 | E4: 考核 | F4: 实际 | G4: 调整 | H4: 考核 | I4: 实际 | J4: 调整 | K4: 考核 | L4: 实际 | M4: 调整 | N4: 考核 | O4: 实际 | P4: 调整 | Q4: 考核 | R4: 实际 | S4: 调整 | T4: 考核 | U4: 实际 | V4: 调整 | W4: 考核 | X4: 实际 | Y4: 调整 | Z4: 考核 | AA4: 实际 | AB4: 调整 | AC4: 考核 | AD4: 实际 | AE4: 调整 | AF4: 考核 | AG4: 实际 | AH4: 调整 | AI4: 考核 | AJ4: 实际 | AK4: 调整 | AL4: 考核 | AM4: 实际 | AN4: 调整 | AO4: 考核 | AP4: 实际 | AQ4: 调整 | AR4: 考核 | AS4: 实际 | AT4: 调整 | AU4: 考核 | AY4: 实际 | AZ4: 调整 | BA4: 考核
A5: 收入 | B5: 20年 | C5: 103126.72 | D5: 49052.333 | E5: 152179.05 | F5: 43115.865 | G5: 18999.793 | H5: 62115.658 | I5: 10735.966 | J5: 8870.4761 | K5: 19606.442 | L5: 3184.1495 | M5: 693.60293 | N5: 3877.7525 | O5: 19826.253 | P5: 8803.2275 | Q5: 28629.48 | R5: 28797.799 | S5: 13248.79 | T5: 42046.59 | U5: 40582.555 | V5: 17436.236 | W5: 58018.791 | X5: 43115.865 | Y5: 18999.793 | Z5: 62115.658 | AS5: 146242.59 | AT5: 68052.126 | AU5: 214294.71 | AY5: 40582.555 | AZ5: 17436.236 | BA5: 58018.791 | BB5: 0.062423617
B6: 19年 | C6: 146275.27 | D6: 55105.054 | E6: 201380.33 | F6: 47827.638 | G6: 19321.227 | H6: 67148.864 | I6: 29026.42 | J6: 9544.7776 | K6: 38571.198 | L6: 9470.5408 | M6: 3377.1911 | N6: 12847.732 | O6: 27974.577 | P6: 12560.083 | Q6: 40534.66 | R6: 37940.902 | S6: 13151.869 | T6: 51092.771 | U6: 41862.833 | V6: 16471.133 | W6: 58333.966 | X6: 47827.638 | Y6: 19321.227 | Z6: 67148.864 | AS6: 194102.91 | AT6: 74426.28 | AU6: 268529.19 | AY6: 41862.833 | AZ6: 16471.133 | BA6: 58333.966 | BB6: 0.1424845
B7: 增长率 | C7: -0.29498185 | D7: -0.10983967 | E7: -0.24432015 | F7: -0.098515693 | G7: -0.016636292 | H7: -0.074955943 | I7: -0.63013126 | J7: -0.070646121 | K7: -0.49168181 | L7: -0.66378377 | M7: -0.79462135 | N7: -0.6981761 | O7: -0.29127605 | P7: -0.29911073 | Q7: -0.29370371 | R7: -0.24098275 | S7: 0.0073694085 | T7: -0.17705404 | U7: -0.030582686 | V7: 0.058593584 | W7: -0.0054029444 | X7: -0.098515693 | Y7: -0.016636292 | Z7: -0.074955943 | AS7: -0.2465719 | AT7: -0.085643869 | AU7: -0.20196865 | AV7: 0.0515 | AW7: -0.25346865 | AY7: -0.030582686 | AZ7: 0.058593584 | BA7: -0.0054029444
A8: 成本 | B8: 20年 | C8: 68631.699 | D8: 49074.657 | E8: 117706.36 | F8: 28592.991 | G8: 19010.767 | H8: 47603.758 | I8: 7026.1351 | J8: 8878.4609 | K8: 15904.596 | L8: 2547.1396 | M8: 694.41732 | N8: 3241.5569 | O8: 13532.488 | P8: 8806.8365 | Q8: 22339.325 | R8: 19283.709 | S8: 13254.916 | T8: 32538.625 | U8: 26242.227 | V8: 17440.026 | W8: 43682.254 | X8: 28592.991 | Y8: 19010.767 | Z8: 47603.758 | AS8: 97224.69 | AT8: 68085.424 | AU8: 165310.11 | AY8: 26242.227 | AZ8: 17440.026 | BA8: 43682.254
B9: 19年 | C9: 100783.1 | D9: 55191.236 | E9: 155974.34 | F9: 32242.425 | G9: 19325.845 | H9: 51568.269 | I9: 20135.247 | J9: 9571.6568 | K9: 29706.904 | L9: 6932.2042 | M9: 3389.4892 | N9: 10321.693 | O9: 19493.815 | P9: 12573.761 | Q9: 32067.576 | R9: 24281.099 | S9: 13161.826 | T9: 37442.925 | U9: 29940.74 | V9: 16494.502 | W9: 46435.243 | X9: 32242.425 | Y9: 19325.845 | Z9: 51568.269 | AS9: 133025.53 | AT9: 74517.08 | AU9: 207542.61 | AY9: 29940.74 | AZ9: 16494.502 | BA9: 46435.243
B10: 增长率 | C10: -0.31901583 | D10: -0.11082518 | E10: -0.24534794 | F10: -0.11318732 | G10: -0.016303442 | H10: -0.076878892 | I10: -0.65105295 | J10: -0.072421721 | K10: -0.46461617 | L10: -0.63256426 | M10: -0.79512626 | N10: -0.68594718 | O10: -0.30580605 | P10: -0.29958614 | Q10: -0.30336721 | R10: -0.20581399 | S10: 0.0070727423 | T10: -0.13098068 | U10: -0.12352776 | V10: 0.057323559 | W10: -0.059286629 | X10: -0.11318732 | Y10: -0.016303442 | Z10: -0.076878892 | AS10: -0.26912758 | AT10: -0.086311168 | AU10: -0.20348831 | AY10: -0.12352776 | AZ10: 0.057323559 | BA10: -0.059286629
A11: 毛利 | B11: 20年 | C11: 34495.023 | D11: -22.324757 | E11: 34472.698 | F11: 14522.874 | G11: -10.973732 | H11: 14511.9 | I11: 3709.8305 | J11: -7.984862 | K11: 3701.8456 | L11: 637.00996 | M11: -0.814392 | N11: 636.19557 | O11: 6293.7644 | P11: -3.609011 | Q11: 6290.1554 | R11: 9514.0902 | S11: -6.126068 | T11: 9507.9642 | U11: 14340.328 | V11: -3.790424 | W11: 14336.537 | X11: 14522.874 | Y11: -10.973732 | Z11: 14511.9 | AS11: 49017.897 | AT11: -33.298489 | AU11: 48984.598 | AY11: 14340.328 | AZ11: -3.790424 | BA11: 14336.537
B12: 19年 | C12: 45492.168 | D12: -86.182166 | E12: 45405.986 | F12: 15585.213 | G12: -4.617952 | H12: 15580.595 | I12: 8891.1732 | J12: -26.87921 | K12: 8864.294 | L12: 2538.3366 | M12: -12.298141 | N12: 2526.0385 | O12: 8480.7624 | P12: -13.677903 | Q12: 8467.0845 | R12: 13659.803 | S12: -9.957358 | T12: 13649.846 | U12: 11922.093 | V12: -23.369554 | W12: 11898.723 | X12: 15585.213 | Y12: -4.617952 | Z12: 15580.595 | AS12: 61077.382 | AT12: -90.800118 | AU12: 60986.582 | AY12: 11922.093 | AZ12: -23.369554 | BA12: 11898.723
B13: 增长率 | C13: -0.24173712 | E13: -0.24078958 | F13: -0.068163279 | H13: -0.068591411 | I13: -0.58275129 | K13: -0.58238686 | L13: -0.74904433 | N13: -0.74814494 | O13: -0.25787752 | Q13: -0.25710492 | R13: -0.30349728 | T13: -0.30343799 | U13: 0.20283643 | W13: 0.20488029 | X13: -0.068163279 | Z13: -0.068591411 | AS13: -0.197446 | AU13: -0.19679712 | AY13: 0.20283643 | BA13: 0.20488029
B14: 20年毛利率 | C14: 0.3344916 | D14: -0.00045512121 | E14: 0.22652722 | F14: 0.33683365 | G14: -0.00057757113 | H14: 0.23362709 | I14: 0.34555164 | J14: -0.00090016161 | K14: 0.18880762 | L14: 0.20005655 | M14: -0.0011741473 | N14: 0.16406297 | O14: 0.31744599 | P14: -0.00040996453 | Q14: 0.21970903 | R14: 0.3303756 | S14: -0.00046238697 | T14: 0.22612926 | U14: 0.35336187 | V14: -0.00021738775 | W14: 0.24710162 | X14: 0.33683365 | Y14: -0.00057757113 | Z14: 0.23362709 | AS14: 0.3351821 | AT14: -0.00048930858 | AU14: 0.22858519 | AY14: 0.35336187 | AZ14: -0.00021738775 | BA14: 0.24710162
B15: 19年毛利率 | C15: 0.31100382 | D15: -0.0015639612 | E15: 0.22547379 | F15: 0.32586207 | G15: -0.00023900926 | H15: 0.23203066 | I15: 0.30631311 | J15: -0.002816117 | K15: 0.2298164 | L15: 0.26802446 | M15: -0.0036415295 | N15: 0.19661357 | O15: 0.30315963 | P15: -0.0010889978 | Q15: 0.20888505 | R15: 0.36002843 | S15: -0.00075710593 | T15: 0.26715807 | U15: 0.28478944 | V15: -0.0014188189 | W15: 0.2039759 | X15: 0.32586207 | Y15: -0.00023900926 | Z15: 0.23203066 | AS15: 0.31466494 | AT15: -0.0012200008 | AU15: 0.22711341 | AY15: 0.28478944 | AZ15: -0.0014188189 | BA15: 0.2039759
B16: 增减变动 | C16: 0.023487787 | D16: 0.00110884 | E16: 0.0010534248 | F16: 0.010971572 | G16: -0.00033856188 | H16: 0.0015964282 | I16: 0.039238524 | J16: 0.0019159554 | K16: -0.041008781 | L16: -0.067967915 | M16: 0.0024673823 | N16: -0.032550608 | O16: 0.014286361 | P16: 0.00067903328 | Q16: 0.010823984 | R16: -0.029652826 | S16: 0.00029471897 | T16: -0.041028809 | U16: 0.068572428 | V16: 0.0012014311 | W16: 0.043125718 | X16: 0.010971572 | Y16: -0.00033856188 | Z16: 0.0015964282 | AS16: 0.020517151 | AT16: 0.00073069217 | AU16: 0.0014717783 | AY16: 0.068572428 | AZ16: 0.0012014311 | BA16: 0.043125718
A17: 费用 | B17: 20年 | C17: 15556.633 | D17: -1335.0851 | E17: 14221.548 | F17: 6709.5636 | G17: -892.86136 | H17: 5816.7023 | I17: 2124.71 | J17: -163.27326 | K17: 1961.4367 | L17: 1024.3392 | M17: 36.328836 | N17: 1060.668 | O17: 2283.4293 | P17: -168.1423 | Q17: 2115.287 | R17: 4313.5904 | S17: -273.20516 | T17: 4040.3852 | U17: 5810.5645 | V17: -766.7932 | W17: 5043.7713 | X17: 6709.5636 | Y17: -892.86136 | Z17: 5816.7023 | AS17: 22266.197 | AT17: -2227.9465 | AU17: 20038.25 | AY17: 5810.5645 | AZ17: -766.7932 | BA17: 5043.7713
B18: 19年 | C18: 23353.356 | D18: -1021.9324 | E18: 22331.424 | F18: 7559.4133 | G18: -805.79854 | H18: 6753.6147 | I18: 4153.13 | J18: -59.579936 | K18: 4093.55 | L18: 1873.9097 | M18: -5.858451 | N18: 1868.0513 | O18: 4665.327 | P18: -264.5325 | Q18: 4400.7945 | R18: 5987.3857 | S18: -249.16399 | T18: 5738.2218 | U18: 6673.604 | V18: -442.79757 | W18: 6230.8064 | X18: 7559.4133 | Y18: -805.79854 | Z18: 6753.6147 | AS18: 30912.77 | AT18: -1827.731 | AU18: 29085.039 | AY18: 6673.604 | AZ18: -442.79757 | BA18: 6230.8064
B19: 增长率 | C19: -0.33385878 | E19: -0.36315981 | F19: -0.11242269 | H19: -0.13872755 | I19: -0.48840755 | K19: -0.52084702 | L19: -0.45336793 | N19: -0.43220617 | O19: -0.51055321 | Q19: -0.51933974 | R19: -0.27955362 | T19: -0.295882 | U19: -0.12932135 | W19: -0.19051067 | X19: -0.11242269 | Z19: -0.13872755 | AS19: -0.27970877 | AU19: -0.31104611 | AY19: -0.12932135 | BA19: -0.19051067
B20: 20年费用率 | C20: 0.15084968 | D20: -0.027217566 | E20: 0.093452731 | F20: 0.15561705 | G20: -0.046993215 | H20: 0.093643092 | I20: 0.19790581 | J20: -0.01840637 | K20: 0.10004042 | L20: 0.32169945 | M20: 0.052376994 | N20: 0.27352648 | O20: 0.11517201 | P20: -0.019100075 | Q20: 0.073884925 | R20: 0.14978889 | S20: -0.02062114 | T20: 0.096093054 | U20: 0.14317887 | V20: -0.043976992 | W20: 0.08693341 | X20: 0.15561705 | Y20: -0.046993215 | Z20: 0.093643092 | AS20: 0.15225522 | AT20: -0.032738822 | AU20: 0.093507909 | AY20: 0.14317887 | AZ20: -0.043976992 | BA20: 0.08693341
B21: 19年费用率 | C21: 0.15965348 | D21: -0.018545167 | E21: 0.11089179 | F21: 0.15805533 | G21: -0.041705351 | H21: 0.10057675 | I21: 0.14308103 | J21: -0.0062421503 | K21: 0.10612971 | L21: 0.19786724 | M21: -0.0017347112 | N21: 0.1453993 | O21: 0.16677024 | P21: -0.021061366 | Q21: 0.10856868 | R21: 0.15780821 | S21: -0.018945139 | T21: 0.11230986 | U21: 0.15941597 | V21: -0.026883249 | W21: 0.10681267 | X21: 0.15805533 | Y21: -0.041705351 | Z21: 0.10057675 | AS21: 0.15925969 | AT21: -0.024557602 | AU21: 0.10831239 | AY21: 0.15941597 | AZ21: -0.026883249 | BA21: 0.10681267
B22: 增减变动 | C22: -0.0088037975 | D22: -0.0086723984 | E22: -0.017439055 | F22: -0.0024382851 | G22: -0.0052878638 | H22: -0.0069336602 | I22: 0.054824784 | J22: -0.01216422 | K22: -0.0060892883 | L22: 0.12383222 | M22: 0.054111705 | N22: 0.12812718 | O22: -0.051598236 | P22: 0.0019612907 | Q22: -0.034683753 | R22: -0.0080193168 | S22: -0.001676001 | T22: -0.016216802 | U22: -0.016237094 | V22: -0.017093743 | W22: -0.019879256 | X22: -0.0024382851 | Y22: -0.0052878638 | Z22: -0.0069336602 | AS22: -0.0070044734 | AT22: -0.0081812201 | AU22: -0.014804482 | AY22: -0.016237094 | AZ22: -0.017093743 | BA22: -0.019879256
A23: 利润 | B23: 20年 | C23: 18938.389 | D23: 1312.7603 | E23: 20251.15 | F23: 7813.3103 | G23: 881.88763 | H23: 8695.1979 | I23: 1585.1205 | J23: 155.2884 | K23: 1740.4089 | L23: -387.3292 | M23: -37.143228 | N23: -424.47243 | O23: 4010.3351 | P23: 164.53329 | Q23: 4174.8684 | R23: 5200.4999 | S23: 267.0791 | T23: 5467.579 | U23: 8529.7631 | V23: 763.00277 | W23: 9292.7659 | X23: 7813.3103 | Y23: 881.88763 | Z23: 8695.1979 | AS23: 26751.7 | AT23: 2194.648 | AU23: 28946.348 | AY23: 8529.7631 | AZ23: 763.00277 | BA23: 9292.7659 | BB23: -0.083994454
B24: 19年 | C24: 22138.812 | D24: 935.75028 | E24: 23074.562 | F24: 8025.7999 | G24: 801.18059 | H24: 8826.9805 | I24: 4738.0432 | J24: 32.700726 | K24: 4770.7439 | L24: 664.42687 | M24: -6.43969 | N24: 657.98718 | O24: 3815.4354 | P24: 250.8546 | Q24: 4066.29 | R24: 7672.4176 | S24: 239.20663 | T24: 7911.6243 | U24: 5248.4889 | V24: 419.42802 | W24: 5667.9169 | X24: 8025.7999 | Y24: 801.18059 | Z24: 8826.9805 | AS24: 30164.612 | AT24: 1736.9309 | AU24: 31901.543 | AY24: 5248.4889 | AZ24: 419.42802 | BA24: 5667.9169 | BB24: 0.52916394
B25: 增长率 | C25: -0.14456162 | D25: 0.40289601 | E25: -0.12236039 | F25: -0.02647582 | G25: 0.10073514 | H25: -0.014929521 | I25: -0.66544827 | J25: 3.7487754 | K25: -0.63519129 | L25: -1.5829523 | N25: -1.6451074 | O25: 0.051081907 | P25: -0.34410892 | Q25: 0.026702082 | R25: -0.32218238 | S25: 0.11652046 | T25: -0.30891827 | U25: 0.62518456 | V25: 0.8191507 | W25: 0.63953813 | X25: -0.02647582 | Y25: 0.10073514 | Z25: -0.014929521 | AS25: -0.11314292 | AT25: 0.26352061 | AU25: -0.092634865 | AV25: 0.0041 | AW25: -0.096734865 | AY25: 0.62518456 | AZ25: 0.8191507 | BA25: 0.63953813
B26: 20年利润率 | C26: 0.18364192 | D26: 0.026762445 | E26: 0.13307449 | F26: 0.1812166 | G26: 0.046415644 | H26: 0.13998399 | I26: 0.14764583 | J26: 0.017506208 | K26: 0.088767201 | L26: -0.12164291 | M26: -0.053551141 | N26: -0.10946352 | O26: 0.20227398 | P26: 0.01869011 | Q26: 0.14582411 | R26: 0.18058671 | S26: 0.020158753 | T26: 0.13003621 | U26: 0.210183 | V26: 0.043759604 | W26: 0.16016821 | X26: 0.1812166 | Y26: 0.046415644 | Z26: 0.13998399 | AS26: 0.18292688 | AT26: 0.032249514 | AU26: 0.13507728 | AY26: 0.210183 | AZ26: 0.043759604 | BA26: 0.16016821
B27: 19年利润率 | C27: 0.15135034 | D27: 0.016981206 | E27: 0.11458201 | F27: 0.16780674 | G27: 0.041466342 | H27: 0.13145391 | I27: 0.16323209 | J27: 0.0034260333 | K27: 0.12368669 | L27: 0.070157226 | M27: -0.0019068184 | N27: 0.051214268 | O27: 0.13638939 | P27: 0.019972368 | Q27: 0.10031637 | R27: 0.20222022 | S27: 0.018188033 | T27: 0.15484821 | U27: 0.12537348 | V27: 0.02546443 | W27: 0.097163236 | X27: 0.16780674 | Y27: 0.041466342 | Z27: 0.13145391 | AS27: 0.15540525 | AT27: 0.023337601 | AU27: 0.11880102 | AY27: 0.12537348 | AZ27: 0.02546443 | BA27: 0.097163236
B28: 增减变动 | C28: 0.032291584 | D28: 0.0097812384 | E28: 0.01849248 | F28: 0.013409858 | G28: 0.0049493019 | H28: 0.0085300884 | I28: -0.015586259 | J28: 0.014080175 | K28: -0.034919493 | L28: -0.19180013 | M28: -0.051644323 | N28: -0.16067779 | O28: 0.065884597 | P28: -0.0012822574 | Q28: 0.045507737 | R28: -0.021633509 | S28: 0.0019707199 | T28: -0.024812007 | U28: 0.084809522 | V28: 0.018295174 | W28: 0.063004974 | X28: 0.013409858 | Y28: 0.0049493019 | Z28: 0.0085300884 | AS28: 0.027521624 | AT28: 0.0089119122 | AU28: 0.01627626 | AY28: 0.084809522 | AZ28: 0.018295174 | BA28: 0.063004974
A29: 核对： | C29: 5.0931703e-11 | D29: 5.0022209e-12 | E29: 3.2741809e-11 | F29: 0 | G29: 1.4779289e-12 | H29: 0 | I29: 0 | J29: 6.5369932e-13 | K29: 2.7284841e-12 | L29: 9.6633812e-13 | M29: 0 | N29: 1.1368684e-12 | O29: -2.1373125e-11 | P29: -4.5474735e-13 | Q29: -2.0008883e-11 | R29: 4.9112714e-11 | S29: 0 | T29: 5.4569682e-11 | AS29: 4.3655746e-11 | AT29: -7.730705e-12 | AU29: 2.910383e-11
C30: -4.3655746e-11 | D30: -6.1390892e-12 | E30: -3.6379788e-11 | F30: 7.2759576e-12 | G30: 0 | H30: 0 | I30: -4.8203219e-11 | J30: 8.4554586e-13 | K30: -4.7293724e-11 | L30: 5.0022209e-12 | M30: 2.3980817e-13 | N30: 4.888534e-12 | O30: 2.0918378e-11 | P30: 0 | Q30: 2.1373125e-11 | R30: 0 | S30: 3.4106051e-13 | T30: 0 | AS30: -2.910383e-11 | AT30: 0 | AU30: 0
S33: 1.4753231

Sheet 基数汇总
F1: 0 | AP1: 橱柜营销线M/N值调整汇总表
A2: 表6.实际表=表1+表2+表3+表4+表5 | B2: 实际+剔除补贴+剔除增城+成本调整 | F2: 是 | G2: 是 | H2: 是 | I2: 是 | J2: 是 | K2: 是 | W2: 表5：基数实际表 | Z2: =F2 -> 是 | AA2: =G2 -> 是 | AB2: =H2 -> 是 | AC2: =I2 -> 是 | AD2: =J2 -> 是 | AE2: =K2 -> 是 | AF2: =L2 -> 0 | AG2: =M2 -> 0 | ... AK2: =Q2 -> 0 | CB2: =F2 -> 是 | CC2: =G2 -> 是 | CD2: =H2 -> 是 | CE2: =I2 -> 是 | CF2: =J2 -> 是 | CG2: =K2 -> 是 | CH2: =L2 -> 0 | CI2: =M2 -> 0 | ... CN2: =R2 -> 0
A3: 部门 | B3: 项目 | C3: 口径 | D3: 类别 | E3: 本月 | F3: 1月 | G3: 2月 | H3: 3月 | I3: 4月 | J3: 5月 | K3: 6月 | L3: 7月 | M3: 8月 | N3: 9月 | O3: 10月 | P3: 11月 | Q3: 12月 | R3: 本年累计 | S3: 同期 | V3: 基数 | W3: 2020年部门名称 | X3: 项目 | Y3: 本月 | Z3: 1月 | AA3: 2月 | AB3: 3月 | AC3: 4月 | AD3: 5月 | AE3: 6月 | AF3: 7月 | AG3: 8月 | AH3: 9月 | AI3: 10月 | AJ3: 11月 | AK3: 12月 | AL3: 本年累计 | AM3: 同期 | AP3: 表5.橱柜营销线M/N值调整汇总（基数）=表4+表3 | AS3: =Z2 -> 是 | AT3: =AA2 -> 是 | AU3: =AB2 -> 是 | AV3: =AC2 -> 是 | AW3: =AD2 -> 是 | AX3: =AE2 -> 是 | AY3: =AF2 -> 0 | AZ3: =AG2 -> 0 | ... BD3: =AK2 -> 0 | BH3: =F2 -> 是 | BI3: =G2 -> 是 | BJ3: =H2 -> 是 | BK3: =I2 -> 是 | BL3: =J2 -> 是 | BM3: =K2 -> 是 | BN3: =L2 -> 0 | BO3: =M2 -> 0 | ... BS3: =Q2 -> 0 | BZ3: 大礼包 | CA3: 本月 | CB3: 1月 | CC3: 2月 | CD3: 3月 | CE3: 4月 | CF3: 5月 | CG3: 6月 | CH3: 7月 | CI3: 8月 | CJ3: 9月 | CK3: 10月 | CL3: 11月 | CM3: 12月 | CN3: 本年累计 | CO3: 同期
A4: 橱柜经销一部 | B4: 收入 | C4: 按产品 | D4: 柜门 | E4: =K4 -> 3392.3086 | F4: 2271.0135 | G4: 683.0953 | H4: 1973.7591 | I4: 2692.0759 | J4: 2900.2694 | K4: 3392.3086 | L4: 3817.283 | M4: 3883.3402 | N4: 3556.811 | O4: 3047.548 | P4: 3351.1119 | Q4: 3428.5239 | R4: 34997.14 | S4: =SUMIFS(F4:Q4,$F$2:$Q$2,"是") -> 13912.522 | T4: 基数 | V4: 基数 | W4: 橱柜经销一部 | X4: 房租 | Y4: =AE4 -> 3.9773909 | Z4: 0.63301828 | AA4: 0.64290318 | AB4: 0.59290318 | AC4: -0.036409115 | AD4: 2.8952019 | AE4: 3.9773909 | AF4: 2.0979909 | AG4: 2.1479909 | AH4: 2.7269909 | AI4: 2.7269909 | AJ4: 3.3969909 | AK4: 3.3969909 | AL4: 25.198954 | AM4: =SUMIFS(Z4:AK4,$Z$2:$AK$2,"是") -> 8.7050083 | AP4: 序号 | AQ4: 部门 | AS4: M值指标情况 | BH4: N值指标情况 | BX4: TZ0091 | BY4: 橱柜经销一部 | BZ4: 收入 | CA4: =CG4 -> 0.275 | CB4: 24.91 | CC4: 6.325 | CD4: 10.56 | CE4: 10.055 | CF4: 4.16 | CG4: 0.275 | CH4: 14.415 | CI4: 15.13 | CJ4: 7.59 | CK4: 3.685 | CL4: 8.305 | CM4: 3.3 | CN4: 108.71 | CO4: =SUMIFS(CB4:CM4,$F$2:$Q$2,"是") -> 56.285
A5: 橱柜经销一部 | B5: 收入 | C5: 按产品 | D5: 台面 | E5: =K5 -> 2022.2313 | F5: 1165.9941 | G5: 425.8761 | H5: 972.194 | I5: 1563.8114 | J5: 1858.2594 | K5: 2022.2313 | L5: 1999.2671 | M5: 1914.8097 | N5: 1831.1195 | O5: 1688.0693 | P5: 1960.5722 | Q5: 2076.9125 | R5: 19479.117 | S5: =SUMIFS(F5:Q5,$F$2:$Q$2,"是") -> 8008.3663 | T5: 基数 | V5: 基数 | W5: 橱柜经销一部 | X5: 水费 | Y5: =AE5 -> 0.041796 | Z5: 0.119556 | AA5: 0.042768 | AB5: 0.03402 | AC5: 0.032562 | AD5: 0.037422 | AE5: 0.041796 | AF5: 0.044226 | AG5: 0.044226 | AH5: 0.082414 | AI5: 0.067554 | AJ5: 0.040338 | AK5: 0.073872 | AL5: 0.660754 | AM5: =SUMIFS(Z5:AK5,$Z$2:$AK$2,"是") -> 0.308124 | AR5: 本月 | AS5: 1月 | AT5: 2月 | AU5: 3月 | AV5: 4月 | AW5: 5月 | AX5: 6月 | AY5: 7月 | AZ5: 8月 | BA5: 9月 | BB5: 10月 | BC5: 11月 | BD5: 12月 | BE5: 本年M值累计 | BF5: 同期 | BG5: 本月 | BH5: 1月 | BI5: 2月 | BJ5: 3月 | BK5: 4月 | BL5: 5月 | BM5: 6月 | BN5: 7月 | BO5: 8月 | BP5: 9月 | BQ5: 10月 | BR5: 11月 | BS5: 12月 | BT5: 本年N值累计 | BU5: 同期 | BX5: TZ0092 | BY5: 橱柜经销二部 | BZ5: 收入 | CA5: =CG5 -> 3.04 | CB5: 25.175 | CC5: 19.435 | CD5: 11.02 | CE5: 16.75 | CF5: 7.615 | CG5: 3.04 | CH5: 14.635 | CI5: 12.575 | CJ5: 11.99 | CK5: 23.57 | CL5: 15.84 | CM5: 4.675 | CN5: 166.32 | CO5: =SUMIFS(CB5:CM5,$F$2:$Q$2,"是") -> 83.035
A6: 橱柜经销一部 | B6: 收入 | C6: 按产品 | D6: OEM烟灶 | E6: =K6 -> 1051.0142 | F6: 545.97619 | G6: 194.04775 | H6: 960.76985 | I6: 964.26035 | J6: 1056.834 | K6: 1051.0142 | L6: 685.12106 | M6: 387.98021 | N6: 477.51717 | O6: 616.4769 | P6: 687.78849 | Q6: 498.93431 | R6: 8126.7205 | S6: =SUMIFS(F6:Q6,$F$2:$Q$2,"是") -> 4772.9023 | T6: 基数 | V6: 基数 | W6: 橱柜经销一部 | X6: 电费 | Y6: =AE6 -> 0.19544 | Z6: 0.10048 | AA6: 0.0652 | AB6: 0.12048 | AC6: 0.15072 | AD6: 0.16264 | AE6: 0.19544 | AF6: 0.22856 | AG6: 0.25512 | AH6: 0.24897 | AI6: 0.240921 | AJ6: 0.19969 | AK6: 0.15447 | AL6: 2.122691 | AM6: =SUMIFS(Z6:AK6,$Z$2:$AK$2,"是") -> 0.79496 | AP6: 1 | AQ6: 橱柜经销一部 | AR6: =AX6 -> 0.057155 | AS6: 4.589966 | AT6: 1.268917 | AU6: 2.067512 | AV6: 1.796353 | AW6: 0.845133 | AX6: 0.057155 | AY6: 3.029382 | AZ6: 3.240785 | BA6: 1.653571 | BB6: 0.80526 | BC6: 1.807054 | BD6: 0.715303 | BE6: 21.876391 | BF6: =SUMIFS(AS6:BD6,$AS$3:$BD$3,"是") -> 10.625036 | BG6: =BM6 -> 0.275 | BH6: 24.91 | BI6: 6.325 | BJ6: 10.56 | BK6: 10.055 | BL6: 4.16 | BM6: 0.275 | BN6: 14.415 | BO6: 15.13 | BP6: 7.59 | BQ6: 3.685 | BR6: 8.305 | BS6: 3.3 | BT6: 108.71 | BU6: =SUMIFS(BH6:BS6,$BH$3:$BS$3,"是") -> 56.285 | BX6: TZ0093 | BY6: 橱柜经销三分部 | BZ6: 收入 | CA6: =CG6 -> 0.22 | CB6: 19.55 | CC6: 1.87 | CD6: 6.92 | CE6: 2.385 | CF6: 3.165 | CG6: 0.22 | CH6: 11.765 | CI6: 12.545 | CJ6: 8.03 | CK6: 7.425 | CL6: 5.404 | CM6: 8.47 | CN6: 87.749 | CO6: =SUMIFS(CB6:CM6,$F$2:$Q$2,"是") -> 34.11
A7: 橱柜经销一部 | B7: 收入 | C7: 按产品 | D7: OEM其他 | E7: =K7 -> 1518.0457 | F7: 669.10002 | G7: 216.24924 | H7: 850.9555 | I7: 1216.2173 | J7: 1377.5036 | K7: 1518.0457 | L7: 1090.8743 | M7: 1322.7164 | N7: 1421.8503 | O7: 1302.6485 | P7: 1262.7462 | Q7: 1393.8252 | R7: 13642.732 | S7: =SUMIFS(F7:Q7,$F$2:$Q$2,"是") -> 5848.0713 | T7: 基数 | V7: 基数 | W7: 橱柜经销一部 | X7: 办公费 | Y7: =AE7 -> 2.5168612 | Z7: 0.789478 | AA7: 0.483046 | AB7: 0.311864 | AC7: 6.5112765 | AD7: 0.259553 | AE7: 2.5168612 | AF7: 2.4070954 | AG7: 2.079791 | AH7: 2.213605 | AI7: 2.126552 | AJ7: 1.4730034 | AK7: 2.921029 | AL7: 24.093155 | AM7: =SUMIFS(Z7:AK7,$Z$2:$AK$2,"是") -> 10.872079 | AO7: TZ0091 | AP7: 2 | AQ7: 其中：剔除礼包 | AR7: =AX7 -> 0.057155 | AS7: 4.589966 | AT7: 1.268917 | AU7: 2.067512 | AV7: 1.796353 | AW7: 0.845133 | AX7: 0.057155 | AY7: 3.029382 | AZ7: 3.240785 | BA7: 1.653571 | BB7: 0.80526 | BC7: 1.807054 | BD7: 0.715303 | BE7: 21.876391 | BF7: =SUMIFS(AS7:BD7,$AS$3:$BD$3,"是") -> 10.625036 | BG7: =BM7 -> 0.275 | BH7: 24.91 | BI7: 6.325 | BJ7: 10.56 | BK7: 10.055 | BL7: 4.16 | BM7: 0.275 | BN7: 14.415 | BO7: 15.13 | BP7: 7.59 | BQ7: 3.685 | BR7: 8.305 | BS7: 3.3 | BT7: 108.71 | BU7: =SUMIFS(BH7:BS7,$BH$3:$BS$3,"是") -> 56.285 | BX7: TZ0094 | BY7: 橱柜经销四部 | BZ7: 收入 | CA7: =CG7 -> 0.055 | CB7: 13.09 | CC7: 6.16 | CD7: 7.9 | CE7: 2.585 | CF7: 1.33 | CG7: 0.055 | CH7: 6.795 | CI7: 6.215 | CJ7: 2.835 | CK7: 3.575 | CL7: 3.025 | CM7: 6.93 | CN7: 60.495 | CO7: =SUMIFS(CB7:CM7,$F$2:$Q$2,"是") -> 31.12
A8: 橱柜经销一部 | B8: 收入 | C8: 按产品 | D8: 自制烟灶 | E8: =K8 -> 724.3066 | F8: 445.9957 | G8: 90.8991 | H8: 309.1492 | I8: 418.48435 | J8: 433.85455 | K8: 724.3066 | L8: 771.79107 | M8: 774.3538 | N8: 670.98247 | O8: 482.4488 | P8: 485.66195 | Q8: 571.36315 | R8: 6179.2907 | S8: =SUMIFS(F8:Q8,$F$2:$Q$2,"是") -> 2422.6895 | T8: 基数 | V8: 基数 | W8: 橱柜经销一部 | X8: 工资 | Y8: =AE8 -> -430.84342 | Z8: 68.702602 | AA8: 70.131083 | AB8: 66.026857 | AC8: 107.31734 | AD8: 81.418094 | AE8: -430.84342 | AF8: 126.01074 | AG8: 115.19098 | AH8: 85.470495 | AI8: 94.187383 | AJ8: 89.95371 | AK8: 210.13094 | AL8: 683.6968 | AM8: =SUMIFS(Z8:AK8,$Z$2:$AK$2,"是") -> -37.247446 | AP8: 3 | AQ8: 橱柜经销二部 | AR8: =AX8 -> 2.512677 | AS8: 4.886906 | AT8: 3.745348 | AU8: 2.116422 | AV8: 3.036339 | AW8: 1.592485 | AX8: 2.512677 | AY8: 1.676983 | AZ8: 2.69128 | BA8: 2.590064 | BB8: 5.154776 | BC8: 3.43844 | BD8: 1.024343 | BE8: 34.466063 | BF8: =SUMIFS(AS8:BD8,$AS$3:$BD$3,"是") -> 17.890177 | BG8: =BM8 -> 3.04 | BH8: 25.175 | BI8: 19.435 | BJ8: 11.02 | BK8: 16.75 | BL8: 7.615 | BM8: 3.04 | BN8: 14.635 | BO8: 12.575 | BP8: 11.99 | BQ8: 23.57 | BR8: 15.84 | BS8: 4.675 | BT8: 166.32 | BU8: =SUMIFS(BH8:BS8,$BH$3:$BS$3,"是") -> 83.035 | BX8: TZ0095 | BY8: 橱柜经销五部 | BZ8: 收入 | CA8: =CG8 -> 1.3 | CB8: 11.02 | CC8: 18.48 | CD8: 8.13 | CE8: 5.79 | CF8: 56.985 | CG8: 1.3 | CH8: 36.415 | CI8: 33.42 | CJ8: 17.19 | CK8: 8.165 | CL8: 40.135 | CM8: 16.17 | CN8: 253.2 | CO8: =SUMIFS(CB8:CM8,$F$2:$Q$2,"是") -> 101.705
A9: 橱柜经销一部 | B9: 收入 | C9: 按产品 | D9: 其他加收 | E9: =K9 -> 7.8366 | F9: 3.1685 | G9: 0.9922 | H9: 1.8536 | I9: 2.4893 | J9: 3.0266 | K9: 7.8366 | L9: 3.8791 | M9: 1.7751 | N9: 4.9834 | O9: 2.1527 | P9: 5.6105 | Q9: 5.9123 | R9: 43.6799 | S9: =SUMIFS(F9:Q9,$F$2:$Q$2,"是") -> 19.3668 | T9: 基数 | V9: 基数 | W9: 橱柜经销一部 | X9: 福利费 | Y9: =AE9 -> 7.6524583 | Z9: 7.6085803 | AA9: 13.419557 | AB9: 6.6804389 | AC9: 4.2535355 | AD9: 4.8920197 | AE9: 7.6524583 | AF9: 7.9889814 | AG9: 8.627493 | AH9: 6.868883 | AI9: 6.312455 | AJ9: 6.099349 | AK9: 6.371741 | AL9: 86.775492 | AM9: =SUMIFS(Z9:AK9,$Z$2:$AK$2,"是") -> 44.50659 | AO9: TZ0092 | AP9: 4 | AQ9: 其中：剔除礼包 | AR9: =AX9 -> 2.512677 | AS9: 4.886906 | AT9: 3.745348 | AU9: 2.116422 | AV9: 3.036339 | AW9: 1.592485 | AX9: 2.512677 | AY9: 1.676983 | AZ9: 2.69128 | BA9: 2.590064 | BB9: 5.154776 | BC9: 3.43844 | BD9: 1.024343 | BE9: 34.466063 | BF9: =SUMIFS(AS9:BD9,$AS$3:$BD$3,"是") -> 17.890177 | BG9: =BM9 -> 3.04 | BH9: 25.175 | BI9: 19.435 | BJ9: 11.02 | BK9: 16.75 | BL9: 7.615 | BM9: 3.04 | BN9: 14.635 | BO9: 12.575 | BP9: 11.99 | BQ9: 23.57 | BR9: 15.84 | BS9: 4.675 | BT9: 166.32 | BU9: =SUMIFS(BH9:BS9,$BH$3:$BS$3,"是") -> 83.035 | BX9: TZ0096 | BY9: 橱柜经销六部 | BZ9: 收入 | CA9: =CG9 -> 6.44 | CB9: 43.88 | CC9: 11.495 | CD9: 22.935 | CE9: 13.8 | CF9: 14.33 | CG9: 6.44 | CH9: 18.8 | CI9: 11.425 | CJ9: 19.255 | CK9: 13.915 | CL9: 10.615 | CM9: 23.265 | CN9: 210.155 | CO9: =SUMIFS(CB9:CM9,$F$2:$Q$2,"是") -> 112.88
A10: 橱柜经销一部 | B10: 收入 | C10: 按订单类型 | D10: 常规单 | E10: =K10 -> 6793.0988 | F10: 3948.2012 | G10: 1352.7048 | H10: 4024.0496 | I10: 5310.5349 | J10: 5868.1905 | K10: 6793.0988 | L10: 6228.5765 | M10: 6050.1384 | N10: 6036.9225 | O10: 5429.3277 | P10: 6023.0953 | Q10: 6016.7836 | R10: 63081.624 | S10: =SUMIFS(F10:Q10,$F$2:$Q$2,"是") -> 27296.78 | T10: 基数 | V10: 基数 | W10: 橱柜经销一部 | X10: 交通车辆费 | Y10: =AE10 -> 0.009 | Z10: 0.213314 | AA10: 0.094 | AB10: 0.09228 | AC10: 0.45 | AD10: 0 | AE10: 0.009 | AF10: 0.018 | AG10: 0 | AH10: 0.0135 | AI10: 0 | AJ10: 0.123 | AK10: 0.1445 | AL10: 1.157594 | AM10: =SUMIFS(Z10:AK10,$Z$2:$AK$2,"是") -> 0.858594 | AP10: 5 | AQ10: 橱柜经销三部 | AR10: =AX10 -> 0.045724 | AS10: 3.877786 | AT10: 0.375133 | AU10: 1.439067 | AV10: 0.478951 | AW10: 0.643334 | AX10: 0.045724 | AY10: 2.558844 | AZ10: 2.687273 | BA10: 1.749427 | BB10: 1.622539 | BC10: 1.099549 | BD10: 1.83593 | BE10: 18.413557 | BF10: =SUMIFS(AS10:BD10,$AS$3:$BD$3,"是") -> 6.859995 | BG10: =BM10 -> 0.22 | BH10: 19.55 | BI10: 1.87 | BJ10: 6.92 | BK10: 2.385 | BL10: 3.165 | BM10: 0.22 | BN10: 11.765 | BO10: 12.545 | BP10: 8.03 | BQ10: 7.425 | BR10: 5.404 | BS10: 8.47 | BT10: 87.749 | BU10: =SUMIFS(BH10:BS10,$BH$3:$BS$3,"是") -> 34.11 | BY10: 橱柜经销七部 | BZ10: 收入 | CA10: =CG10 -> 0 | CB10: 0 | CC10: 0 | CD10: 0 | CE10: 0 | CF10: 0 | CG10: 0 | CH10: 0 | CI10: 0 | CJ10: 0 | CK10: 0 | CL10: 0 | CM10: 0 | CN10: 0 | CO10: =SUMIFS(CB10:CM10,$F$2:$Q$2,"是") -> 0
A11: 橱柜经销一部 | B11: 收入 | C11: 按订单类型 | D11: 家装单 | E11: =K11 -> 654.9689 | F11: 369.5321 | G11: 56.2776 | H11: 285.4503 | I11: 467.4448 | J11: 576.6056 | K11: 654.9689 | L11: 676.5664 | M11: 744.7215 | N11: 21.2159 | O11: 594.5727 | P11: 626.0369 | Q11: 746.9981 | R11: 5820.3908 | S11: =SUMIFS(F11:Q11,$F$2:$Q$2,"是") -> 2410.2793 | T11: 基数 | V11: 基数 | W11: 橱柜经销一部 | X11: 运杂费 | Y11: =AE11 -> 85.802051 | Z11: 46.260708 | AA11: 14.357193 | AB11: 49.785689 | AC11: 68.743926 | AD11: 68.71566 | AE11: 85.802051 | AF11: 90.512756 | AG11: 83.98607 | AH11: 83.283247 | AI11: 72.282609 | AJ11: 82.640754 | AK11: 85.394917 | AL11: 831.76558 | AM11: =SUMIFS(Z11:AK11,$Z$2:$AK$2,"是") -> 333.66523 | AO11: TZ0093 | AP11: 6 | AQ11: 其中：剔除礼包 | AR11: =AX11 -> 0.045724 | AS11: 3.877786 | AT11: 0.375133 | AU11: 1.439067 | AV11: 0.478951 | AW11: 0.643334 | AX11: 0.045724 | AY11: 2.558844 | AZ11: 2.687273 | BA11: 1.749427 | BB11: 1.622539 | BC11: 1.099549 | BD11: 1.83593 | BE11: 18.413557 | BF11: =SUMIFS(AS11:BD11,$AS$3:$BD$3,"是") -> 6.859995 | BG11: =BM11 -> 0.22 | BH11: 19.55 | BI11: 1.87 | BJ11: 6.92 | BK11: 2.385 | BL11: 3.165 | BM11: 0.22 | BN11: 11.765 | BO11: 12.545 | BP11: 8.03 | BQ11: 7.425 | BR11: 5.404 | BS11: 8.47 | BT11: 87.749 | BU11: =SUMIFS(BH11:BS11,$BH$3:$BS$3,"是") -> 34.11 | BZ11: 合计 | CA11: =CG11 -> 11.33 | CB11: 137.625 | CC11: 63.765 | CD11: 67.465 | CE11: 51.365 | CF11: 87.585 | CG11: 11.33 | CH11: 102.825 | CI11: 91.31 | CJ11: 66.89 | CK11: 60.335 | CL11: 83.324 | CM11: 62.81 | CN11: 886.629 | CO11: =SUMIFS(CB11:CM11,$F$2:$Q$2,"是") -> 419.135
A12: 橱柜经销一部 | B12: 收入 | C12: 按订单类型 | D12: 直供单 | E12: =K12 -> 1224.82 | F12: 778.531 | G12: 198.7136 | H12: 755.588 | I12: 1063.6247 | J12: 1167.193 | K12: 1224.82 | L12: 1373.304 | M12: 1428.2792 | N12: 1835.3346 | O12: 1052.7613 | P12: 1032.3098 | Q12: 1142.3131 | R12: 13052.772 | S12: =SUMIFS(F12:Q12,$F$2:$Q$2,"是") -> 5188.4703 | T12: 基数 | V12: 基数 | W12: 橱柜经销一部 | X12: 差旅费 | Y12: =AE12 -> 19.80485 | Z12: -10.38555 | AA12: 2.3208 | AB12: 12.6304 | AC12: 44.692248 | AD12: 19.51595 | AE12: 19.80485 | AF12: 36.5181 | AG12: 27.363851 | AH12: 29.88065 | AI12: 23.9705 | AJ12: 29.6386 | AK12: 48.07405 | AL12: 284.02445 | AM12: =SUMIFS(Z12:AK12,$Z$2:$AK$2,"是") -> 88.578698 | AP12: 7 | AQ12: 橱柜经销四部 | AR12: =AX12 -> 0.011431 | AS12: 2.615818 | AT12: 1.235815 | AU12: 1.620089 | AV12: 0.479375 | AW12: 0.277986 | AX12: 0.011431 | AY12: 1.554557 | AZ12: 1.330982 | BA12: 0.617255 | BB12: 0.781222 | BC12: 0.653356 | BD12: 1.502137 | BE12: 12.680023 | BF12: =SUMIFS(AS12:BD12,$AS$3:$BD$3,"是") -> 6.240514 | BG12: =BM12 -> 0.055 | BH12: 13.09 | BI12: 6.16 | BJ12: 7.9 | BK12: 2.585 | BL12: 1.33 | BM12: 0.055 | BN12: 6.795 | BO12: 6.215 | BP12: 2.835 | BQ12: 3.575 | BR12: 3.025 | BS12: 6.93 | BT12: 60.495 | BU12: =SUMIFS(BH12:BS12,$BH$3:$BS$3,"是") -> 31.12 | BX12: TZ0091 | BY12: 橱柜经销一部 | BZ12: 成本 | CA12: =CG12 -> 0.217845 | CB12: 20.320034 | CC12: 5.056083 | CD12: 8.492488 | CE12: 8.258647 | CF12: 3.314867 | CG12: 0.217845 | CH12: 11.385618 | CI12: 11.889215 | CJ12: 5.936429 | CK12: 2.87974 | CL12: 6.497946 | CM12: 2.584697 | CN12: 86.833609 | CO12: =SUMIFS(CB12:CM12,$F$2:$Q$2,"是") -> 45.659964
A13: 橱柜经销一部 | B13: 收入 | C13: 按订单类型 | D13: 网销单 | E13: =K13 -> 0 | F13: 0.9592 | G13: 0 | H13: 0 | I13: 1.8725 | J13: 0 | K13: 0 | L13: 0 | M13: 0 | N13: 0 | O13: 0 | P13: 0 | Q13: 0 | R13: 2.8317 | S13: =SUMIFS(F13:Q13,$F$2:$Q$2,"是") -> 2.8317 | T13: 基数 | V13: 基数 | W13: 橱柜经销一部 | X13: 折旧费用 | Y13: =AE13 -> 0.093722 | Z13: 0.089844 | AA13: 0 | AB13: 0.179688 | AC13: 0.089844 | AD13: 0.093722 | AE13: 0.093722 | AF13: 0.100755 | AG13: 0.018988 | AH13: 0.028009 | AI13: 0.028009 | AJ13: 0.039333 | AK13: 0.359689 | AL13: 1.121603 | AM13: =SUMIFS(Z13:AK13,$Z$2:$AK$2,"是") -> 0.54682 | AO13: TZ0094 | AP13: 8 | AQ13: 其中：剔除礼包 | AR13: =AX13 -> 0.011431 | AS13: 2.615818 | AT13: 1.235815 | AU13: 1.620089 | AV13: 0.479375 | AW13: 0.277986 | AX13: 0.011431 | AY13: 1.554557 | AZ13: 1.330982 | BA13: 0.617255 | BB13: 0.781222 | BC13: 0.653356 | BD13: 1.502137 | BE13: 12.680023 | BF13: =SUMIFS(AS13:BD13,$AS$3:$BD$3,"是") -> 6.240514 | BG13: =BM13 -> 0.055 | BH13: 13.09 | BI13: 6.16 | BJ13: 7.9 | BK13: 2.585 | BL13: 1.33 | BM13: 0.055 | BN13: 6.795 | BO13: 6.215 | BP13: 2.835 | BQ13: 3.575 | BR13: 3.025 | BS13: 6.93 | BT13: 60.495 | BU13: =SUMIFS(BH13:BS13,$BH$3:$BS$3,"是") -> 31.12 | BX13: TZ0092 | BY13: 橱柜经销二部 | BZ13: 成本 | CA13: =CG13 -> 0.527323 | CB13: 20.288094 | CC13: 15.689652 | CD13: 8.903578 | CE13: 13.713661 | CF13: 6.022515 | CG13: 0.527323 | CH13: 12.958017 | CI13: 9.88372 | CJ13: 9.399936 | CK13: 18.415224 | CL13: 12.40156 | CM13: 3.650657 | CN13: 131.85394 | CO13: =SUMIFS(CB13:CM13,$F$2:$Q$2,"是") -> 65.144823
A14: 橱柜经销一部 | B14: 收入 | C14: 按订单类型 | D14: 星居单 | E14: =K14 -> 41.6034 | F14: 4.0245 | G14: 3.4637 | H14: 3.5934 | I14: 13.8617 | J14: 17.7585 | K14: 41.6034 | L14: 85.1252 | M14: 61.8364 | N14: 69.7909 | O14: 47.9083 | P14: 61.7251 | Q14: 77.2221 | R14: 487.9132 | S14: =SUMIFS(F14:Q14,$F$2:$Q$2,"是") -> 84.3052 | T14: 基数 | V14: 基数 | W14: 橱柜经销一部 | X14: 低值易耗品摊销 | Y14: =AE14 -> 0 | Z14: 0 | AA14: 0 | AB14: 0 | AC14: 0 | AD14: 0 | AE14: 0 | AF14: 0 | AG14: 0 | AH14: 0 | AI14: 0 | AJ14: 0 | AK14: 0 | AL14: 0 | AM14: =SUMIFS(Z14:AK14,$Z$2:$AK$2,"是") -> 0 | AP14: 9 | AQ14: 橱柜经销五分部 | AR14: =AX14 -> 0.656066 | AS14: 1.904806 | AT14: 3.356137 | AU14: 1.697109 | AV14: 1.525364 | AW14: 17.253666 | AX14: 0.656066 | AY14: 8.966632 | AZ14: 7.161739 | BA14: 3.744661 | BB14: 1.779124 | BC14: 8.681797 | BD14: 3.509264 | BE14: 60.236365 | BF14: =SUMIFS(AS14:BD14,$AS$3:$BD$3,"是") -> 26.393148 | BG14: =BM14 -> 1.3 | BH14: 11.02 | BI14: 18.48 | BJ14: 8.13 | BK14: 5.79 | BL14: 56.985 | BM14: 1.3 | BN14: 36.415 | BO14: 33.42 | BP14: 17.19 | BQ14: 8.165 | BR14: 40.135 | BS14: 16.17 | BT14: 253.2 | BU14: =SUMIFS(BH14:BS14,$BH$3:$BS$3,"是") -> 101.705 | BX14: TZ0093 | BY14: 橱柜经销三分部 | BZ14: 成本 | CA14: =CG14 -> 0.174276 | CB14: 15.672214 | CC14: 1.494867 | CD14: 5.480933 | CE14: 1.906049 | CF14: 2.521666 | CG14: 0.174276 | CH14: 9.206156 | CI14: 9.857727 | CJ14: 6.280573 | CK14: 5.802461 | CL14: 4.304451 | CM14: 6.63407 | CN14: 69.335443 | CO14: =SUMIFS(CB14:CM14,$F$2:$Q$2,"是") -> 27.250005
A15: 橱柜经销一部 | B15: 收入 | C15: 按订单类型 | D15: 微居单 | E15: =K15 -> 1.2518 | F15: 0 | G15: 0 | H15: 0 | I15: 0 | J15: 0 | K15: 1.2518 | L15: 4.6435 | M15: 0 | N15: 0 | O15: 14.7742 | P15: 10.3242 | Q15: 0.3745 | R15: 31.3682 | S15: =SUMIFS(F15:Q15,$F$2:$Q$2,"是") -> 1.2518 | T15: 基数 | V15: 基数 | W15: 橱柜经销一部 | X15: 展示设计点将费用 | Y15: =AE15 -> 0 | Z15: -124.99562 | AA15: 0 | AB15: 0 | AC15: 0.298 | AD15: 4.05 | AE15: 0 | AF15: 0.339 | AG15: 1.122 | AH15: 0 | AI15: 0.196 | AJ15: 0.045 | AK15: 47.56824 | AL15: -71.37738 | AM15: =SUMIFS(Z15:AK15,$Z$2:$AK$2,"是") -> -120.64762 | AO15: TZ0095 | AP15: 10 | AQ15: 其中：剔除礼包 | AR15: =AX15 -> 0.656066 | AS15: 1.904806 | AT15: 3.356137 | AU15: 1.697109 | AV15: 1.525364 | AW15: 17.253666 | AX15: 0.656066 | AY15: 8.966632 | AZ15: 7.161739 | BA15: 3.744661 | BB15: 1.779124 | BC15: 8.681797 | BD15: 3.509264 | BE15: 60.236365 | BF15: =SUMIFS(AS15:BD15,$AS$3:$BD$3,"是") -> 26.393148 | BG15: =BM15 -> 1.3 | BH15: 11.02 | BI15: 18.48 | BJ15: 8.13 | BK15: 5.79 | BL15: 56.985 | BM15: 1.3 | BN15: 36.415 | BO15: 33.42 | BP15: 17.19 | BQ15: 8.165 | BR15: 40.135 | BS15: 16.17 | BT15: 253.2 | BU15: =SUMIFS(BH15:BS15,$BH$3:$BS$3,"是") -> 101.705 | BX15: TZ0094 | BY15: 橱柜经销四部 | BZ15: 成本 | CA15: =CG15 -> 0.043569 | CB15: 10.474182 | CC15: 4.924185 | CD15: 6.279911 | CE15: 2.105625 | CF15: 1.052014 | CG15: 0.043569 | CH15: 5.240443 | CI15: 4.884018 | CJ15: 2.217745 | CK15: 2.793778 | CL15: 2.371644 | CM15: 5.427863 | CN15: 47.814977 | CO15: =SUMIFS(CB15:CM15,$F$2:$Q$2,"是") -> 24.879486
A16: 橱柜经销一部 | B16: 收入 | C16: 按合同类型 | D16: 普通单 | E16: =K16 -> 7118.1817 | F16: 4751.7043 | G16: 1259.4157 | H16: 4736.1823 | I16: 6403.8774 | J16: 6396.0269 | K16: 7118.1817 | L16: 6924.9352 | M16: 7127.7138 | N16: 6662.2736 | O16: 6332.3654 | P16: 7372.2437 | Q16: 7578.4362 | R16: 72663.356 | S16: =SUMIFS(F16:Q16,$F$2:$Q$2,"是") -> 30665.388 | T16: 基数 | V16: 基数 | W16: 橱柜经销一部 | X16: 百货广告费 | Y16: =AE16 -> 1006.0944 | Z16: 588.85822 | AA16: 185.98285 | AB16: 584.7668 | AC16: 792.31943 | AD16: 880.73341 | AE16: 1006.0944 | AF16: 966.39296 | AG16: 956.36817 | AH16: 919.39742 | AI16: 825.18638 | AJ16: 893.94852 | AK16: 919.65329 | AL16: 9519.7018 | AM16: =SUMIFS(Z16:AK16,$Z$2:$AK$2,"是") -> 4038.7551 | AP16: 11 | AQ16: 橱柜经销六分部 | AR16: =AX16 -> 1.334899 | AS16: 9.003928 | AT16: 2.316791 | AU16: 4.737704 | AV16: 2.640976 | AW16: 2.75695 | AX16: 1.334899 | AY16: 4.196915 | AZ16: 2.448849 | BA16: 4.189522 | BB16: 3.038406 | BC16: 2.292683 | BD16: 5.053039 | BE16: 44.010662 | BF16: =SUMIFS(AS16:BD16,$AS$3:$BD$3,"是") -> 22.791248 | BG16: =BM16 -> 6.44 | BH16: 43.88 | BI16: 11.495 | BJ16: 22.935 | BK16: 13.8 | BL16: 14.33 | BM16: 6.44 | BN16: 18.8 | BO16: 11.425 | BP16: 19.255 | BQ16: 13.915 | BR16: 10.615 | BS16: 23.265 | BT16: 210.155 | BU16: =SUMIFS(BH16:BS16,$BH$3:$BS$3,"是") -> 112.88 | BX16: TZ0095 | BY16: 橱柜经销五部 | BZ16: 成本 | CA16: =CG16 -> 0.643934 | CB16: 9.115194 | CC16: 15.123863 | CD16: 6.432891 | CE16: 4.264636 | CF16: 39.731334 | CG16: 0.643934 | CH16: 27.448368 | CI16: 26.258261 | CJ16: 13.445339 | CK16: 6.385876 | CL16: 31.453203 | CM16: 12.660736 | CN16: 192.96364 | CO16: =SUMIFS(CB16:CM16,$F$2:$Q$2,"是") -> 75.311852
A17: 橱柜经销一部 | B17: 收入 | C17: 按合同类型 | D17: 样品单 | E17: =K17 -> 1530.1929 | F17: 330.3433 | G17: 269.11331 | H17: 267.20432 | I17: 406.26941 | J17: 1161.1097 | K17: 1530.1929 | L17: 1380.4858 | M17: 1077.8366 | N17: 1219.1957 | O17: 722.47663 | P17: 295.55115 | Q17: 344.79109 | R17: 9004.57 | S17: =SUMIFS(F17:Q17,$F$2:$Q$2,"是") -> 3964.233 | T17: 基数 | V17: 基数 | W17: 橱柜经销一部 | X17: 收回费用 | Y17: =AE17 -> -58.949467 | Z17: 36.849646 | AA17: -3.289644 | AB17: -32.251506 | AC17: -64.99782 | AD17: -46.15686 | AE17: -58.949467 | AF17: -20.237917 | AG17: -50.092104 | AH17: -46.259381 | AI17: -49.943956 | AJ17: -44.197092 | AK17: -16.358691 | AL17: -395.88479 | AM17: =SUMIFS(Z17:AK17,$Z$2:$AK$2,"是") -> -168.79565 | AO17: TZ0096 | AP17: 12 | AQ17: 其中：剔除礼包 | AR17: =AX17 -> 1.334899 | AS17: 9.003928 | AT17: 2.316791 | AU17: 4.737704 | AV17: 2.640976 | AW17: 2.75695 | AX17: 1.334899 | AY17: 4.196915 | AZ17: 2.448849 | BA17: 4.189522 | BB17: 3.038406 | BC17: 2.292683 | BD17: 5.053039 | BE17: 44.010662 | BF17: =SUMIFS(AS17:BD17,$AS$3:$BD$3,"是") -> 22.791248 | BG17: =BM17 -> 6.44 | BH17: 43.88 | BI17: 11.495 | BJ17: 22.935 | BK17: 13.8 | BL17: 14.33 | BM17: 6.44 | BN17: 18.8 | BO17: 11.425 | BP17: 19.255 | BQ17: 13.915 | BR17: 10.615 | BS17: 23.265 | BT17: 210.155 | BU17: =SUMIFS(BH17:BS17,$BH$3:$BS$3,"是") -> 112.88 | BX17: TZ0096 | BY17: 橱柜经销六部 | BZ17: 成本 | CA17: =CG17 -> 5.105101 | CB17: 34.876072 | CC17: 9.178209 | CD17: 18.197296 | CE17: 11.159024 | CF17: 11.57305 | CG17: 5.105101 | CH17: 14.603085 | CI17: 8.976151 | CJ17: 15.065478 | CK17: 10.876594 | CL17: 8.322317 | CM17: 18.211961 | CN17: 166.14434 | CO17: =SUMIFS(CB17:CM17,$F$2:$Q$2,"是") -> 90.088752
A18: 橱柜经销一部 | B18: 收入 | C18: 按合同类型 | D18: 遗留单 | E18: =K18 -> 67.3683 | F18: 19.2004 | G18: 82.6307 | H18: 65.2946 | I18: 47.1918 | J18: 72.611 | K18: 67.3683 | L18: 62.7946 | M18: 79.425 | N18: 81.7945 | O18: 84.5022 | P18: 85.6964 | Q18: 60.4641 | R18: 808.9736 | S18: =SUMIFS(F18:Q18,$F$2:$Q$2,"是") -> 354.2968 | T18: 基数 | V18: 基数 | W18: 橱柜经销一部 | X18: 培训费 | Y18: =AE18 -> 0 | Z18: 0 | AA18: 0 | AB18: 0 | AC18: 0 | AD18: 3 | AE18: 0 | AF18: 0 | AG18: 0 | AH18: 0 | AI18: 0 | AJ18: 1.31 | AK18: 0 | AL18: 4.31 | AM18: =SUMIFS(Z18:AK18,$Z$2:$AK$2,"是") -> 3 | AP18: 13 | AQ18: 厨电百货经销部-直售 | AR18: =AX18 -> 0 | AS18: 0 | AT18: 0 | AU18: 0 | AV18: 0 | AW18: 0 | AX18: 0 | AY18: 0 | AZ18: 0 | BA18: 0 | BB18: 0 | BC18: 0 | BD18: 0 | BE18: 0 | BF18: =SUMIFS(AS18:BD18,$AS$3:$BD$3,"是") -> 0 | BG18: =BM18 -> 0 | BH18: 0 | BI18: 0 | BJ18: 0 | BK18: 0 | BL18: 0 | BM18: 0 | BN18: 0 | BO18: 0 | BP18: 0 | BQ18: 0 | BR18: 0 | BS18: 0 | BT18: 0 | BU18: =SUMIFS(BH18:BS18,$BH$3:$BS$3,"是") -> 0 | BY18: 橱柜经销七部 | CA18: =CG18 -> 0 | CB18: 0 | CC18: 0 | CD18: 0 | CE18: 0 | CF18: 0 | CG18: 0 | CH18: 0 | CI18: 0 | CJ18: 0 | CK18: 0 | CL18: 0 | CM18: 0 | CN18: 0 | CO18: =SUMIFS(CB18:CM18,$F$2:$Q$2,"是") -> 0
A19: 橱柜经销一部 | B19: 成本 | C19: 按产品 | D19: 柜门 | E19: =K19 -> 2443.0378 | F19: 1702.0842 | G19: 546.58391 | H19: 1499.6289 | I19: 1789.7766 | J19: 2257.142 | K19: 2443.0378 | L19: 2735.2125 | M19: 2756.9694 | N19: 2515.0532 | O19: 2154.1072 | P19: 2366.0543 | Q19: 2394.2617 | R19: 25159.912 | S19: =SUMIFS(F19:Q19,$F$2:$Q$2,"是") -> 10238.253 | T19: 基数 | V19: 基数 | W19: 橱柜经销一部 | X19: 税款 | Y19: =AE19 -> 0 | Z19: 0 | AA19: 0 | AB19: 0 | AC19: 0 | AD19: 0 | AE19: 0 | AF19: 0 | AG19: 0 | AH19: 0 | AI19: 0 | AJ19: 0 | AK19: 0 | AL19: 0 | AM19: =SUMIFS(Z19:AK19,$Z$2:$AK$2,"是") -> 0 | AP19: 14 | AQ19: 橱柜营销利润中心合计 | AR19: =AX19 -> 4.617952 | AS19: 26.87921 | AT19: 12.298141 | AU19: 13.677903 | AV19: 9.957358 | AW19: 23.369554 | AX19: 4.617952 | AY19: 21.983313 | AZ19: 19.560908 | BA19: 14.5445 | BB19: 13.181327 | BC19: 17.972879 | BD19: 13.640016 | BE19: 191.68306 | BF19: =SUMIFS(AS19:BD19,$AS$3:$BD$3,"是") -> 90.800118 | BG19: =BM19 -> 11.33 | BH19: 137.625 | BI19: 63.765 | BJ19: 67.465 | BK19: 51.365 | BL19: 87.585 | BM19: 11.33 | BN19: 102.825 | BO19: 91.31 | BP19: 66.89 | BQ19: 60.335 | BR19: 83.324 | BS19: 62.81 | BT19: 886.629 | BU19: =SUMIFS(BH19:BS19,$BH$3:$BS$3,"是") -> 419.135 | BZ19: 合计 | CA19: =CG19 -> 6.712048 | CB19: 110.74579 | CC19: 51.466859 | CD19: 53.787097 | CE19: 41.407642 | CF19: 64.215446 | CG19: 6.712048 | CH19: 80.841687 | CI19: 71.749092 | CJ19: 52.3455 | CK19: 47.153673 | CL19: 65.351121 | CM19: 49.169984 | CN19: 694.94594 | CO19: =SUMIFS(CB19:CM19,$F$2:$Q$2,"是") -> 328.33488
A20: 橱柜经销一部 | B20: 成本 | C20: 按产品 | D20: 台面 | E20: =K20 -> 1457.7964 | F20: 873.89184 | G20: 337.84003 | H20: 738.579 | I20: 1049.7702 | J20: 1435.4915 | K20: 1457.7964 | L20: 1429.5327 | M20: 1354.4627 | N20: 1292.4731 | O20: 1193.5503 | P20: 1386.1763 | Q20: 1454.2295 | R20: 14003.794 | S20: =SUMIFS(F20:Q20,$F$2:$Q$2,"是") -> 5893.369 | T20: 基数 | V20: 基数 | W20: 橱柜经销一部 | X20: 资金占用费 | Y20: =AE20 -> 0.0002 | Z20: 0.6042 | AA20: 0.9428 | AB20: 0.9689 | AC20: 3.8761 | AD20: 0.0211 | AE20: 0.0002 | AF20: 0.1392 | AG20: 0.0002 | AH20: 0.2342 | AI20: 0.139 | AJ20: 0.6142 | AK20: 0.5514 | AL20: 8.0915 | AM20: =SUMIFS(Z20:AK20,$Z$2:$AK$2,"是") -> 6.4133 | AP20: 15 | AQ20: 其中：剔除礼包 | AR20: =AX20 -> 4.617952 | AS20: 26.87921 | AT20: 12.298141 | AU20: 13.677903 | AV20: 9.957358 | AW20: 23.369554 | AX20: 4.617952 | AY20: 21.983313 | AZ20: 19.560908 | BA20: 14.5445 | BB20: 13.181327 | BC20: 17.972879 | BD20: 13.640016 | BE20: 191.68306 | BF20: =SUMIFS(AS20:BD20,$AS$3:$BD$3,"是") -> 90.800118 | BG20: =BM20 -> 11.33 | BH20: 137.625 | BI20: 63.765 | BJ20: 67.465 | BK20: 51.365 | BL20: 87.585 | BM20: 11.33 | BN20: 102.825 | BO20: 91.31 | BP20: 66.89 | BQ20: 60.335 | BR20: 83.324 | BS20: 62.81 | BT20: 886.629 | BU20: =SUMIFS(BH20:BS20,$BH$3:$BS$3,"是") -> 419.135 | BX20: TZ0091 | BY20: 橱柜经销一部 | BZ20: 毛利 | CA20: =CG20 -> 0.057155 | CB20: 4.589966 | CC20: 1.268917 | CD20: 2.067512 | CE20: 1.796353 | CF20: 0.845133 | CG20: 0.057155 | CH20: 3.029382 | CI20: 3.240785 | CJ20: 1.653571 | CK20: 0.80526 | CL20: 1.807054 | CM20: 0.715303 | CN20: 21.876391 | CO20: =SUMIFS(CB20:CM20,$F$2:$Q$2,"是") -> 10.625036
A21: 橱柜经销一部 | B21: 成本 | C21: 按产品 | D21: OEM烟灶 | E21: =K21 -> 694.03108 | F21: 365.45227 | G21: 142.67827 | H21: 631.66865 | I21: 632.67797 | J21: 670.33671 | K21: 694.03108 | L21: 446.75619 | M21: 255.64906 | N21: 335.20915 | O21: 441.19858 | P21: 505.39399 | Q21: 304.4219 | R21: 5425.4738 | S21: =SUMIFS(F21:Q21,$F$2:$Q$2,"是") -> 3136.8449 | T21: 基数 | V21: 基数 | W21: 橱柜经销一部 | X21: 业务招待费 | Y21: =AE21 -> 0 | Z21: 0.8399 | AA21: 0 | AB21: 0.4522 | AC21: 0.3867 | AD21: 0.0425 | AE21: 0 | AF21: 0.3313 | AG21: 0.1946 | AH21: 0.2577 | AI21: 0.035 | AJ21: 0 | AK21: 0.165 | AL21: 2.7049 | AM21: =SUMIFS(Z21:AK21,$Z$2:$AK$2,"是") -> 1.7213 | AP21: 16 | AQ21: 橱柜培训部 | AR21: =AX21 -> 0 | AS21: 0 | AT21: 0 | AU21: 0 | AV21: 0 | AW21: 0 | AX21: 0 | AY21: 0 | AZ21: 0 | BA21: 0 | BB21: 0 | BC21: 0 | BD21: 0 | BE21: 0 | BF21: =SUMIFS(AS21:BD21,$AS$3:$BD$3,"是") -> 0 | BG21: =BM21 -> 0 | BH21: 0 | BI21: 0 | BJ21: 0 | BK21: 0 | BL21: 0 | BM21: 0 | BN21: 0 | BO21: 0 | BP21: 0 | BQ21: 0 | BR21: 0 | BS21: 0 | BT21: 0 | BU21: =SUMIFS(BH21:BS21,$BH$3:$BS$3,"是") -> 0 | BX21: TZ0092 | BY21: 橱柜经销二部 | BZ21: 毛利 | CA21: =CG21 -> 2.512677 | CB21: 4.886906 | CC21: 3.745348 | CD21: 2.116422 | CE21: 3.036339 | CF21: 1.592485 | CG21: 2.512677 | CH21: 1.676983 | CI21: 2.69128 | CJ21: 2.590064 | CK21: 5.154776 | CL21: 3.43844 | CM21: 1.024343 | CN21: 34.466063 | CO21: =SUMIFS(CB21:CM21,$F$2:$Q$2,"是") -> 17.890177
A22: 橱柜经销一部 | B22: 成本 | C22: 按产品 | D22: OEM其他 | E22: =K22 -> 876.04334 | F22: 367.77592 | G22: 118.27083 | H22: 485.30963 | I22: 708.07367 | J22: 877.64814 | K22: 876.04334 | L22: 1104.7998 | M22: 772.17408 | N22: 818.87342 | O22: 737.73048 | P22: 710.58104 | Q22: 771.64711 | R22: 8348.9275 | S22: =SUMIFS(F22:Q22,$F$2:$Q$2,"是") -> 3433.1215 | T22: 基数 | V22: 基数 | W22: 橱柜经销一部 | X22: 质量赔偿费 | Y22: =AE22 -> -0.042 | Z22: 0 | AA22: 0 | AB22: 0 | AC22: 0 | AD22: 0 | AE22: -0.042 | AF22: 0 | AG22: 0 | AH22: 0 | AI22: 0 | AJ22: 0 | AK22: -0.376 | AL22: -0.418 | AM22: =SUMIFS(Z22:AK22,$Z$2:$AK$2,"是") -> -0.042 | AP22: 17 | AQ22: 橱柜营销服务支持部 | AR22: =AX22 -> 0 | AS22: 0 | AT22: 0 | AU22: 0 | AV22: 0 | AW22: 0 | AX22: 0 | AY22: 0 | AZ22: 0 | BA22: 0 | BB22: 0 | BC22: 0 | BD22: 0 | BE22: 0 | BF22: =SUMIFS(AS22:BD22,$AS$3:$BD$3,"是") -> 0 | BG22: =BM22 -> 0 | BH22: 0 | BI22: 0 | BJ22: 0 | BK22: 0 | BL22: 0 | BM22: 0 | BN22: 0 | BO22: 0 | BP22: 0 | BQ22: 0 | BR22: 0 | BS22: 0 | BT22: 0 | BU22: =SUMIFS(BH22:BS22,$BH$3:$BS$3,"是") -> 0 | BX22: TZ0093 | BY22: 橱柜经销三分部 | BZ22: 毛利 | CA22: =CG22 -> 0.045724 | CB22: 3.877786 | CC22: 0.375133 | CD22: 1.439067 | CE22: 0.478951 | CF22: 0.643334 | CG22: 0.045724 | CH22: 2.558844 | CI22: 2.687273 | CJ22: 1.749427 | CK22: 1.622539 | CL22: 1.099549 | CM22: 1.83593 | CN22: 18.413557 | CO22: =SUMIFS(CB22:CM22,$F$2:$Q$2,"是") -> 6.859995
A23: 橱柜经销一部 | B23: 成本 | C23: 按产品 | D23: 自制烟灶 | E23: =K23 -> 410.65288 | F23: 248.76788 | G23: 50.224854 | H23: 167.46583 | I23: 226.54801 | J23: 234.02531 | K23: 410.65288 | L23: 436.81997 | M23: 450.92019 | N23: 377.14224 | O23: 271.81043 | P23: 273.94828 | Q23: 316.4573 | R23: 3464.7832 | S23: =SUMIFS(F23:Q23,$F$2:$Q$2,"是") -> 1337.6848 | T23: 基数 | V23: 基数 | W23: 橱柜经销一部 | X23: 其他 | Y23: =AE23 -> 2.5108628 | Z23: 0.871013 | AA23: -52.39748 | AB23: 3.2712085 | AC23: -1.4141644 | AD23: 0.51772634 | AE23: 2.5108628 | AF23: 6.2721392 | AG23: 1.52172 | AH23: 4.3464564 | AI23: -0.45225194 | AJ23: 1.9567495 | AK23: 1.9360607 | AL23: -31.05996 | AM23: =SUMIFS(Z23:AK23,$Z$2:$AK$2,"是") -> -46.640834 | AP23: 18 | AQ23: 橱柜展示设计部 | AR23: =AX23 -> 0 | AS23: 0 | AT23: 0 | AU23: 0 | AV23: 0 | AW23: 0 | AX23: 0 | AY23: 0 | AZ23: 0 | BA23: 0 | BB23: 0 | BC23: 0 | BD23: 0 | BE23: 0 | BF23: =SUMIFS(AS23:BD23,$AS$3:$BD$3,"是") -> 0 | BG23: =BM23 -> 0 | BH23: 0 | BI23: 0 | BJ23: 0 | BK23: 0 | BL23: 0 | BM23: 0 | BN23: 0 | BO23: 0 | BP23: 0 | BQ23: 0 | BR23: 0 | BS23: 0 | BT23: 0 | BU23: =SUMIFS(BH23:BS23,$BH$3:$BS$3,"是") -> 0 | BX23: TZ0094 | BY23: 橱柜经销四部 | BZ23: 毛利 | CA23: =CG23 -> 0.011431 | CB23: 2.615818 | CC23: 1.235815 | CD23: 1.620089 | CE23: 0.479375 | CF23: 0.277986 | CG23: 0.011431 | CH23: 1.554557 | CI23: 1.330982 | CJ23: 0.617255 | CK23: 0.781222 | CL23: 0.653356 | CM23: 1.502137 | CN23: 12.680023 | CO23: =SUMIFS(CB23:CM23,$F$2:$Q$2,"是") -> 6.240514
A24: 橱柜经销一部 | B24: 成本 | C24: 按产品 | D24: 其他加收 | E24: =K24 -> 0 | F24: 0 | G24: 0 | H24: 0 | I24: 0 | J24: 0 | K24: 0 | L24: 0 | M24: 0 | N24: 0 | O24: 0 | P24: 0 | Q24: 0 | R24: 0 | S24: =SUMIFS(F24:Q24,$F$2:$Q$2,"是") -> 0 | T24: 基数 | V24: 基数 | W24: 橱柜经销一部 | X24: 百货进出仓 | Y24: =AE24 -> 0 | Z24: 0 | AA24: 0 | AB24: 0 | AC24: 0 | AD24: 0 | AE24: 0 | AF24: 0 | AG24: 0 | AH24: 0 | AI24: 0 | AJ24: 0 | AK24: 0 | AL24: 0 | AM24: =SUMIFS(Z24:AK24,$Z$2:$AK$2,"是") -> 0 | AP24: 19 | AQ24: 厨电百货售后服务部 | AR24: =AX24 -> 0 | AS24: 0 | AT24: 0 | AU24: 0 | AV24: 0 | AW24: 0 | AX24: 0 | AY24: 0 | AZ24: 0 | BA24: 0 | BB24: 0 | BC24: 0 | BD24: 0 | BE24: 0 | BF24: =SUMIFS(AS24:BD24,$AS$3:$BD$3,"是") -> 0 | BG24: =BM24 -> 0 | BH24: 0 | BI24: 0 | BJ24: 0 | BK24: 0 | BL24: 0 | BM24: 0 | BN24: 0 | BO24: 0 | BP24: 0 | BQ24: 0 | BR24: 0 | BS24: 0 | BT24: 0 | BU24: =SUMIFS(BH24:BS24,$BH$3:$BS$3,"是") -> 0 | BX24: TZ0095 | BY24: 橱柜经销五部 | BZ24: 毛利 | CA24: =CG24 -> 0.656066 | CB24: 1.904806 | CC24: 3.356137 | CD24: 1.697109 | CE24: 1.525364 | CF24: 17.253666 | CG24: 0.656066 | CH24: 8.966632 | CI24: 7.161739 | CJ24: 3.744661 | CK24: 1.779124 | CL24: 8.681797 | CM24: 3.509264 | CN24: 60.236365 | CO24: =SUMIFS(CB24:CM24,$F$2:$Q$2,"是") -> 26.393148
A25: 橱柜经销一部 | B25: 成本 | C25: 按订单类型 | D25: 常规单 | E25: =K25 -> 4414.7832 | F25: 2637.3831 | G25: 991.86565 | H25: 2662.8773 | I25: 3399.7713 | J25: 3873.3673 | K25: 4414.7832 | L25: 4544.5743 | M25: 3937.8789 | N25: 3949.3344 | O25: 3520.9297 | P25: 3915.6345 | Q25: 3801.1457 | R25: 41649.545 | S25: =SUMIFS(F25:Q25,$F$2:$Q$2,"是") -> 17980.048 | T25: 基数 | V25: 基数 | W25: 橱柜经销一部 | X25: 展厅装修费用 | Y25: =AE25 -> 0 | Z25: 0 | AA25: 0 | AB25: 0 | AC25: 0 | AD25: 0 | AE25: 0 | AF25: 0 | AG25: 0 | AH25: 0 | AI25: 0 | AJ25: 0 | AK25: 0 | AL25: 0 | AM25: =SUMIFS(Z25:AK25,$Z$2:$AK$2,"是") -> 0 | AP25: 20 | AQ25: 橱柜招商部 | AR25: =AX25 -> 0 | AS25: 0 | AT25: 0 | AU25: 0 | AV25: 0 | AW25: 0 | AX25: 0 | AY25: 0 | AZ25: 0 | BA25: 0 | BB25: 0 | BC25: 0 | BD25: 0 | BE25: 0 | BF25: =SUMIFS(AS25:BD25,$AS$3:$BD$3,"是") -> 0 | BG25: =BM25 -> 0 | BH25: 0 | BI25: 0 | BJ25: 0 | BK25: 0 | BL25: 0 | BM25: 0 | BN25: 0 | BO25: 0 | BP25: 0 | BQ25: 0 | BR25: 0 | BS25: 0 | BT25: 0 | BU25: =SUMIFS(BH25:BS25,$BH$3:$BS$3,"是") -> 0 | BX25: TZ0096 | BY25: 橱柜经销六部 | BZ25: 毛利 | CA25: =CG25 -> 1.334899 | CB25: 9.003928 | CC25: 2.316791 | CD25: 4.737704 | CE25: 2.640976 | CF25: 2.75695 | CG25: 1.334899 | CH25: 4.196915 | CI25: 2.448849 | CJ25: 4.189522 | CK25: 3.038406 | CL25: 2.292683 | CM25: 5.053039 | CN25: 44.010662 | CO25: =SUMIFS(CB25:CM25,$F$2:$Q$2,"是") -> 22.791248
A26: 橱柜经销一部 | B26: 成本 | C26: 按订单类型 | D26: 家装单 | E26: =K26 -> 532.38733 | F26: 314.26584 | G26: 47.774496 | H26: 259.65729 | I26: 325.07312 | J26: 586.47783 | K26: 532.38733 | L26: 535.24602 | M26: 578.17554 | N26: 16.976962 | O26: 471.19411 | P26: 523.30491 | Q26: 578.22696 | R26: 4768.7604 | S26: =SUMIFS(F26:Q26,$F$2:$Q$2,"是") -> 2065.6359 | T26: 基数 | V26: 基数 | W26: 橱柜经销一部 | X26: 政府补贴 | Y26: =AE26 -> 0 | Z26: 0 | AA26: 0 | AB26: 0 | AC26: 0 | AD26: 0 | AE26: 0 | AF26: 0 | AG26: 0 | AH26: 0 | AI26: 0 | AJ26: 0 | AK26: 0 | AL26: 0 | AM26: =SUMIFS(Z26:AK26,$Z$2:$AK$2,"是") -> 0 | AP26: 21 | AQ26: 厨电百货供应服务分部 | AR26: =AX26 -> 0 | AS26: 0 | AT26: 0 | AU26: 0 | AV26: 0 | AW26: 0 | AX26: 0 | AY26: 0 | AZ26: 0 | BA26: 0 | BB26: 0 | BC26: 0 | BD26: 0 | BE26: 0 | BF26: =SUMIFS(AS26:BD26,$AS$3:$BD$3,"是") -> 0 | BG26: =BM26 -> 0 | BH26: 0 | BI26: 0 | BJ26: 0 | BK26: 0 | BL26: 0 | BM26: 0 | BN26: 0 | BO26: 0 | BP26: 0 | BQ26: 0 | BR26: 0 | BS26: 0 | BT26: 0 | BU26: =SUMIFS(BH26:BS26,$BH$3:$BS$3,"是") -> 0 | BY26: 橱柜经销七部 | BZ26: 毛利 | CA26: =CG26 -> 0 | CB26: 0 | CC26: 0 | CD26: 0 | CE26: 0 | CF26: 0 | CG26: 0 | CH26: 0 | CI26: 0 | CJ26: 0 | CK26: 0 | CL26: 0 | CM26: 0 | CN26: 0 | CO26: =SUMIFS(CB26:CM26,$F$2:$Q$2,"是") -> 0
A27: 橱柜经销一部 | B27: 成本 | C27: 按订单类型 | D27: 直供单 | E27: =K27 -> 899.88955 | F27: 602.68759 | G27: 153.47938 | H27: 597.45374 | I27: 669.76321 | J27: 1001.4182 | K27: 899.88955 | L27: 1000.7527 | M27: 1025.4231 | N27: 1320.5086 | O27: 760.69812 | P27: 752.97379 | Q27: 810.17293 | R27: 9595.2209 | S27: =SUMIFS(F27:Q27,$F$2:$Q$2,"是") -> 3924.6917 | T27: 基数 | V27: 基数 | W27: 橱柜经销一部 | X27: 经销商会议费用 | Y27: =AE27 -> 0 | Z27: 0 | AA27: 0 | AB27: 0 | AC27: 0 | AD27: 0 | AE27: 0 | AF27: 0 | AG27: 0 | AH27: 0 | AI27: 0 | AJ27: 0 | AK27: 0 | AL27: 0 | AM27: =SUMIFS(Z27:AK27,$Z$2:$AK$2,"是") -> 0 | AP27: 22 | AQ27: 橱柜营销数据支部 | AR27: =AX27 -> 0 | AS27: 0 | AT27: 0 | AU27: 0 | AV27: 0 | AW27: 0 | AX27: 0 | AY27: 0 | AZ27: 0 | BA27: 0 | BB27: 0 | BC27: 0 | BD27: 0 | BE27: 0 | BF27: =SUMIFS(AS27:BD27,$AS$3:$BD$3,"是") -> 0 | BG27: =BM27 -> 0 | BH27: 0 | BI27: 0 | BJ27: 0 | BK27: 0 | BL27: 0 | BM27: 0 | BN27: 0 | BO27: 0 | BP27: 0 | BQ27: 0 | BR27: 0 | BS27: 0 | BT27: 0 | BU27: =SUMIFS(BH27:BS27,$BH$3:$BS$3,"是") -> 0 | BZ27: 合计 | CA27: =CG27 -> 4.617952 | CB27: 26.87921 | CC27: 12.298141 | CD27: 13.677903 | CE27: 9.957358 | CF27: 23.369554 | CG27: 4.617952 | CH27: 21.983313 | CI27: 19.560908 | CJ27: 14.5445 | CK27: 13.181327 | CL27: 17.972879 | CM27: 13.640016 | CN27: 191.68306 | CO27: =SUMIFS(CB27:CM27,$F$2:$Q$2,"是") -> 90.800118
A28: 橱柜经销一部 | B28: 成本 | C28: 按订单类型 | D28: 网销单 | E28: =K28 -> 0 | F28: 0.75003752 | G28: 0 | H28: 0 | I28: 1.4036896 | J28: 0 | K28: 0 | L28: 0 | M28: 0 | N28: 0 | O28: 0 | P28: 0 | Q28: 0 | R28: 2.1537271 | S28: =SUMIFS(F28:Q28,$F$2:$Q$2,"是") -> 2.1537271 | T28: 基数 | V28: 基数 | W28: 橱柜经销一部 | X28: 软件提点 | Y28: =AE28 -> 0 | Z28: 0 | AA28: 0 | AB28: 0 | AC28: 0 | AD28: 0 | AE28: 0 | AF28: 0 | AG28: 0 | AH28: 0 | AI28: 0 | AJ28: 0 | AK28: 0 | AL28: 0 | AM28: =SUMIFS(Z28:AK28,$Z$2:$AK$2,"是") -> 0 | AP28: 23 | AQ28: 橱柜市场部 | AR28: =AX28 -> 0 | AS28: 0 | AT28: 0 | AU28: 0 | AV28: 0 | AW28: 0 | AX28: 0 | AY28: 0 | AZ28: 0 | BA28: 0 | BB28: 0 | BC28: 0 | BD28: 0 | BE28: 0 | BF28: =SUMIFS(AS28:BD28,$AS$3:$BD$3,"是") -> 0 | BG28: =BM28 -> 0 | BH28: 0 | BI28: 0 | BJ28: 0 | BK28: 0 | BL28: 0 | BM28: 0 | BN28: 0 | BO28: 0 | BP28: 0 | BQ28: 0 | BR28: 0 | BS28: 0 | BT28: 0 | BU28: =SUMIFS(BH28:BS28,$BH$3:$BS$3,"是") -> 0 | BX28: TZ0091 | BY28: 橱柜经销一部 | BZ28: 利润 | CA28: =CG28 -> 0.057155 | CB28: 4.589966 | CC28: 1.268917 | CD28: 2.067512 | CE28: 1.796353 | CF28: 0.845133 | CG28: 0.057155 | CH28: 3.029382 | CI28: 3.240785 | CJ28: 1.653571 | CK28: 0.80526 | CL28: 1.807054 | CM28: 0.715303 | CN28: 21.876391 | CO28: =SUMIFS(CB28:CM28,$F$2:$Q$2,"是") -> 10.625036
A29: 橱柜经销一部 | B29: 成本 | C29: 按订单类型 | D29: 星居单 | E29: =K29 -> 33.479446 | F29: 2.8855209 | G29: 2.4783645 | H29: 2.6637083 | I29: 10.835236 | J29: 13.380293 | K29: 33.479446 | L29: 68.788755 | M29: 48.697886 | N29: 51.931221 | O29: 33.870897 | P29: 41.957374 | Q29: 51.335355 | R29: 362.30406 | S29: =SUMIFS(F29:Q29,$F$2:$Q$2,"是") -> 65.722569 | T29: 基数 | V29: 基数 | W29: 橱柜经销一部 | X29: 材料成本差异 | Y29: =AE29 -> 0 | Z29: 0 | AA29: 0 | AB29: 0 | AC29: 0 | AD29: 0 | AE29: 0 | AF29: 0 | AG29: 0 | AH29: 0 | AI29: 0 | AJ29: 0 | AK29: 0 | AL29: 0 | AM29: =SUMIFS(Z29:AK29,$Z$2:$AK$2,"是") -> 0 | AP29: 24 | AQ29: 橱柜主动营销部 | AR29: =AX29 -> 0 | AS29: 0 | AT29: 0 | AU29: 0 | AV29: 0 | AW29: 0 | AX29: 0 | AY29: 0 | AZ29: 0 | BA29: 0 | BB29: 0 | BC29: 0 | BD29: 0 | BE29: 0 | BF29: =SUMIFS(AS29:BD29,$AS$3:$BD$3,"是") -> 0 | BG29: =BM29 -> 0 | BH29: 0 | BI29: 0 | BJ29: 0 | BK29: 0 | BL29: 0 | BM29: 0 | BN29: 0 | BO29: 0 | BP29: 0 | BQ29: 0 | BR29: 0 | BS29: 0 | BT29: 0 | BU29: =SUMIFS(BH29:BS29,$BH$3:$BS$3,"是") -> 0 | BX29: TZ0092 | BY29: 橱柜经销二部 | BZ29: 利润 | CA29: =CG29 -> 2.512677 | CB29: 4.886906 | CC29: 3.745348 | CD29: 2.116422 | CE29: 3.036339 | CF29: 1.592485 | CG29: 2.512677 | CH29: 1.676983 | CI29: 2.69128 | CJ29: 2.590064 | CK29: 5.154776 | CL29: 3.43844 | CM29: 1.024343 | CN29: 34.466063 | CO29: =SUMIFS(CB29:CM29,$F$2:$Q$2,"是") -> 17.890177
A30: 橱柜经销一部 | B30: 成本 | C30: 按订单类型 | D30: 微居单 | E30: =K30 -> 1.0219387 | F30: 0 | G30: 0 | H30: 0 | I30: 0 | J30: 0 | K30: 1.0219387 | L30: 3.7594012 | M30: 0 | N30: 0 | O30: 11.704263 | P30: 8.2833264 | Q30: 0.13657812 | R30: 24.905507 | S30: =SUMIFS(F30:Q30,$F$2:$Q$2,"是") -> 1.0219387 | T30: 基数 | V30: 基数 | W30: 橱柜经销一部 | X30: 维修费 | Y30: =AE30 -> 0 | Z30: 0 | AA30: 0 | AB30: 0 | AC30: 0 | AD30: 0 | AE30: 0 | AF30: 0 | AG30: 0 | AH30: 0 | AI30: 0 | AJ30: 0 | AK30: 0 | AL30: 0 | AM30: =SUMIFS(Z30:AK30,$Z$2:$AK$2,"是") -> 0 | AP30: 25 | AQ30: 橱柜渠道拓展部 | AR30: =AX30 -> 0 | AS30: 0 | AT30: 0 | AU30: 0 | AV30: 0 | AW30: 0 | AX30: 0 | AY30: 0 | AZ30: 0 | BA30: 0 | BB30: 0 | BC30: 0 | BD30: 0 | BE30: 0 | BF30: =SUMIFS(AS30:BD30,$AS$3:$BD$3,"是") -> 0 | BG30: =BM30 -> 0 | BH30: 0 | BI30: 0 | BJ30: 0 | BK30: 0 | BL30: 0 | BM30: 0 | BN30: 0 | BO30: 0 | BP30: 0 | BQ30: 0 | BR30: 0 | BS30: 0 | BT30: 0 | BU30: =SUMIFS(BH30:BS30,$BH$3:$BS$3,"是") -> 0 | BX30: TZ0093 | BY30: 橱柜经销三分部 | BZ30: 利润 | CA30: =CG30 -> 0.045724 | CB30: 3.877786 | CC30: 0.375133 | CD30: 1.439067 | CE30: 0.478951 | CF30: 0.643334 | CG30: 0.045724 | CH30: 2.558844 | CI30: 2.687273 | CJ30: 1.749427 | CK30: 1.622539 | CL30: 1.099549 | CM30: 1.83593 | CN30: 18.413557 | CO30: =SUMIFS(CB30:CM30,$F$2:$Q$2,"是") -> 6.859995
A31: 橱柜经销一部 | B31: 成本 | C31: 按合同类型 | D31: 普通单 | E31: =K31 -> 4742.717 | F31: 3288.1402 | G31: 873.86071 | H31: 3249.6408 | I31: 4051.7549 | J31: 4535.4305 | K31: 4742.717 | L31: 5105.4554 | M31: 4730.8094 | N31: 4392.1361 | O31: 4185.9485 | P31: 4946.3432 | Q31: 4909.6002 | R31: 49011.837 | S31: =SUMIFS(F31:Q31,$F$2:$Q$2,"是") -> 20741.544 | T31: 基数 | V31: 基数 | W31: 橱柜经销一部 | X31: 呆滞物料收支 | Y31: =AE31 -> 0 | Z31: 0 | AA31: 0 | AB31: 0 | AC31: 0 | AD31: 0 | AE31: 0 | AF31: 0 | AG31: 0 | AH31: 0 | AI31: 0 | AJ31: 0 | AK31: 0 | AL31: 0 | AM31: =SUMIFS(Z31:AK31,$Z$2:$AK$2,"是") -> 0 | AP31: 26 | AQ31: 橱柜电商及信息化推广分部 | AR31: =AX31 -> 0 | AS31: 0 | AT31: 0 | AU31: 0 | AV31: 0 | AW31: 0 | AX31: 0 | AY31: 0 | AZ31: 0 | BA31: 0 | BB31: 0 | BC31: 0 | BD31: 0 | BE31: 0 | BF31: =SUMIFS(AS31:BD31,$AS$3:$BD$3,"是") -> 0 | BG31: =BM31 -> 0 | BH31: 0 | BI31: 0 | BJ31: 0 | BK31: 0 | BL31: 0 | BM31: 0 | BN31: 0 | BO31: 0 | BP31: 0 | BQ31: 0 | BR31: 0 | BS31: 0 | BT31: 0 | BU31: =SUMIFS(BH31:BS31,$BH$3:$BS$3,"是") -> 0 | BX31: TZ0094 | BY31: 橱柜经销四部 | BZ31: 利润 | CA31: =CG31 -> 0.011431 | CB31: 2.615818 | CC31: 1.235815 | CD31: 1.620089 | CE31: 0.479375 | CF31: 0.277986 | CG31: 0.011431 | CH31: 1.554557 | CI31: 1.330982 | CJ31: 0.617255 | CK31: 0.781222 | CL31: 0.653356 | CM31: 1.502137 | CN31: 12.680023 | CO31: =SUMIFS(CB31:CM31,$F$2:$Q$2,"是") -> 6.240514
A32: 橱柜经销一部 | B32: 成本 | C32: 按合同类型 | D32: 样品单 | E32: =K32 -> 1082.0267 | F32: 256.08254 | G32: 252.3414 | H32: 217.37448 | I32: 308.45037 | J32: 883.49074 | K32: 1082.0267 | L32: 989.04226 | M32: 790.53146 | N32: 875.11065 | O32: 538.61069 | P32: 230.93242 | Q32: 275.81325 | R32: 6699.8069 | S32: =SUMIFS(F32:Q32,$F$2:$Q$2,"是") -> 2999.7662 | T32: 基数 | V32: 基数 | W32: 橱柜经销一部 | X32: 委托加工费 | Y32: =AE32 -> 10.5344 | Z32: 0 | AA32: 0 | AB32: 3.0006 | AC32: 6.5142 | AD32: 15.4258 | AE32: 10.5344 | AF32: 12.483 | AG32: 12.1389 | AH32: 7.0965 | AI32: 11.25597 | AJ32: 9.5494 | AK32: 10.3969 | AL32: 98.39567 | AM32: =SUMIFS(Z32:AK32,$Z$2:$AK$2,"是") -> 35.475 | AP32: 27 | AQ32: 厨电百货经销部 | AR32: =AX32 -> 0 | AS32: 0 | AT32: 0 | AU32: 0 | AV32: 0 | AW32: 0 | AX32: 0 | AY32: 0 | AZ32: 0 | BA32: 0 | BB32: 0 | BC32: 0 | BD32: 0 | BE32: 0 | BF32: =SUMIFS(AS32:BD32,$AS$3:$BD$3,"是") -> 0 | BG32: =BM32 -> 0 | BH32: 0 | BI32: 0 | BJ32: 0 | BK32: 0 | BL32: 0 | BM32: 0 | BN32: 0 | BO32: 0 | BP32: 0 | BQ32: 0 | BR32: 0 | BS32: 0 | BT32: 0 | BU32: =SUMIFS(BH32:BS32,$BH$3:$BS$3,"是") -> 0 | BX32: TZ0095 | BY32: 橱柜经销五部 | BZ32: 利润 | CA32: =CG32 -> 0.656066 | CB32: 1.904806 | CC32: 3.356137 | CD32: 1.697109 | CE32: 1.525364 | CF32: 17.253666 | CG32: 0.656066 | CH32: 8.966632 | CI32: 7.161739 | CJ32: 3.744661 | CK32: 1.779124 | CL32: 8.681797 | CM32: 3.509264 | CN32: 60.236365 | CO32: =SUMIFS(CB32:CM32,$F$2:$Q$2,"是") -> 26.393148
A33: 橱柜经销一部 | B33: 成本 | C33: 按合同类型 | D33: 遗留单 | E33: =K33 -> 56.817851 | F33: 13.7494 | G33: 69.395779 | H33: 55.636764 | I33: 46.641264 | J33: 55.722484 | K33: 56.817851 | L33: 58.623546 | M33: 68.834625 | N33: 71.504487 | O33: 73.837848 | P33: 64.878289 | Q33: 55.604046 | R33: 691.24638 | S33: =SUMIFS(F33:Q33,$F$2:$Q$2,"是") -> 297.96354 | T33: 基数 | V33: 基数 | W33: 橱柜经销一部 | X33: 佣金 | Y33: =AE33 -> 0 | Z33: 0 | AA33: 0 | AB33: 0 | AC33: 0 | AD33: 0 | AE33: 0 | AF33: 0 | AG33: 0 | AH33: 0 | AI33: 0 | AJ33: 0 | AK33: 0 | AL33: 0 | AM33: =SUMIFS(Z33:AK33,$Z$2:$AK$2,"是") -> 0 | AP33: 28 | AQ33: 厨电百货行政支部 | AR33: =AX33 -> 0 | AS33: 0 | AT33: 0 | AU33: 0 | AV33: 0 | AW33: 0 | AX33: 0 | AY33: 0 | AZ33: 0 | BA33: 0 | BB33: 0 | BC33: 0 | BD33: 0 | BE33: 0 | BF33: =SUMIFS(AS33:BD33,$AS$3:$BD$3,"是") -> 0 | BG33: =BM33 -> 0 | BH33: 0 | BI33: 0 | BJ33: 0 | BK33: 0 | BL33: 0 | BM33: 0 | BN33: 0 | BO33: 0 | BP33: 0 | BQ33: 0 | BR33: 0 | BS33: 0 | BT33: 0 | BU33: =SUMIFS(BH33:BS33,$BH$3:$BS$3,"是") -> 0 | BX33: TZ0096 | BY33: 橱柜经销六部 | BZ33: 利润 | CA33: =CG33 -> 1.334899 | CB33: 9.003928 | CC33: 2.316791 | CD33: 4.737704 | CE33: 2.640976 | CF33: 2.75695 | CG33: 1.334899 | CH33: 4.196915 | CI33: 2.448849 | CJ33: 4.189522 | CK33: 3.038406 | CL33: 2.292683 | CM33: 5.053039 | CN33: 44.010662 | CO33: =SUMIFS(CB33:CM33,$F$2:$Q$2,"是") -> 22.791248
A34: 橱柜经销一部 | B34: 毛利 | C34: 按产品 | D34: 柜门 | E34: =K34 -> 949.27084 | F34: 568.92928 | G34: 136.51139 | H34: 474.13016 | I34: 902.29926 | J34: 643.12742 | K34: 949.27084 | L34: 1082.0705 | M34: 1126.3708 | N34: 1041.7578 | O34: 893.44077 | P34: 985.05763 | Q34: 1034.2622 | R34: 9837.228 | S34: =SUMIFS(F34:Q34,$F$2:$Q$2,"是") -> 3674.2684 | T34: 基数 | V34: 基数 | W34: 橱柜经销一部 | X34: 燃气动力 | Y34: =AE34 -> 0 | Z34: 0 | AA34: 0 | AB34: 0 | AC34: 0 | AD34: 0 | AE34: 0 | AF34: 0 | AG34: 0 | AH34: 0 | AI34: 0 | AJ34: 0 | AK34: 0 | AL34: 0 | AM34: =SUMIFS(Z34:AK34,$Z$2:$AK$2,"是") -> 0 | AP34: 29 | AQ34: 配件产品分部 | AR34: =AX34 -> 0 | AS34: 0 | AT34: 0 | AU34: 0 | AV34: 0 | AW34: 0 | AX34: 0 | AY34: 0 | AZ34: 0 | BA34: 0 | BB34: 0 | BC34: 0 | BD34: -33.791925 | BE34: -33.791925 | BF34: =SUMIFS(AS34:BD34,$AS$3:$BD$3,"是") -> 0 | BG34: =BM34 -> 0 | BH34: 0 | BI34: 0 | BJ34: 0 | BK34: 0 | BL34: 0 | BM34: 0 | BN34: 0 | BO34: 0 | BP34: 0 | BQ34: 0 | BR34: 0 | BS34: 0 | BT34: 0 | BU34: =SUMIFS(BH34:BS34,$BH$3:$BS$3,"是") -> 0 | BY34: 橱柜经销七部 | BZ34: 利润 | CA34: =CG34 -> 0 | CB34: 0 | CC34: 0 | CD34: 0 | CE34: 0 | CF34: 0 | CG34: 0 | CH34: 0 | CI34: 0 | CJ34: 0 | CK34: 0 | CL34: 0 | CM34: 0 | CN34: 0 | CO34: =SUMIFS(CB34:CM34,$F$2:$Q$2,"是") -> 0
A35: 橱柜经销一部 | B35: 毛利 | C35: 按产品 | D35: 台面 | E35: =K35 -> 564.43485 | F35: 292.10226 | G35: 88.036065 | H35: 233.615 | I35: 514.04118 | J35: 422.76792 | K35: 564.43485 | L35: 569.73442 | M35: 560.34708 | N35: 538.64641 | O35: 494.51903 | P35: 574.39599 | Q35: 622.68303 | R35: 5475.3232 | S35: =SUMIFS(F35:Q35,$F$2:$Q$2,"是") -> 2114.9973 | T35: 基数 | V35: 基数 | W35: 橱柜经销一部 | X35: 搬迁费 | Y35: =AE35 -> 0 | Z35: 0 | AA35: 0 | AB35: 0 | AC35: 0 | AD35: 0 | AE35: 0 | AF35: 0 | AG35: 0 | AH35: 0 | AI35: 0 | AJ35: 0 | AK35: 0 | AL35: 0 | AM35: =SUMIFS(Z35:AK35,$Z$2:$AK$2,"是") -> 0 | AP35: 30 | AQ35: 电器产品部 | AR35: =AX35 -> 0 | AS35: 0 | AT35: 0 | AU35: 0 | AV35: 0 | AW35: 0 | AX35: 0 | AY35: 0 | AZ35: 0 | BA35: 0 | BB35: 0 | BC35: 0 | BD35: -111.86617 | BE35: -111.86617 | BF35: =SUMIFS(AS35:BD35,$AS$3:$BD$3,"是") -> 0 | BG35: =BM35 -> 0 | BH35: 0 | BI35: 0 | BJ35: 0 | BK35: 0 | BL35: 0 | BM35: 0 | BN35: 0 | BO35: 0 | BP35: 0 | BQ35: 0 | BR35: 0 | BS35: 0 | BT35: 0 | BU35: =SUMIFS(BH35:BS35,$BH$3:$BS$3,"是") -> 0 | BZ35: 合计 | CA35: =CG35 -> 4.617952 | CB35: 26.87921 | CC35: 12.298141 | CD35: 13.677903 | CE35: 9.957358 | CF35: 23.369554 | CG35: 4.617952 | CH35: 21.983313 | CI35: 19.560908 | CJ35: 14.5445 | CK35: 13.181327 | CL35: 17.972879 | CM35: 13.640016 | CN35: 191.68306 | CO35: =SUMIFS(CB35:CM35,$F$2:$Q$2,"是") -> 90.800118
A36: 橱柜经销一部 | B36: 毛利 | C36: 按产品 | D36: OEM烟灶 | E36: =K36 -> 356.9831 | F36: 180.52392 | G36: 51.369483 | H36: 329.1012 | I36: 331.58238 | J36: 386.49728 | K36: 356.9831 | L36: 238.36487 | M36: 132.33114 | N36: 142.30802 | O36: 175.27832 | P36: 182.3945 | Q36: 194.51241 | R36: 2701.2466 | S36: =SUMIFS(F36:Q36,$F$2:$Q$2,"是") -> 1636.0574 | T36: 基数 | V36: 基数 | W36: 橱柜经销一部 | X36: 劳务赔偿费 | Y36: =AE36 -> 0 | Z36: 0 | AA36: 0 | AB36: 0 | AC36: 0 | AD36: 0 | AE36: 0 | AF36: 0 | AG36: 0 | AH36: 0 | AI36: 0 | AJ36: 0 | AK36: 0 | AL36: 0 | AM36: =SUMIFS(Z36:AK36,$Z$2:$AK$2,"是") -> 0 | AP36: 31 | AQ36: 厨电百货质量部 | AR36: =AX36 -> 0 | AS36: 0 | AT36: 0 | AU36: 0 | AV36: 0 | AW36: 0 | AX36: 0 | AY36: 0 | AZ36: 0 | BA36: 0 | BB36: 0 | BC36: 0 | BD36: -75.82297 | BE36: -75.82297 | BF36: =SUMIFS(AS36:BD36,$AS$3:$BD$3,"是") -> 0 | BG36: =BM36 -> 0 | BH36: 0 | BI36: 0 | BJ36: 0 | BK36: 0 | BL36: 0 | BM36: 0 | BN36: 0 | BO36: 0 | BP36: 0 | BQ36: 0 | BR36: 0 | BS36: 0 | BT36: 0 | BU36: =SUMIFS(BH36:BS36,$BH$3:$BS$3,"是") -> 0
A37: 橱柜经销一部 | B37: 毛利 | C37: 按产品 | D37: OEM其他 | E37: =K37 -> 642.00232 | F37: 301.3241 | G37: 97.978413 | H37: 365.64587 | I37: 508.14364 | J37: 499.85546 | K37: 642.00232 | L37: -13.925582 | M37: 550.54231 | N37: 602.97685 | O37: 564.91799 | P37: 552.16511 | Q37: 622.17811 | R37: 5293.8046 | S37: =SUMIFS(F37:Q37,$F$2:$Q$2,"是") -> 2414.9498 | T37: 基数 | V37: 基数 | W37: 橱柜经销一部 | X37: 研发费 | Y37: =AE37 -> 0 | Z37: 0 | AA37: 0 | AB37: 0 | AC37: 0 | AD37: 0 | AE37: 0 | AF37: 0 | AG37: 0 | AH37: 0 | AI37: 0 | AJ37: 0 | AK37: 0 | AL37: 0 | AM37: =SUMIFS(Z37:AK37,$Z$2:$AK$2,"是") -> 0 | AP37: 32 | AQ37: 厨电百货工艺分部 | AR37: =AX37 -> 0 | AS37: 0 | AT37: 0 | AU37: 0 | AV37: 0 | AW37: 0 | AX37: 0 | AY37: 0 | AZ37: 0 | BA37: 0 | BB37: 0 | BC37: 0 | BD37: -86.039238 | BE37: -86.039238 | BF37: =SUMIFS(AS37:BD37,$AS$3:$BD$3,"是") -> 0 | BG37: =BM37 -> 0 | BH37: 0 | BI37: 0 | BJ37: 0 | BK37: 0 | BL37: 0 | BM37: 0 | BN37: 0 | BO37: 0 | BP37: 0 | BQ37: 0 | BR37: 0 | BS37: 0 | BT37: 0 | BU37: =SUMIFS(BH37:BS37,$BH$3:$BS$3,"是") -> 0
A38: 橱柜经销一部 | B38: 毛利 | C38: 按产品 | D38: 自制烟灶 | E38: =K38 -> 313.65372 | F38: 197.22782 | G38: 40.674246 | H38: 141.68337 | I38: 191.93634 | J38: 199.82924 | K38: 313.65372 | L38: 334.9711 | M38: 323.43361 | N38: 293.84023 | O38: 210.63837 | P38: 211.71367 | Q38: 254.90585 | R38: 2714.5076 | S38: =SUMIFS(F38:Q38,$F$2:$Q$2,"是") -> 1085.0047 | T38: 基数 | V38: 基数 | W38: 橱柜经销一部 | X38: 合计 | Y38: =AE38 -> 649.3985 | Z38: 617.15939 | AA38: 232.79507 | AB38: 696.66282 | AC38: 969.18748 | AD38: 1035.6239 | AE38: 649.3985 | AF38: 1231.6469 | AG38: 1160.968 | AH38: 1095.8897 | AI38: 988.35911 | AJ38: 1076.8315 | AK38: 1320.5584 | AL38: 11075.081 | AM38: =SUMIFS(Z38:AK38,$Z$2:$AK$2,"是") -> 4200.8272 | AP38: 33 | AQ38: 橱柜电商运营推广支部（旧） | AR38: =AX38 -> 0 | AS38: 0 | AT38: 0 | AU38: 0 | AV38: 0 | AW38: 0 | AX38: 0 | AY38: 0 | AZ38: 0 | BA38: 0 | BB38: 0 | BC38: 0 | BD38: 0 | BE38: 0 | BF38: =SUMIFS(AS38:BD38,$AS$3:$BD$3,"是") -> 0 | BG38: =BM38 -> 0 | BH38: 0 | BI38: 0 | BJ38: 0 | BK38: 0 | BL38: 0 | BM38: 0 | BN38: 0 | BO38: 0 | BP38: 0 | BQ38: 0 | BR38: 0 | BS38: 0 | BT38: 0 | BU38: =SUMIFS(BH38:BS38,$BH$3:$BS$3,"是") -> 0
A39: 橱柜经销一部 | B39: 毛利 | C39: 按产品 | D39: 其他加收 | E39: =K39 -> 7.8366 | F39: 3.1685 | G39: 0.9922 | H39: 1.8536 | I39: 2.4893 | J39: 3.0266 | K39: 7.8366 | L39: 3.8791 | M39: 1.7751 | N39: 4.9834 | O39: 2.1527 | P39: 5.6105 | Q39: 5.9123 | R39: 43.6799 | S39: =SUMIFS(F39:Q39,$F$2:$Q$2,"是") -> 19.3668 | T39: 基数 | V39: 基数 | Y39: =AE39 -> 0 | AM39: =SUMIFS(Z39:AK39,$Z$2:$AK$2,"是") -> 0 | AP39: 34 | AQ39: 橱柜营销线总经理室 | AR39: =AX39 -> 0 | AS39: 0 | AT39: 0 | AU39: 0 | AV39: 0 | AW39: 0 | AX39: 0 | AY39: 0 | AZ39: 0 | BA39: 0 | BB39: 0 | BC39: 0 | BD39: 0 | BE39: 0 | BF39: =SUMIFS(AS39:BD39,$AS$3:$BD$3,"是") -> 0 | BG39: =BM39 -> 0 | BH39: 0 | BI39: 0 | BJ39: 0 | BK39: 0 | BL39: 0 | BM39: 0 | BN39: 0 | BO39: 0 | BP39: 0 | BQ39: 0 | BR39: 0 | BS39: 0 | BT39: 0 | BU39: =SUMIFS(BH39:BS39,$BH$3:$BS$3,"是") -> 0
A40: 橱柜经销一部 | B40: 毛利 | C40: 按订单类型 | D40: 常规单 | E40: =K40 -> 2378.3156 | F40: 1310.8181 | G40: 360.83914 | H40: 1361.1722 | I40: 1910.7637 | J40: 1994.8232 | K40: 2378.3156 | L40: 1684.0022 | M40: 2112.2595 | N40: 2087.5881 | O40: 1908.398 | P40: 2107.4608 | Q40: 2215.638 | R40: 21432.078 | S40: =SUMIFS(F40:Q40,$F$2:$Q$2,"是") -> 9316.7319 | T40: 基数 | V40: 基数 | Y40: =AE40 -> 0 | AM40: =SUMIFS(Z40:AK40,$Z$2:$AK$2,"是") -> 0 | AP40: 35 | AQ40: 橱柜职能费用小计 | AR40: =AX40 -> 0 | AS40: 0 | AT40: 0 | AU40: 0 | AV40: 0 | AW40: 0 | AX40: 0 | AY40: 0 | AZ40: 0 | BA40: 0 | BB40: 0 | BC40: 0 | BD40: -307.5203 | BE40: -307.5203 | BF40: =SUMIFS(AS40:BD40,$AS$3:$BD$3,"是") -> 0 | BG40: =BM40 -> 0 | BH40: 0 | BI40: 0 | BJ40: 0 | BK40: 0 | BL40: 0 | BM40: 0 | BN40: 0 | BO40: 0 | BP40: 0 | BQ40: 0 | BR40: 0 | BS40: 0 | BT40: 0 | BU40: =SUMIFS(BH40:BS40,$BH$3:$BS$3,"是") -> 0
A41: 橱柜经销一部 | B41: 毛利 | C41: 按订单类型 | D41: 家装单 | E41: =K41 -> 122.58157 | F41: 55.266256 | G41: 8.5031042 | H41: 25.793008 | I41: 142.37168 | J41: -9.8722277 | K41: 122.58157 | L41: 141.32038 | M41: 166.54596 | N41: 4.2389378 | O41: 123.37859 | P41: 102.73199 | Q41: 168.77114 | R41: 1051.6304 | S41: =SUMIFS(F41:Q41,$F$2:$Q$2,"是") -> 344.64339 | T41: 基数 | V41: 基数 | W41: 2020年部门名称 | X41: 项目 | Y41: =AE41 -> 6月 | Z41: 1月 | AA41: 2月 | AB41: 3月 | AC41: 4月 | AD41: 5月 | AE41: 6月 | AF41: 7月 | AG41: 8月 | AH41: 9月 | AI41: 10月 | AJ41: 11月 | AK41: 12月 | AL41: 本年累计 | AM41: 同期 | AP41: 36 | AQ41: 橱柜零售合计 | AR41: =AX41 -> 4.617952 | AS41: 26.87921 | AT41: 12.298141 | AU41: 13.677903 | AV41: 9.957358 | AW41: 23.369554 | AX41: 4.617952 | AY41: 21.983313 | AZ41: 19.560908 | BA41: 14.5445 | BB41: 13.181327 | BC41: 17.972879 | BD41: -293.88029 | BE41: -115.83724 | BF41: =SUMIFS(AS41:BD41,$AS$3:$BD$3,"是") -> 90.800118 | BG41: =BM41 -> 11.33 | BH41: 137.625 | BI41: 63.765 | BJ41: 67.465 | BK41: 51.365 | BL41: 87.585 | BM41: 11.33 | BN41: 102.825 | BO41: 91.31 | BP41: 66.89 | BQ41: 60.335 | BR41: 83.324 | BS41: 62.81 | BT41: 886.629 | BU41: =SUMIFS(BH41:BS41,$BH$3:$BS$3,"是") -> 419.135
A42: 橱柜经销一部 | B42: 毛利 | C42: 按订单类型 | D42: 直供单 | E42: =K42 -> 324.93045 | F42: 175.84341 | G42: 45.234223 | H42: 158.13426 | I42: 393.86149 | J42: 165.77474 | K42: 324.93045 | L42: 372.55131 | M42: 402.85602 | N42: 514.82599 | O42: 292.06323 | P42: 279.33601 | Q42: 332.14017 | R42: 3457.5513 | S42: =SUMIFS(F42:Q42,$F$2:$Q$2,"是") -> 1263.7786 | T42: 基数 | V42: 基数 | W42: 橱柜经销二部 | X42: 房租 | Y42: =AE42 -> 2.4050503 | Z42: 1.2337655 | AA42: 2.2769051 | AB42: 0.98547618 | AC42: 0.74046777 | AD42: 5.990598 | AE42: 2.4050503 | AF42: 2.3005361 | AG42: 6.807372 | AH42: 2.0630559 | AI42: 8.4016354 | AJ42: 3.311364 | AK42: 6.6348365 | AL42: 43.151063 | AM42: =SUMIFS(Z42:AK42,$Z$2:$AK$2,"是") -> 13.632263 | AP42: 37 | AQ42: 橱柜营销事业部合计 | AR42: =AX42 -> 841.53526 | AS42: 57.192326 | AT42: 1.5511565 | AU42: 274.45813 | AV42: 271.21918 | AW42: 454.35071 | AX42: 841.53526 | AY42: 638.91583 | AZ42: 865.22142 | BA42: 772.27972 | BB42: 604.74277 | BC42: 633.3563 | BD42: 689.70945 | BE42: 6104.5323 | BF42: =SUMIFS(AS42:BD42,$AS$3:$BD$3,"是") -> 1900.3068 | BG42: =BM42 -> 19321.227 | BH42: 9544.7776 | BI42: 3377.1911 | BJ42: 12560.083 | BK42: 13151.869 | BL42: 16471.133 | BM42: 19321.227 | BN42: 21291.756 | BO42: 22795.836 | BP42: 18743.757 | BQ42: 17947.283 | BR42: 22548.342 | BS42: 24705.721 | BT42: 202458.98 | BU42: =SUMIFS(BH42:BS42,$BH$3:$BS$3,"是") -> 74426.28
A43: 橱柜经销一部 | B43: 毛利 | C43: 按订单类型 | D43: 网销单 | E43: =K43 -> 0 | F43: 0.20916248 | G43: 0 | H43: 0 | I43: 0.46881038 | J43: 0 | K43: 0 | L43: 0 | M43: 0 | N43: 0 | O43: 0 | P43: 0 | Q43: 0 | R43: 0.67797286 | S43: =SUMIFS(F43:Q43,$F$2:$Q$2,"是") -> 0.67797286 | T43: 基数 | V43: 基数 | W43: 橱柜经销二部 | X43: 水费 | Y43: =AE43 -> 0.03826356 | Z43: 0.099412792 | AA43: 0.037798703 | AB43: 0.03097587 | AC43: 0.033524154 | AD43: 0.033962198 | AE43: 0.03826356 | AF43: 0.038824778 | AG43: 0.038662739 | AH43: 0.064439707 | AI43: 0.060474487 | AJ43: 0.035892994 | AK43: 0.063291622 | AL43: 0.5755236 | AM43: =SUMIFS(Z43:AK43,$Z$2:$AK$2,"是") -> 0.27393728 | AP43: 60 | AQ43: 厨电线合计 | AR43: =AX43 -> 841.53526 | AS43: 57.192326 | AT43: 1.5511565 | AU43: 274.45813 | AV43: 271.21918 | AW43: 454.35071 | AX43: 841.53526 | AY43: 638.91583 | AZ43: 865.22142 | BA43: 772.27972 | BB43: 604.74277 | BC43: 633.3563 | BD43: 689.70945 | BE43: 6104.5323 | BF43: =SUMIFS(AS43:BD43,$AS$3:$BD$3,"是") -> 1900.3068 | BG43: =BM43 -> 19178.136 | BH43: 9520.0668 | BI43: 3366.2192 | BJ43: 12530.464 | BK43: 13131.036 | BL43: 16379.495 | BM43: 19178.136 | BN43: 21077.568 | BO43: 22569.605 | BP43: 18580.074 | BQ43: 17693.308 | BR43: 22205.484 | BS43: 24309.2 | BT43: 200540.66 | BU43: =SUMIFS(BH43:BS43,$BH$3:$BS$3,"是") -> 74105.416
A44: 橱柜经销一部 | B44: 毛利 | C44: 按订单类型 | D44: 星居单 | E44: =K44 -> 8.123954 | F44: 1.1389791 | G44: 0.98533553 | H44: 0.92969169 | I44: 3.026464 | J44: 4.378207 | K44: 8.123954 | L44: 16.336445 | M44: 13.138514 | N44: 17.859679 | O44: 14.037403 | P44: 19.767726 | Q44: 25.886745 | R44: 125.60914 | S44: =SUMIFS(F44:Q44,$F$2:$Q$2,"是") -> 18.582631 | T44: 基数 | V44: 基数 | W44: 橱柜经销二部 | X44: 电费 | Y44: =AE44 -> 0.19038221 | Z44: 0.083779883 | AA44: 0.061390293 | AB44: 0.11652535 | AC44: 0.15067912 | AD44: 0.15716802 | AE44: 0.19038221 | AF44: 0.2135473 | AG44: 0.23707334 | AH44: 0.20038724 | AI44: 0.19709703 | AJ44: 0.18896316 | AK44: 0.14093399 | AL44: 1.9379269 | AM44: =SUMIFS(Z44:AK44,$Z$2:$AK$2,"是") -> 0.75992488 | AP44: 38 | AQ44: 其中：剔除礼包 | AR44: =AX44 -> -4.617952 | AS44: -26.87921 | AT44: -12.298141 | AU44: -13.677903 | AV44: -9.957358 | AW44: -23.369554 | AX44: -4.617952 | AY44: -21.983313 | AZ44: -19.560908 | BA44: -14.5445 | BB44: -13.181327 | BC44: -17.972879 | BD44: -13.640016 | BE44: -191.68306 | BF44: =SUMIFS(AS44:BD44,$AS$3:$BD$3,"是") -> -90.800118 | BG44: =BM44 -> -11.33 | BH44: -137.625 | BI44: -63.765 | BJ44: -67.465 | BK44: -51.365 | BL44: -87.585 | BM44: -11.33 | BN44: -102.825 | BO44: -91.31 | BP44: -66.89 | BQ44: -60.335 | BR44: -83.324 | BS44: -62.81 | BT44: -886.629 | BU44: =SUMIFS(BH44:BS44,$BH$3:$BS$3,"是") -> -419.135
A45: 橱柜经销一部 | B45: 毛利 | C45: 按订单类型 | D45: 微居单 | E45: =K45 -> 0.22986129 | F45: 0 | G45: 0 | H45: 0 | I45: 0 | J45: 0 | K45: 0.22986129 | L45: 0.88409885 | M45: 0 | N45: 0 | O45: 3.069937 | P45: 2.0408736 | Q45: 0.23792188 | R45: 6.4626926 | S45: =SUMIFS(F45:Q45,$F$2:$Q$2,"是") -> 0.22986129 | T45: 基数 | V45: 基数 | W45: 橱柜经销二部 | X45: 办公费 | Y45: =AE45 -> 3.624362 | Z45: 0.21085013 | AA45: 0.52057707 | AB45: 0.17624205 | AC45: 4.3752837 | AD45: 0.38587755 | AE45: 3.624362 | AF45: 2.0771896 | AG45: 4.7354009 | AH45: 1.6292862 | AI45: 1.1305556 | AJ45: 2.5592244 | AK45: 2.0710007 | AL45: 23.49585 | AM45: =SUMIFS(Z45:AK45,$Z$2:$AK$2,"是") -> 9.2931925 | AO45: TZ0090 | AP45: 39 | AQ45: 共享工程-各品类收入毛利-橱柜 | AR45: =AX45 -> 281.14571 | AS45: 46.415875 | AT45: 35.937273 | AU45: 134.16178 | AV45: 116.7153 | AW45: 149.00024 | AX45: 281.14571 | AY45: 283.44339 | AZ45: 254.94071 | BA45: 274.75634 | BB45: 322.38819 | BC45: 284.94958 | BD45: 442.37209 | BE45: 2626.2265 | BF45: =SUMIFS(AS45:BD45,$AS$3:$BD$3,"是") -> 763.37617 | BG45: =BM45 -> 0 | BH45: 0 | BI45: 0 | BJ45: 0 | BK45: 0 | BL45: 0 | BM45: 0 | BN45: 0 | BO45: 0 | BP45: 0 | BQ45: 0 | BR45: 0 | BS45: 0 | BT45: 0 | BU45: =SUMIFS(BH45:BS45,$BH$3:$BS$3,"是") -> 0
A46: 橱柜经销一部 | B46: 毛利 | C46: 按合同类型 | D46: 普通单 | E46: =K46 -> 2375.4647 | F46: 1463.5641 | G46: 385.55497 | H46: 1486.5415 | I46: 2352.1225 | J46: 1860.5964 | K46: 2375.4647 | L46: 1819.4798 | M46: 2396.9045 | N46: 2270.1376 | O46: 2146.4169 | P46: 2425.9006 | Q46: 2668.836 | R46: 23651.52 | S46: =SUMIFS(F46:Q46,$F$2:$Q$2,"是") -> 9923.8443 | T46: 基数 | V46: 基数 | W46: 橱柜经销二部 | X46: 工资 | Y46: =AE46 -> 144.83862 | Z46: 55.078455 | AA46: -5.787781 | AB46: 44.795333 | AC46: 104.6857 | AD46: 103.25902 | AE46: 144.83862 | AF46: 80.860543 | AG46: 124.95872 | AH46: 105.132 | AI46: 119.92682 | AJ46: 92.967302 | AK46: 182.26746 | AL46: 1152.9822 | AM46: =SUMIFS(Z46:AK46,$Z$2:$AK$2,"是") -> 446.86935 | AO46: TZ0999 | AP46: 40 | AQ46: 共享工程-各品类收入毛利百货 | AR46: =AX46 -> 42.397694 | AS46: 22.923103 | AT46: 9.706499 | AU46: 42.738365 | AV46: 20.908469 | AW46: 65.840926 | AX46: 42.397694 | AY46: 62.822475 | AZ46: 82.043852 | BA46: 59.432694 | BB46: 43.345749 | BC46: 47.072081 | BD46: 51.80606 | BE46: 551.03797 | BF46: =SUMIFS(AS46:BD46,$AS$3:$BD$3,"是") -> 204.51506 | BG46: =BM46 -> 0 | BH46: 0 | BI46: 0 | BJ46: 0 | BK46: 0 | BL46: 0 | BM46: 0 | BN46: 0 | BO46: 0 | BP46: 0 | BQ46: 0 | BR46: 0 | BS46: 0 | BT46: 0 | BU46: =SUMIFS(BH46:BS46,$BH$3:$BS$3,"是") -> 0
A47: 橱柜经销一部 | B47: 毛利 | C47: 按合同类型 | D47: 样品单 | E47: =K47 -> 448.16626 | F47: 74.260752 | G47: 16.771907 | H47: 49.829844 | I47: 97.819037 | J47: 277.61897 | K47: 448.16626 | L47: 391.44358 | M47: 287.30517 | N47: 344.08509 | O47: 183.86594 | P47: 64.618732 | Q47: 68.97784 | R47: 2304.7631 | S47: =SUMIFS(F47:Q47,$F$2:$Q$2,"是") -> 964.46677 | T47: 基数 | V47: 基数 | W47: 橱柜经销二部 | X47: 福利费 | Y47: =AE47 -> 5.3635967 | Z47: 6.0388134 | AA47: 7.2754683 | AB47: 6.3031684 | AC47: 6.5387733 | AD47: 7.4773479 | AE47: 5.3635967 | AF47: 9.4798947 | AG47: 7.7255736 | AH47: 6.9864537 | AI47: 6.2803209 | AJ47: 5.6782202 | AK47: 5.9729668 | AL47: 81.120598 | AM47: =SUMIFS(Z47:AK47,$Z$2:$AK$2,"是") -> 38.997168 | AO47: TZ0183 | AP47: 41 | AQ47: 加：电器厂共享利润 | AR47: =AX47 -> 522.60982 | AS47: 14.732558 | AT47: -31.794475 | AU47: 111.23588 | AV47: 143.55277 | AW47: 262.8791 | AX47: 522.60982 | AY47: 314.63328 | AZ47: 547.79776 | BA47: 452.63518 | BB47: 252.19015 | BC47: 319.30752 | BD47: 209.17132 | BE47: 3118.9509 | BF47: =SUMIFS(AS47:BD47,$AS$3:$BD$3,"是") -> 1023.2157 | BG47: =BM47 -> 0 | BH47: 0 | BI47: 0 | BJ47: 0 | BK47: 0 | BL47: 0 | BM47: 0 | BN47: 0 | BO47: 0 | BP47: 0 | BQ47: 0 | BR47: 0 | BS47: 0 | BT47: 0 | BU47: =SUMIFS(BH47:BS47,$BH$3:$BS$3,"是") -> 0
A48: 橱柜经销一部 | B48: 毛利 | C48: 按合同类型 | D48: 遗留单 | E48: =K48 -> 10.550449 | F48: 5.4509999 | G48: 13.234921 | H48: 9.6578363 | I48: 0.55053605 | J48: 16.888516 | K48: 10.550449 | L48: 4.1710539 | M48: 10.590375 | N48: 10.290013 | O48: 10.664352 | P48: 20.818111 | Q48: 4.8600545 | R48: 117.72722 | S48: =SUMIFS(F48:Q48,$F$2:$Q$2,"是") -> 56.333258 | T48: 基数 | V48: 基数 | W48: 橱柜经销二部 | X48: 交通车辆费 | Y48: =AE48 -> 0.046810348 | Z48: 0.15237537 | AA48: 0.022680487 | AB48: 0.022539572 | AC48: 0.055703949 | AD48: 0.061186967 | AE48: 0.046810348 | AF48: 0.032268826 | AG48: 0.028451174 | AH48: 0.044581999 | AI48: 0.0037608296 | AJ48: 0.060603646 | AK48: 0.021250291 | AL48: 0.55221346 | AM48: =SUMIFS(Z48:AK48,$Z$2:$AK$2,"是") -> 0.3612967 | AO48: TZ0001 | AP48: 42 | AQ48: 加：工程橱柜-共享橱柜 | AR48: =AX48 -> 0 | AS48: 0 | AT48: 0 | AU48: 0 | AV48: 0 | AW48: 0 | AX48: 0 | AY48: 0 | AZ48: 0 | BA48: 0 | BB48: 0 | BC48: 0 | BD48: 0 | BE48: 0 | BF48: =SUMIFS(AS48:BD48,$AS$3:$BD$3,"是") -> 0 | BG48: =BM48 -> 11147.769 | BH48: 4989.1206 | BI48: 1585.2387 | BJ48: 7321.4583 | BK48: 6384.8498 | BL48: 9021.8363 | BM48: 11147.769 | BN48: 12312.022 | BO48: 13249.284 | BP48: 10061.883 | BQ48: 9640.6793 | BR48: 12212.708 | BS48: 13697.607 | BT48: 111624.46 | BU48: =SUMIFS(BH48:BS48,$BH$3:$BS$3,"是") -> 40450.272
A49: 橱柜经销一部 | B49: 收入 | C49: 收入小计 | D49: 收入小计 | E49: =K49 -> 8715.7429 | F49: 5101.248 | G49: 1611.1597 | H49: 5068.6812 | I49: 6857.3386 | J49: 7629.7476 | K49: 8715.7429 | L49: 8368.2156 | M49: 8284.9755 | N49: 7963.2639 | O49: 7139.3442 | P49: 7753.4913 | Q49: 7975.4714 | R49: 82468.68 | S49: =SUMIFS(F49:Q49,$F$2:$Q$2,"是") -> 34983.918 | T49: 基数 | V49: 基数 | W49: 橱柜经销二部 | X49: 运杂费 | Y49: =AE49 -> 80.867394 | Z49: 28.557079 | AA49: 11.612535 | AB49: 39.298415 | AC49: 56.668599 | AD49: 59.108339 | AE49: 80.867394 | AF49: 76.335501 | AG49: 75.107747 | AH49: 76.645666 | AI49: 61.155495 | AJ49: 67.521707 | AK49: 62.716474 | AL49: 695.59495 | AM49: =SUMIFS(Z49:AK49,$Z$2:$AK$2,"是") -> 276.11236 | AO49: TZ0002 | AP49: 43 | AQ49: 加：工程橱柜-共享百货 | AR49: =AX49 -> 0 | AS49: 0 | AT49: 0 | AU49: 0 | AV49: 0 | AW49: 0 | AX49: 0 | AY49: 0 | AZ49: 0 | BA49: 0 | BB49: 0 | BC49: 0 | BD49: 0 | BE49: 0 | BF49: =SUMIFS(AS49:BD49,$AS$3:$BD$3,"是") -> 0 | BG49: =BM49 -> 1416.3785 | BH49: 576.86715 | BI49: 159.43523 | BJ49: 917.56193 | BK49: 1021.9146 | BL49: 1194.0584 | BM49: 1416.3785 | BN49: 1600.1345 | BO49: 1941.6776 | BP49: 1585.4629 | BQ49: 1428.0055 | BR49: 1189.1162 | BS49: 1357.3323 | BT49: 14387.945 | BU49: =SUMIFS(BH49:BS49,$BH$3:$BS$3,"是") -> 5286.2158
A50: 橱柜经销一部 | B50: 成本 | C50: 成本小计 | D50: 成本小计 | E50: =K50 -> 5881.5615 | F50: 3557.9721 | G50: 1195.5979 | H50: 3522.652 | I50: 4406.8465 | J50: 5474.6437 | K50: 5881.5615 | L50: 6153.1212 | M50: 5590.1754 | N50: 5338.7512 | O50: 4798.397 | P50: 5242.1539 | Q50: 5241.0175 | R50: 56402.89 | S50: =SUMIFS(F50:Q50,$F$2:$Q$2,"是") -> 24039.274 | T50: 基数 | V50: 基数 | W50: 橱柜经销二部 | X50: 差旅费 | Y50: =AE50 -> 18.811901 | Z50: -16.571112 | AA50: 7.9798437 | AB50: 24.795176 | AC50: 46.32549 | AD50: 33.597629 | AE50: 18.811901 | AF50: 45.511607 | AG50: 28.372334 | AH50: 38.344534 | AI50: 31.704051 | AJ50: 29.346457 | AK50: 55.530852 | AL50: 343.74876 | AM50: =SUMIFS(Z50:AK50,$Z$2:$AK$2,"是") -> 114.93893 | AP50: 44 | AQ50: 加：整装大家居共享 | AR50: =AX50 -> 0 | AS50: 0 | AT50: 0 | AU50: 0 | AV50: 0 | AW50: 0 | AX50: 0 | AY50: 0 | AZ50: 0 | BA50: 0 | BB50: 0 | BC50: 0 | BD50: 0 | BE50: 0 | BF50: =SUMIFS(AS50:BD50,$AS$3:$BD$3,"是") -> 0 | BG50: =BM50 -> 1809.6431 | BH50: 542.26094 | BI50: 259.4623 | BJ50: 935.93902 | BK50: 1452.4131 | BL50: 1536.9159 | BM50: 1809.6431 | BN50: 2145.3886 | BO50: 2091.4637 | BP50: 2199.4545 | BQ50: 2006.9184 | BR50: 2915.1875 | BS50: 3170.1224 | BT50: 21065.17 | BU50: =SUMIFS(BH50:BS50,$BH$3:$BS$3,"是") -> 6536.6344
A51: 橱柜经销一部 | B51: 毛利 | C51: 毛利小计 | D51: 毛利小计 | E51: =K51 -> 2834.1814 | F51: 1543.2759 | G51: 415.5618 | H51: 1546.0292 | I51: 2450.4921 | J51: 2155.1039 | K51: 2834.1814 | L51: 2215.0944 | M51: 2694.8 | N51: 2624.5127 | O51: 2340.9472 | P51: 2511.3374 | Q51: 2734.4539 | R51: 26065.79 | S51: =SUMIFS(F51:Q51,$F$2:$Q$2,"是") -> 10944.644 | T51: 基数 | V51: 基数 | W51: 橱柜经销二部 | X51: 折旧费用 | Y51: =AE51 -> 0.05771113 | Z51: 0.071903958 | AA51: 0 | AB51: 0.13148752 | AC51: 0.063085148 | AD51: 0.057448566 | AE51: 0.05771113 | AF51: 0.055525653 | AG51: 0.058284342 | AH51: 0.11463066 | AI51: 0.11571455 | AJ51: 0.059216754 | AK51: 0.077610103 | AL51: 0.86261838 | AM51: =SUMIFS(Z51:AK51,$Z$2:$AK$2,"是") -> 0.38163632 | AP51: 45 | AQ51: 加：欧铂丽共享 | AR51: =AX51 -> 0 | AS51: 0 | AT51: 0 | AU51: 0 | AV51: 0 | AW51: 0 | AX51: 0 | AY51: 0 | AZ51: 0 | BA51: 0 | BB51: 0 | BC51: 0 | BD51: 0 | BE51: 0 | BF51: =SUMIFS(AS51:BD51,$AS$3:$BD$3,"是") -> 0 | BG51: =BM51 -> 2678.4251 | BH51: 1621.7064 | BI51: 637.61542 | BJ51: 1920.9946 | BK51: 2485.8378 | BL51: 2691.2429 | BM51: 2678.4251 | BN51: 2982.1084 | BO51: 3384.5875 | BP51: 2781.8175 | BQ51: 2798.6538 | BR51: 3382.8497 | BS51: 3713.9472 | BT51: 31079.786 | BU51: =SUMIFS(BH51:BS51,$BH$3:$BS$3,"是") -> 12035.822
A52: 橱柜经销一部 | B52: 费用 | C52: 费用小计 | D52: 费用小计 | E52: =K52 -> 649.3985 | F52: 617.15939 | G52: 232.79507 | H52: 696.66282 | I52: 969.18748 | J52: 1035.6239 | K52: 649.3985 | L52: 1231.6469 | M52: 1160.968 | N52: 1095.8897 | O52: 988.35911 | P52: 1076.8315 | Q52: 1320.5584 | R52: 11075.081 | S52: =SUMIFS(F52:Q52,$F$2:$Q$2,"是") -> 4200.8272 | T52: 基数 | V52: 基数 | W52: 橱柜经销二部 | X52: 低值易耗品摊销 | Y52: =AE52 -> 0 | Z52: 0 | AA52: 0 | AB52: 0 | AC52: 0 | AD52: 0.0044950113 | AE52: 0 | AF52: 0 | AG52: 0 | AH52: 0 | AI52: 0 | AJ52: 0 | AK52: 0 | AL52: 0.0044950113 | AM52: =SUMIFS(Z52:AK52,$Z$2:$AK$2,"是") -> 0.0044950113 | AP52: 46 | AQ52: 加：星居微居 | AR52: =AX52 -> 0 | AS52: 0 | AT52: 0 | AU52: 0 | AV52: 0 | AW52: 0 | AX52: 0 | AY52: 0 | AZ52: 0 | BA52: 0 | BB52: 0 | BC52: 0 | BD52: 0 | BE52: 0 | BF52: =SUMIFS(AS52:BD52,$AS$3:$BD$3,"是") -> 0 | BG52: =BM52 -> 143.0911 | BH52: 24.710818 | BI52: 10.971888 | BJ52: 29.618941 | BK52: 20.833178 | BL52: 91.638296 | BM52: 143.0911 | BN52: 214.18742 | BO52: 226.23152 | BP52: 163.6833 | BQ52: 253.97463 | BR52: 342.85748 | BS52: 396.52119 | BT52: 1918.3198 | BU52: =SUMIFS(BH52:BS52,$BH$3:$BS$3,"是") -> 320.86423
A53: 橱柜经销一部 | B53: 利润 | C53: 利润小计 | D53: 利润小计 | E53: =K53 -> 2184.7829 | F53: 926.11649 | G53: 182.76673 | H53: 849.36639 | I53: 1481.3046 | J53: 1119.48 | K53: 2184.7829 | L53: 983.44755 | M53: 1533.832 | N53: 1528.623 | O53: 1352.5881 | P53: 1434.5059 | Q53: 1413.8955 | R53: 14990.709 | S53: =SUMIFS(F53:Q53,$F$2:$Q$2,"是") -> 6743.8171 | T53: 基数 | V53: 基数 | W53: 橱柜经销二部 | X53: 展示设计点将费用 | Y53: =AE53 -> 0 | Z53: -116.21278 | AA53: 0 | AB53: 0 | AC53: 0.070426505 | AD53: 0.08 | AE53: 0 | AF53: 0.1825 | AG53: 0.25569207 | AH53: 0 | AI53: 0.018098054 | AJ53: 0.011331308 | AK53: 90.087745 | AL53: -25.506986 | AM53: =SUMIFS(Z53:AK53,$Z$2:$AK$2,"是") -> -116.06235 | AP53: 47 | AQ53: 加：外贸共享 | AR53: =AX53 -> 0 | AS53: 0 | AT53: 0 | AU53: 0 | AV53: 0 | AW53: 0 | AX53: 0 | AY53: 0 | AZ53: 0 | BA53: 0 | BB53: 0 | BC53: 0 | BD53: 0 | BE53: 0 | BF53: =SUMIFS(AS53:BD53,$AS$3:$BD$3,"是") -> 0 | BG53: =BM53 -> 1169.7901 | BH53: 1053.2248 | BI53: 459.0268 | BJ53: 817.606 | BK53: 1156.6336 | BL53: 1136.3009 | BM53: 1169.7901 | BN53: 1173.4533 | BO53: 877.3855 | BP53: 970.3692 | BQ53: 858.6558 | BR53: 1234.5277 | BS53: 615.1571 | BT53: 11522.131 | BU53: =SUMIFS(BH53:BS53,$BH$3:$BS$3,"是") -> 5792.5822
A54: 橱柜经销一部 | B54: 毛利率 | C54: 毛利率 | D54: 毛利率 | E54: =K54 -> 0.32517956 | F54: 0.30252908 | G54: 0.25792713 | H54: 0.30501606 | I54: 0.35735323 | J54: 0.28246071 | K54: 0.32517956 | L54: 0.26470332 | M54: 0.32526349 | N54: 0.32957751 | O54: 0.32789387 | P54: 0.32389762 | Q54: 0.34285796 | R54: 0.31606896 | S54: =S51/S49 -> 0.31284787 | T54: 基数 | V54: 基数 | W54: 橱柜经销二部 | X54: 百货广告费 | Y54: =AE54 -> 905.01127 | Z54: 380.70471 | AA54: 159.99484 | AB54: 478.6647 | AC54: 692.70401 | AD54: 811.16353 | AE54: 905.01127 | AF54: 809.79791 | AG54: 869.02024 | AH54: 878.84642 | AI54: 700.18773 | AJ54: 750.26634 | AK54: 696.23232 | AL54: 8132.594 | AM54: =SUMIFS(Z54:AK54,$Z$2:$AK$2,"是") -> 3428.2431 | AP54: 48 | AQ54: 加：广分共享 | AR54: =AX54 -> 0 | AS54: 0 | AT54: 0 | AU54: 0 | AV54: 0 | AW54: 0 | AX54: 0 | AY54: 0 | AZ54: 0 | BA54: 0 | BB54: 0 | BC54: 0 | BD54: 0 | BE54: 0 | BF54: =SUMIFS(AS54:BD54,$AS$3:$BD$3,"是") -> 0 | BG54: =BM54 -> 967.46007 | BH54: 874.51185 | BI54: 329.20571 | BJ54: 684.36939 | BK54: 680.75182 | BL54: 886.72524 | BM54: 967.46007 | BN54: 967.28632 | BO54: 1116.516 | BP54: 1047.9767 | BQ54: 1020.7305 | BR54: 1354.4193 | BS54: 1817.8437 | BT54: 11747.797 | BU54: =SUMIFS(BH54:BS54,$BH$3:$BS$3,"是") -> 4423.0241
A55: 橱柜经销一部 | B55: 费用率 | C55: 费用率 | D55: 费用率 | E55: =K55 -> 0.07450868 | F55: 0.12098204 | G55: 0.14448914 | H55: 0.13744459 | I55: 0.14133581 | J55: 0.13573502 | K55: 0.07450868 | L55: 0.14718154 | M55: 0.14012932 | N55: 0.13761815 | O55: 0.13843836 | P55: 0.13888344 | Q55: 0.16557747 | R55: 0.13429439 | S55: =S52/S49 -> 0.12007881 | T55: 基数 | V55: 基数 | W55: 橱柜经销二部 | X55: 收回费用 | Y55: =AE55 -> -43.213741 | Z55: 44.062605 | AA55: -0.024747309 | AB55: -56.263709 | AC55: -39.329877 | AD55: -29.500233 | AE55: -43.213741 | AF55: -16.846578 | AG55: -50.829866 | AH55: -48.167023 | AI55: -47.092854 | AJ55: -53.174255 | AK55: -40.776633 | AL55: -381.15691 | AM55: =SUMIFS(Z55:AK55,$Z$2:$AK$2,"是") -> -124.2697 | AP55: 49 | AQ55: 共享小计 | AR55: =AX55 -> 846.15322 | AS55: 84.071536 | AT55: 13.849298 | AU55: 288.13603 | AV55: 281.17654 | AW55: 477.72027 | AX55: 846.15322 | AY55: 660.89914 | AZ55: 884.78233 | BA55: 786.82422 | BB55: 617.9241 | BC55: 651.32918 | BD55: 703.34947 | BE55: 6296.2153 | BF55: =SUMIFS(AS55:BD55,$AS$3:$BD$3,"是") -> 1991.1069 | BG55: =BM55 -> 19332.557 | BH55: 9682.4026 | BI55: 3440.9561 | BJ55: 12627.548 | BK55: 13203.234 | BL55: 16558.718 | BM55: 19332.557 | BN55: 21394.581 | BO55: 22887.146 | BP55: 18810.647 | BQ55: 18007.618 | BR55: 22631.666 | BS55: 24768.531 | BT55: 203345.6 | BU55: =SUMIFS(BH55:BS55,$BH$3:$BS$3,"是") -> 74845.415
A56: 橱柜经销一部 | B56: 净利率 | C56: 净利率 | D56: 净利率 | E56: =K56 -> 0.25067088 | F56: 0.18154704 | G56: 0.113438 | H56: 0.16757147 | I56: 0.21601742 | J56: 0.14672569 | K56: 0.25067088 | L56: 0.11752177 | M56: 0.18513417 | N56: 0.19195936 | O56: 0.1894555 | P56: 0.18501418 | Q56: 0.17728049 | R56: 0.18177457 | S56: =S53/S49 -> 0.19276906 | T56: 基数 | V56: 基数 | W56: 橱柜经销二部 | X56: 培训费 | Y56: =AE56 -> 0 | Z56: 0 | AA56: 0.11134057 | AB56: 0 | AC56: 0.8774 | AD56: 0.0084981898 | AE56: 0 | AF56: 0 | AG56: 0.0019493405 | AH56: 0.0066047405 | AI56: 0 | AJ56: 2.0175 | AK56: 0 | AL56: 3.0232928 | AM56: =SUMIFS(Z56:AK56,$Z$2:$AK$2,"是") -> 0.99723876 | AO56: TZ0151 | AP56: 50 | AQ56: 加：研发费用分摊 | AR56: =AX56 -> -40.354674 | AS56: -24.491599 | AT56: -7.9908465 | AU56: -23.603529 | AV56: -32.01255 | AW56: -35.322029 | AX56: -40.354674 | AY56: -38.561892 | AZ56: -41.758888 | BA56: -41.808857 | BB56: -35.56936 | BC56: -39.229622 | BD56: -41.710847 | BE56: -402.41469 | BF56: =SUMIFS(AS56:BD56,$AS$3:$BD$3,"是") -> -163.77523 | BG56: =BM56 -> 0 | BH56: 0 | BI56: 0 | BJ56: 0 | BK56: 0 | BL56: 0 | BM56: 0 | BN56: 0 | BO56: 0 | BP56: 0 | BQ56: 0 | BR56: 0 | BS56: 0 | BT56: 0 | BU56: =SUMIFS(BH56:BS56,$BH$3:$BS$3,"是") -> 0
A57: 橱柜经销二部 | B57: 收入 | C57: 按产品 | D57: 柜门 | E57: =K57 -> 3117.4992 | F57: 1267.982 | G57: 462.0892 | H57: 1662.8542 | I57: 2178.1393 | J57: 2534.8028 | K57: 3117.4992 | L57: 3082.3381 | M57: 3147.149 | N57: 3189.1349 | O57: 2495.2218 | P57: 2539.8758 | Q57: 2606.0132 | R57: 28283.1 | S57: =SUMIFS(F57:Q57,$F$2:$Q$2,"是") -> 11223.367 | T57: 基数 | V57: 基数 | W57: 橱柜经销二部 | X57: 税款 | Y57: =AE57 -> 0 | Z57: 4.2632564e-13 | AA57: 0 | AB57: 0 | AC57: 0 | AD57: 0 | AE57: 0 | AF57: 0 | AG57: 0 | AH57: 0 | AI57: 0 | AJ57: 0 | AK57: 0 | AL57: 0 | AM57: =SUMIFS(Z57:AK57,$Z$2:$AK$2,"是") -> 4.2632564e-13 | AP57: 51 | AQ57: 其中：剔除礼包 | AR57: =AX57 -> -4.617952 | AS57: -26.87921 | AT57: -12.298141 | AU57: -13.677903 | AV57: -9.957358 | AW57: -23.369554 | AX57: -4.617952 | AY57: -21.983313 | AZ57: -19.560908 | BA57: -14.5445 | BB57: -13.181327 | BC57: -17.972879 | BD57: -13.640016 | BE57: -191.68306 | BF57: =SUMIFS(AS57:BD57,$AS$3:$BD$3,"是") -> -90.800118 | BG57: =BM57 -> -11.33 | BH57: -137.625 | BI57: -63.765 | BJ57: -67.465 | BK57: -51.365 | BL57: -87.585 | BM57: -11.33 | BN57: -102.825 | BO57: -91.31 | BP57: -66.89 | BQ57: -60.335 | BR57: -83.324 | BS57: -62.81 | BT57: -886.629 | BU57: =SUMIFS(BH57:BS57,$BH$3:$BS$3,"是") -> -419.135
A58: 橱柜经销二部 | B58: 收入 | C58: 按产品 | D58: 台面 | E58: =K58 -> 1656.3277 | F58: 783.7069 | G58: 373.9071 | H58: 863.4952 | I58: 1288.4574 | J58: 1625.4286 | K58: 1656.3277 | L58: 1720.8138 | M58: 1704.767 | N58: 1657.9933 | O58: 1440.9287 | P58: 1524.5967 | Q58: 1531.8616 | R58: 16172.284 | S58: =SUMIFS(F58:Q58,$F$2:$Q$2,"是") -> 6591.3229 | T58: 基数 | V58: 基数 | W58: 橱柜经销二部 | X58: 资金占用费 | Y58: =AE58 -> 2.353 | Z58: 0.2223 | AA58: 6.4320991 | AB58: -24.880942 | AC58: 1.4957024 | AD58: 2.4209 | AE58: 2.353 | AF58: 1.4779018 | AG58: 0.011969046 | AH58: 0.0056112927 | AI58: 0.1716 | AJ58: 0.98947118 | AK58: 1.0378246 | AL58: -8.262563 | AM58: =SUMIFS(Z58:AK58,$Z$2:$AK$2,"是") -> -11.956941 | AP58: 39 | AQ58: 共享工程-各品类收入毛利橱柜 | AR58: =AX58 -> 281.14571 | AS58: 46.415875 | AT58: 35.937273 | AU58: 134.16178 | AV58: 116.7153 | AW58: 149.00024 | AX58: 281.14571 | AY58: 283.44339 | AZ58: 254.94071 | BA58: 274.75634 | BB58: 322.38819 | BC58: 284.94958 | BD58: 442.37209 | BE58: 2626.2265 | BF58: =SUMIFS(AS58:BD58,$AS$3:$BD$3,"是") -> 763.37617 | BG58: =BM58 -> 0 | BU58: =SUMIFS(BH58:BS58,$BH$3:$BS$3,"是") -> 0
A59: 橱柜经销二部 | B59: 收入 | C59: 按产品 | D59: OEM烟灶 | E59: =K59 -> 937.38645 | F59: 375.4227 | G59: 191.6028 | H59: 628.8268 | I59: 1059.0568 | J59: 1030.2569 | K59: 937.38645 | L59: 595.93835 | M59: 500.80172 | N59: 574.28089 | O59: 573.98873 | P59: 716.40975 | Q59: 394.90105 | R59: 7578.8729 | S59: =SUMIFS(F59:Q59,$F$2:$Q$2,"是") -> 4222.5525 | T59: 基数 | V59: 基数 | W59: 橱柜经销二部 | X59: 业务招待费 | Y59: =AE59 -> 0.12610502 | Z59: 0.20305249 | AA59: 0.0021016187 | AB59: 0.4183752 | AC59: 0.25616427 | AD59: 0.013645144 | AE59: 0.12610502 | AF59: 0.33684081 | AG59: 0.076633523 | AH59: 0.016584654 | AI59: 0.1415552 | AJ59: 0 | AK59: 0 | AL59: 1.5910579 | AM59: =SUMIFS(Z59:AK59,$Z$2:$AK$2,"是") -> 1.0194437 | AP59: 52 | AQ59: 共享工程-各品类收入毛利百货 | AR59: =AX59 -> 42.397694 | AS59: 22.923103 | AT59: 9.706499 | AU59: 42.738365 | AV59: 20.908469 | AW59: 65.840926 | AX59: 42.397694 | AY59: 62.822475 | AZ59: 82.043852 | BA59: 59.432694 | BB59: 43.345749 | BC59: 47.072081 | BD59: 51.80606 | BE59: 551.03797 | BF59: =SUMIFS(AS59:BD59,$AS$3:$BD$3,"是") -> 204.51506 | BG59: =BM59 -> 0 | BH59: 0 | BI59: 0 | BJ59: 0 | BK59: 0 | BL59: 0 | BM59: 0 | BN59: 0 | BO59: 0 | BP59: 0 | BQ59: 0 | BR59: 0 | BS59: 0 | BT59: 0 | BU59: =SUMIFS(BH59:BS59,$BH$3:$BS$3,"是") -> 0
A60: 橱柜经销二部 | B60: 收入 | C60: 按产品 | D60: OEM其他 | E60: =K60 -> 1297.2089 | F60: 510.66035 | G60: 231.36802 | H60: 642.9438 | I60: 970.09019 | J60: 1246.2393 | K60: 1297.2089 | L60: 736.75659 | M60: 1328.8046 | N60: 1437.9349 | O60: 1053.4387 | P60: 1154.3298 | Q60: 1030.8965 | R60: 11640.672 | S60: =SUMIFS(F60:Q60,$F$2:$Q$2,"是") -> 4898.5106 | T60: 基数 | V60: 基数 | W60: 橱柜经销二部 | X60: 质量赔偿费 | Y60: =AE60 -> 0 | Z60: 0 | AA60: 0 | AB60: 0 | AC60: 0 | AD60: 0 | AE60: 0 | AF60: 0 | AG60: 0.289 | AH60: 0 | AI60: 0 | AJ60: 0 | AK60: -0.5638 | AL60: -0.2748 | AM60: =SUMIFS(Z60:AK60,$Z$2:$AK$2,"是") -> 0 | AP60: 53 | AQ60: 加：电器厂共享利润 | AR60: =AX60 -> 522.60982 | AS60: 14.732558 | AT60: -31.794475 | AU60: 111.23588 | AV60: 143.55277 | AW60: 262.8791 | AX60: 522.60982 | AY60: 314.63328 | AZ60: 547.79776 | BA60: 452.63518 | BB60: 252.19015 | BC60: 319.30752 | BD60: 209.17132 | BE60: 3118.9509 | BF60: =SUMIFS(AS60:BD60,$AS$3:$BD$3,"是") -> 1023.2157 | BG60: =BM60 -> 0 | BH60: 0 | BI60: 0 | BJ60: 0 | BK60: 0 | BL60: 0 | BM60: 0 | BN60: 0 | BO60: 0 | BP60: 0 | BQ60: 0 | BR60: 0 | BS60: 0 | BT60: 0 | BU60: =SUMIFS(BH60:BS60,$BH$3:$BS$3,"是") -> 0
A61: 橱柜经销二部 | B61: 收入 | C61: 按产品 | D61: 自制烟灶 | E61: =K61 -> 830.47825 | F61: 359.8568 | G61: 126.99986 | H61: 349.90845 | I61: 501.0498 | J61: 589.42268 | K61: 830.47825 | L61: 875.29942 | M61: 846.50522 | N61: 754.01018 | O61: 500.1099 | P61: 569.18675 | Q61: 457.25236 | R61: 6760.0797 | S61: =SUMIFS(F61:Q61,$F$2:$Q$2,"是") -> 2757.7158 | T61: 基数 | V61: 基数 | W61: 橱柜经销二部 | X61: 其他 | Y61: =AE61 -> 1.7597154 | Z61: 0.16952 | AA61: -93.173564 | AB61: 2.5771829 | AC61: -0.40421479 | AD61: 1.3565257 | AE61: 1.7597154 | AF61: -7.134033 | AG61: 1.8878042 | AH61: 1.9125924 | AI61: 4.2972807 | AJ61: 1.669071 | AK61: 1.2044715 | AL61: -83.877647 | AM61: =SUMIFS(Z61:AK61,$Z$2:$AK$2,"是") -> -87.714834 | AP61: 54 | AQ61: 其中：工程橱柜-共享百货 | AR61: =AX61 -> 0 | AS61: 0 | AT61: 0 | AU61: 0 | AV61: 0 | AW61: 0 | AX61: 0 | AY61: 0 | AZ61: 0 | BA61: 0 | BB61: 0 | BC61: 0 | BD61: 0 | BE61: 0 | BF61: =SUMIFS(AS61:BD61,$AS$3:$BD$3,"是") -> 0 | BG61: =BM61 -> 11147.769 | BH61: 4989.1206 | BI61: 1585.2387 | BJ61: 7321.4583 | BK61: 6384.8498 | BL61: 9021.8363 | BM61: 11147.769 | BN61: 12312.022 | BO61: 13249.284 | BP61: 10061.883 | BQ61: 9640.6793 | BR61: 12212.708 | BS61: 13697.607 | BT61: 111624.46 | BU61: =SUMIFS(BH61:BS61,$BH$3:$BS$3,"是") -> 40450.272
A62: 橱柜经销二部 | B62: 收入 | C62: 按产品 | D62: 其他加收 | E62: =K62 -> 1.1649 | F62: 0.4659 | G62: 0.06 | H62: 0.2755 | I62: 2.339 | J62: 0.9171 | K62: 1.1649 | L62: 4.0908 | M62: 0.2565 | N62: 2.5084 | O62: 1.6804 | P62: 1.7739 | Q62: 1.6975 | R62: 17.2299 | S62: =SUMIFS(F62:Q62,$F$2:$Q$2,"是") -> 5.2224 | T62: 基数 | V62: 基数 | W62: 橱柜经销二部 | X62: 百货进出仓 | Y62: =AE62 -> 0 | Z62: 0 | AA62: 0 | AB62: 0 | AC62: 0 | AD62: 0 | AE62: 0 | AF62: 0 | AG62: 0 | AH62: 0 | AI62: 0 | AJ62: 0 | AK62: 0 | AL62: 0 | AM62: =SUMIFS(Z62:AK62,$Z$2:$AK$2,"是") -> 0 | AO62: TZ0038 | AP62: 55 | AQ62: 整装大家居共享（百货） | AR62: =AX62 -> 0 | AS62: 0 | AT62: 0 | AU62: 0 | AV62: 0 | AW62: 0 | AX62: 0 | AY62: 0 | AZ62: 0 | BA62: 0 | BB62: 0 | BC62: 0 | BD62: 0 | BE62: 0 | BF62: =SUMIFS(AS62:BD62,$AS$3:$BD$3,"是") -> 0 | BG62: =BM62 -> 1416.3785 | BH62: 576.86715 | BI62: 159.43523 | BJ62: 917.56193 | BK62: 1021.9146 | BL62: 1194.0584 | BM62: 1416.3785 | BN62: 1600.1345 | BO62: 1941.6776 | BP62: 1585.4629 | BQ62: 1428.0055 | BR62: 1189.1162 | BS62: 1357.3323 | BT62: 14387.945 | BU62: =SUMIFS(BH62:BS62,$BH$3:$BS$3,"是") -> 5286.2158
A63: 橱柜经销二部 | B63: 收入 | C63: 按订单类型 | D63: 常规单 | E63: =K63 -> 5483.2189 | F63: 2414.5702 | G63: 1053.5955 | H63: 2978.2011 | I63: 4366.5629 | J63: 5079.8261 | K63: 5483.2189 | L63: 4693.4771 | M63: 5332.3227 | N63: 5641.8526 | O63: 4410.1184 | P63: 4902.4399 | Q63: 4321.3643 | R63: 50677.549 | S63: =SUMIFS(F63:Q63,$F$2:$Q$2,"是") -> 21375.975 | T63: 基数 | V63: 基数 | W63: 橱柜经销二部 | X63: 展厅装修费用 | Y63: =AE63 -> 0 | Z63: 0 | AA63: 0 | AB63: 0 | AC63: 0 | AD63: 0 | AE63: 0 | AF63: 0 | AG63: 0 | AH63: 0 | AI63: 0 | AJ63: 0 | AK63: 0 | AL63: 0 | AM63: =SUMIFS(Z63:AK63,$Z$2:$AK$2,"是") -> 0 | AO63: TZ0021 | AP63: 56 | AQ63: 欧铂丽共享（百货） | AR63: =AX63 -> 0 | AS63: 0 | AT63: 0 | AU63: 0 | AV63: 0 | AW63: 0 | AX63: 0 | AY63: 0 | AZ63: 0 | BA63: 0 | BB63: 0 | BC63: 0 | BD63: 0 | BE63: 0 | BF63: =SUMIFS(AS63:BD63,$AS$3:$BD$3,"是") -> 0 | BG63: =BM63 -> 1276.9801 | BH63: 336.3191 | BI63: 143.9532 | BJ63: 499.4549 | BK63: 888.8861 | BL63: 980.883 | BM63: 1276.9801 | BN63: 1453.3094 | BO63: 1487.9737 | BP63: 1448.9401 | BQ63: 1362.3327 | BR63: 1793.6121 | BS63: 1985.1322 | BT63: 13657.777 | BU63: =SUMIFS(BH63:BS63,$BH$3:$BS$3,"是") -> 4126.4764
A64: 橱柜经销二部 | B64: 收入 | C64: 按订单类型 | D64: 家装单 | E64: =K64 -> 675.7656 | F64: 265.0613 | G64: 84.2599 | H64: 385.6371 | I64: 471.0303 | J64: 589.7743 | K64: 675.7656 | L64: 834.0571 | M64: 701.7349 | N64: -75.41 | O64: 660.0185 | P64: 543.1498 | Q64: 647.7514 | R64: 5782.8302 | S64: =SUMIFS(F64:Q64,$F$2:$Q$2,"是") -> 2471.5285 | T64: 基数 | V64: 基数 | W64: 橱柜经销二部 | X64: 政府补贴 | Y64: =AE64 -> 0 | Z64: 0 | AA64: 0 | AB64: 0 | AC64: 0 | AD64: 0 | AE64: 0 | AF64: 0 | AG64: 0 | AH64: 0 | AI64: 0 | AJ64: 0 | AK64: 0 | AL64: 0 | AM64: =SUMIFS(Z64:AK64,$Z$2:$AK$2,"是") -> 0 | AO64: TZ0029 | AP64: 58 | AQ64: 外贸共享（百货） | AR64: =AX64 -> 0 | AS64: 0 | AT64: 0 | AU64: 0 | AV64: 0 | AW64: 0 | AX64: 0 | AY64: 0 | AZ64: 0 | BA64: 0 | BB64: 0 | BC64: 0 | BD64: 0 | BE64: 0 | BF64: =SUMIFS(AS64:BD64,$AS$3:$BD$3,"是") -> 0 | BG64: =BM64 -> 532.66303 | BH64: 205.94184 | BI64: 115.5091 | BJ64: 436.48413 | BK64: 563.52703 | BL64: 556.03291 | BM64: 532.66303 | BN64: 692.07923 | BO64: 603.49001 | BP64: 750.51443 | BQ64: 644.58573 | BR64: 1121.5754 | BS64: 1184.9902 | BT64: 7407.3931 | BU64: =SUMIFS(BH64:BS64,$BH$3:$BS$3,"是") -> 2410.158
A65: 橱柜经销二部 | B65: 收入 | C65: 按订单类型 | D65: 直供单 | E65: =K65 -> 1633.6688 | F65: 614.1377 | G65: 245.9486 | H65: 775.8281 | I65: 1147.2275 | J65: 1347.578 | K65: 1633.6688 | L65: 1436.3198 | M65: 1435.5356 | N65: 1967.4321 | O65: 938.45085 | P65: 980.28955 | Q65: 970.6952 | R65: 13493.112 | S65: =SUMIFS(F65:Q65,$F$2:$Q$2,"是") -> 5764.3887 | T65: 基数 | V65: 基数 | W65: 橱柜经销二部 | X65: 经销商会议费用 | Y65: =AE65 -> 0 | Z65: 0 | AA65: 0 | AB65: 0 | AC65: 0 | AD65: 0 | AE65: 0 | AF65: 0 | AG65: 0 | AH65: 0 | AI65: 0 | AJ65: 0 | AK65: 0 | AL65: 0 | AM65: =SUMIFS(Z65:AK65,$Z$2:$AK$2,"是") -> 0 | AO65: TZ0012 | AP65: 59 | AQ65: 广分共享（百货） | AR65: =AX65 -> 0 | AS65: 0 | AT65: 0 | AU65: 0 | AV65: 0 | AW65: 0 | AX65: 0 | AY65: 0 | AZ65: 0 | BA65: 0 | BB65: 0 | BC65: 0 | BD65: 0 | BE65: 0 | BF65: =SUMIFS(AS65:BD65,$AS$3:$BD$3,"是") -> 0 | BG65: =BM65 -> 1832.2189 | BH65: 1164.391 | BI65: 371.4874 | BJ65: 1192.8493 | BK65: 1565.6839 | BL65: 1860.6484 | BM65: 1832.2189 | BN65: 2131.2929 | BO65: 2292.1807 | BP65: 1987.235 | BQ65: 1870.3038 | BR65: 2376.0636 | BS65: 2647.6304 | BT65: 21291.985 | BU65: =SUMIFS(BH65:BS65,$BH$3:$BS$3,"是") -> 7987.2789
A66: 橱柜经销二部 | B66: 收入 | C66: 按订单类型 | D66: 网销单 | E66: =K66 -> 0 | F66: 0 | G66: 0 | H66: 0 | I66: 0 | J66: 0 | K66: 0 | L66: 0 | M66: 0 | N66: 0 | O66: 0 | P66: 0 | Q66: 0 | R66: 0 | S66: =SUMIFS(F66:Q66,$F$2:$Q$2,"是") -> 0 | T66: 基数 | V66: 基数 | W66: 橱柜经销二部 | X66: 软件提点 | Y66: =AE66 -> 0 | Z66: 0 | AA66: 0 | AB66: 0 | AC66: 0 | AD66: 0 | AE66: 0 | AF66: 0 | AG66: 0 | AH66: 0 | AI66: 0 | AJ66: 0 | AK66: 0 | AL66: 0 | AM66: =SUMIFS(Z66:AK66,$Z$2:$AK$2,"是") -> 0 | AP66: 42 | AQ66: 加：工程橱柜-共享橱柜 | AR66: =AX66 -> 0 | AS66: 0 | AT66: 0 | AU66: 0 | AV66: 0 | AW66: 0 | AX66: 0 | AY66: 0 | AZ66: 0 | BA66: 0 | BB66: 0 | BC66: 0 | BD66: 0 | BE66: 0 | BF66: =SUMIFS(AS66:BD66,$AS$3:$BD$3,"是") -> 0 | BG66: =BM66 -> 846.20611 | BH66: 457.31538 | BI66: 266.12802 | BJ66: 728.1453 | BK66: 920.1539 | BL66: 830.59452 | BM66: 846.20611 | BN66: 850.81541 | BO66: 1092.4069 | BP66: 794.58251 | BQ66: 928.35002 | BR66: 1006.786 | BS66: 1066.3168 | BT66: 9787.8009 | BU66: =SUMIFS(BH66:BS66,$BH$3:$BS$3,"是") -> 4048.5432
A67: 橱柜经销二部 | B67: 收入 | C67: 按订单类型 | D67: 星居单 | E67: =K67 -> 47.4121 | F67: 4.3255 | G67: 2.223 | H67: 8.6377 | I67: 14.3118 | J67: 9.889 | K67: 47.4121 | L67: 51.3831 | M67: 58.6909 | N67: 81.9879 | O67: 51.4557 | P67: 75.6576 | Q67: 77.079 | R67: 483.0533 | S67: =SUMIFS(F67:Q67,$F$2:$Q$2,"是") -> 86.7991 | T67: 基数 | V67: 基数 | W67: 橱柜经销二部 | X67: 材料成本差异 | Y67: =AE67 -> 0 | Z67: 0 | AA67: 0 | AB67: 0 | AC67: 0 | AD67: 0 | AE67: 0 | AF67: 0 | AG67: 0 | AH67: 0 | AI67: 0 | AJ67: 0 | AK67: 0 | AL67: 0 | AM67: =SUMIFS(Z67:AK67,$Z$2:$AK$2,"是") -> 0 | AO67: TZ0020 | AP67: 61 | AQ67: 欧铂丽共享（橱柜） | AR67: =AX67 -> 0 | AS67: 0 | AT67: 0 | AU67: 0 | AV67: 0 | AW67: 0 | AX67: 0 | AY67: 0 | AZ67: 0 | BA67: 0 | BB67: 0 | BC67: 0 | BD67: 0 | BE67: 0 | BF67: =SUMIFS(AS67:BD67,$AS$3:$BD$3,"是") -> 0 | BG67: =BM67 -> 1063.213 | BH67: 971.336 | BI67: 429.4237 | BJ67: 768.6663 | BK67: 1074.0597 | BL67: 1076.9336 | BM67: 1063.213 | BN67: 1116.9008 | BO67: 797.4168 | BP67: 888.084 | BQ67: 781.1113 | BR67: 1130.2895 | BS67: 547.811 | BT67: 10645.246 | BU67: =SUMIFS(BH67:BS67,$BH$3:$BS$3,"是") -> 5383.6323
A68: 橱柜经销二部 | B68: 收入 | C68: 按订单类型 | D68: 微居单 | E68: =K68 -> 0 | F68: 0 | G68: 0 | H68: 0 | I68: 0 | J68: 0 | K68: 0 | L68: 0 | M68: 0 | N68: 0 | O68: 5.3248 | P68: 4.6359 | Q68: 5.7032 | R68: 15.6639 | S68: =SUMIFS(F68:Q68,$F$2:$Q$2,"是") -> 0 | T68: 基数 | V68: 基数 | W68: 橱柜经销二部 | X68: 维修费 | Y68: =AE68 -> 0 | Z68: 0 | AA68: 0 | AB68: 0 | AC68: 0 | AD68: 0 | AE68: 0 | AF68: 0 | AG68: 0 | AH68: 0 | AI68: 0 | AJ68: 0 | AK68: 0 | AL68: 0 | AM68: =SUMIFS(Z68:AK68,$Z$2:$AK$2,"是") -> 0 | AO68: TZ0037 | AP68: 62 | AQ68: 整装大家居共享（橱柜） | AR68: =AX68 -> 0 | AS68: 0 | AT68: 0 | AU68: 0 | AV68: 0 | AW68: 0 | AX68: 0 | AY68: 0 | AZ68: 0 | BA68: 0 | BB68: 0 | BC68: 0 | BD68: 0 | BE68: 0 | BF68: =SUMIFS(AS68:BD68,$AS$3:$BD$3,"是") -> 0 | BG68: =BM68 -> 106.5771 | BH68: 81.8888 | BI68: 29.6031 | BJ68: 48.9397 | BK68: 82.5739 | BL68: 59.3673 | BM68: 106.5771 | BN68: 56.5525 | BO68: 79.9687 | BP68: 82.2852 | BQ68: 77.5445 | BR68: 104.2382 | BS68: 67.3461 | BT68: 876.8851 | BU68: =SUMIFS(BH68:BS68,$BH$3:$BS$3,"是") -> 408.9499
A69: 橱柜经销二部 | B69: 收入 | C69: 按合同类型 | D69: 普通单 | E69: =K69 -> 6435.3943 | F69: 3039.3063 | G69: 1161.7509 | H69: 3758.7073 | I69: 5489.996 | J69: 5849.7406 | K69: 6435.3943 | L69: 5683.3975 | M69: 6274.1508 | N69: 5903.3266 | O69: 5329.1688 | P69: 6079.671 | Q69: 5641.4007 | R69: 60646.011 | S69: =SUMIFS(F69:Q69,$F$2:$Q$2,"是") -> 25734.895 | T69: 基数 | V69: 基数 | W69: 橱柜经销二部 | X69: 呆滞物料收支 | Y69: =AE69 -> 0 | Z69: 0 | AA69: 0 | AB69: 0 | AC69: 0 | AD69: 0 | AE69: 0 | AF69: 0 | AG69: 0 | AH69: 0 | AI69: 0 | AJ69: 0 | AK69: 0 | AL69: 0 | AM69: =SUMIFS(Z69:AK69,$Z$2:$AK$2,"是") -> 0 | AO69: TZ0028 | AP69: 63 | AQ69: 外贸共享（橱柜） | AR69: =AX69 -> 0 | AS69: 0 | AT69: 0 | AU69: 0 | AV69: 0 | AW69: 0 | AX69: 0 | AY69: 0 | AZ69: 0 | BA69: 0 | BB69: 0 | BC69: 0 | BD69: 0 | BE69: 0 | BF69: =SUMIFS(AS69:BD69,$AS$3:$BD$3,"是") -> 0 | BG69: =BM69 -> 839.60357 | BH69: 767.86478 | BI69: 289.8665 | BJ69: 601.70099 | BK69: 595.372 | BL69: 768.69931 | BM69: 839.60357 | BN69: 805.62437 | BO69: 956.88848 | BP69: 911.75217 | BQ69: 858.60748 | BR69: 1154.1327 | BS69: 1539.2293 | BT69: 10089.342 | BU69: =SUMIFS(BH69:BS69,$BH$3:$BS$3,"是") -> 3863.1072
A70: 橱柜经销二部 | B70: 收入 | C70: 按合同类型 | D70: 样品单 | E70: =K70 -> 1343.982 | F70: 241.90366 | G70: 163.86981 | H70: 339.12541 | I70: 455.86266 | J70: 1132.8899 | K70: 1343.982 | L70: 1269.6722 | M70: 1193.8038 | N70: 1645.2385 | O70: 671.09506 | P70: 372.45168 | Q70: 325.89474 | R70: 9155.7894 | S70: =SUMIFS(F70:Q70,$F$2:$Q$2,"是") -> 3677.6334 | T70: 基数 | V70: 基数 | W70: 橱柜经销二部 | X70: 委托加工费 | Y70: =AE70 -> 15.3256 | Z70: 0 | AA70: 0 | AB70: 5.746244 | AC70: 5.9148 | AD70: 30.10998 | AE70: 15.3256 | AF70: 13.322582 | AG70: 9.0437871 | AH70: 8.3003123 | AI70: 13.453127 | AJ70: 9.4852053 | AK70: 14.227394 | AL70: 124.92903 | AM70: =SUMIFS(Z70:AK70,$Z$2:$AK$2,"是") -> 57.096624 | AO70: TZ0011 | AP70: 64 | AQ70: 广分共享（橱柜） | AR70: =AX70 -> 0 | AS70: 0 | AT70: 0 | AU70: 0 | AV70: 0 | AW70: 0 | AX70: 0 | AY70: 0 | AZ70: 0 | BA70: 0 | BB70: 0 | BC70: 0 | BD70: 0 | BE70: 0 | BF70: =SUMIFS(AS70:BD70,$AS$3:$BD$3,"是") -> 0 | BG70: =BM70 -> 127.8565 | BH70: 106.64707 | BI70: 39.339215 | BJ70: 82.6684 | BK70: 85.379825 | BL70: 118.02593 | BM70: 127.8565 | BN70: 161.66195 | BO70: 159.62755 | BP70: 136.22455 | BQ70: 162.12306 | BR70: 200.28665 | BS70: 278.61442 | BT70: 1658.4551 | BU70: =SUMIFS(BH70:BS70,$BH$3:$BS$3,"是") -> 559.91693
A71: 橱柜经销二部 | B71: 收入 | C71: 按合同类型 | D71: 遗留单 | E71: =K71 -> 60.6892 | F71: 16.8847 | G71: 60.4063 | H71: 50.4712 | I71: 53.2738 | J71: 44.4369 | K71: 60.6892 | L71: 62.1673 | M71: 60.3294 | N71: 67.2975 | O71: 65.1044 | P71: 54.0501 | Q71: 55.2977 | R71: 650.4085 | S71: =SUMIFS(F71:Q71,$F$2:$Q$2,"是") -> 286.1621 | T71: 基数 | V71: 基数 | W71: 橱柜经销二部 | X71: 佣金 | Y71: =AE71 -> 0 | Z71: 0 | AA71: 0 | AB71: 0 | AC71: 0 | AD71: 0 | AE71: 0 | AF71: 0 | AG71: 0 | AH71: 0 | AI71: 0 | AJ71: 0 | AK71: 0 | AL71: 0 | AM71: =SUMIFS(Z71:AK71,$Z$2:$AK$2,"是") -> 0 | AO71: TZ0046 | AP71: 65 | AQ71: 融合店其他品类收入(集成家居) | AR71: =AX71 -> 0 | AS71: 0 | AT71: 0 | AU71: 0 | AV71: 0 | AW71: 0 | AX71: 0 | AY71: 0 | AZ71: 0 | BA71: 0 | BB71: 0 | BC71: 0 | BD71: 0 | BE71: 0 | BF71: =SUMIFS(AS71:BD71,$AS$3:$BD$3,"是") -> 0 | BG71: =BM71 -> 103.6637 | BH71: 20.7329 | BI71: 3.5689 | BJ71: 15.0376 | BK71: 7.5273 | BL71: 63.0126 | BM71: 103.6637 | BN71: 141.3128 | BO71: 163.2881 | BP71: 113.1202 | BQ71: 197.3671 | BR71: 278.6168 | BS71: 325.561 | BT71: 1432.809 | BU71: =SUMIFS(BH71:BS71,$BH$3:$BS$3,"是") -> 213.543
A72: 橱柜经销二部 | B72: 成本 | C72: 按产品 | D72: 柜门 | E72: =K72 -> 2253.0527 | F72: 950.32995 | G72: 366.60054 | H72: 1263.8392 | I72: 1468.2006 | J72: 1957.2697 | K72: 2253.0527 | L72: 2208.6437 | M72: 2234.5584 | N72: 2260.7026 | O72: 1763.6391 | P72: 1790.1419 | Q72: 1816.1143 | R72: 20333.093 | S72: =SUMIFS(F72:Q72,$F$2:$Q$2,"是") -> 8259.2927 | T72: 基数 | V72: 基数 | W72: 橱柜经销二部 | X72: 燃气动力 | Y72: =AE72 -> 0 | Z72: 0 | AA72: 0 | AB72: 0 | AC72: 0 | AD72: 0 | AE72: 0 | AF72: 0 | AG72: 0 | AH72: 0 | AI72: 0 | AJ72: 0 | AK72: 0 | AL72: 0 | AM72: =SUMIFS(Z72:AK72,$Z$2:$AK$2,"是") -> 0 | AO72: TZ0047 | AP72: 66 | AQ72: 融合店其他品类收入(木门) | AR72: =AX72 -> 0 | AS72: 0 | AT72: 0 | AU72: 0 | AV72: 0 | AW72: 0 | AX72: 0 | AY72: 0 | AZ72: 0 | BA72: 0 | BB72: 0 | BC72: 0 | BD72: 0 | BE72: 0 | BF72: =SUMIFS(AS72:BD72,$AS$3:$BD$3,"是") -> 0 | BG72: =BM72 -> 15.380843 | BH72: 1.891918 | BI72: 3.861388 | BJ72: 8.760141 | BK72: 5.975178 | BL72: 15.223596 | BM72: 15.380843 | BN72: 31.072294 | BO72: 20.762338 | BP72: 22.316697 | BQ72: 30.054981 | BR72: 32.715043 | BS72: 39.665961 | BT72: 227.68038 | BU72: =SUMIFS(BH72:BS72,$BH$3:$BS$3,"是") -> 51.093064
A73: 橱柜经销二部 | B73: 成本 | C73: 按产品 | D73: 台面 | E73: =K73 -> 1193.8597 | F73: 587.37438 | G73: 293.8016 | H73: 656.14561 | I73: 868.0242 | J73: 1251.3591 | K73: 1193.8597 | L73: 1231.6886 | M73: 1208.226 | N73: 1172.5517 | O73: 1018.9363 | P73: 1075.9435 | Q73: 1068.5572 | R73: 11626.468 | S73: =SUMIFS(F73:Q73,$F$2:$Q$2,"是") -> 4850.5646 | T73: 基数 | V73: 基数 | W73: 橱柜经销二部 | X73: 搬迁费 | Y73: =AE73 -> 0 | Z73: 0 | AA73: 0 | AB73: 0 | AC73: 0 | AD73: 0 | AE73: 0 | AF73: 0 | AG73: 0 | AH73: 0 | AI73: 0 | AJ73: 0 | AK73: 0 | AL73: 0 | AM73: =SUMIFS(Z73:AK73,$Z$2:$AK$2,"是") -> 0 | AO73: TZ0048 | AP73: 67 | AQ73: 融合店其他品类收入(卫浴) | AR73: =AX73 -> 0 | AS73: 0 | AT73: 0 | AU73: 0 | AV73: 0 | AW73: 0 | AX73: 0 | AY73: 0 | AZ73: 0 | BA73: 0 | BB73: 0 | BC73: 0 | BD73: 0 | BE73: 0 | BF73: =SUMIFS(AS73:BD73,$AS$3:$BD$3,"是") -> 0 | BG73: =BM73 -> 15.3549 | BH73: 2.086 | BI73: 3.5416 | BJ73: 5.8212 | BK73: 7.3307 | BL73: 13.4021 | BM73: 15.3549 | BN73: 35.8996 | BO73: 18.2873 | BP73: 10.9185 | BQ73: 22.4907 | BR73: 19.5513 | BS73: 26.5539 | BT73: 181.2378 | BU73: =SUMIFS(BH73:BS73,$BH$3:$BS$3,"是") -> 47.5365
A74: 橱柜经销二部 | B74: 成本 | C74: 按产品 | D74: OEM烟灶 | E74: =K74 -> 630.7586 | F74: 235.58801 | G74: 129.55694 | H74: 412.47396 | I74: 655.23546 | J74: 639.3761 | K74: 630.7586 | L74: 370.97205 | M74: 330.82392 | N74: 380.26134 | O74: 420.19177 | P74: 502.62747 | Q74: 249.45209 | R74: 4957.3177 | S74: =SUMIFS(F74:Q74,$F$2:$Q$2,"是") -> 2702.9891 | T74: 基数 | V74: 基数 | W74: 橱柜经销二部 | X74: 劳务赔偿费 | Y74: =AE74 -> 0 | Z74: 0 | AA74: 0 | AB74: 0 | AC74: 0 | AD74: 0 | AE74: 0 | AF74: 0 | AG74: 0 | AH74: 0 | AI74: 0 | AJ74: 0 | AK74: 0 | AL74: 0 | AM74: =SUMIFS(Z74:AK74,$Z$2:$AK$2,"是") -> 0 | AO74: TZ0050 | AP74: 68 | AQ74: 融合店其他品类收入(软装) | AR74: =AX74 -> 0 | AS74: 0 | AT74: 0 | AU74: 0 | AV74: 0 | AW74: 0 | AX74: 0 | AY74: 0 | AZ74: 0 | BA74: 0 | BB74: 0 | BC74: 0 | BD74: 0 | BE74: 0 | BF74: =SUMIFS(AS74:BD74,$AS$3:$BD$3,"是") -> 0 | BG74: =BM74 -> 0.5093 | BH74: 0 | BI74: 0 | BJ74: 0 | BK74: 0 | BL74: 0 | BM74: 0.5093 | BN74: 4.034038 | BO74: 18.419504 | BP74: 10.163054 | BQ74: 2.767166 | BR74: 10.713888 | BS74: 3.990747 | BT74: 50.597697 | BU74: =SUMIFS(BH74:BS74,$BH$3:$BS$3,"是") -> 0.5093
A75: 橱柜经销二部 | B75: 成本 | C75: 按产品 | D75: OEM其他 | E75: =K75 -> 737.97474 | F75: 305.05918 | G75: 137.86969 | H75: 382.53563 | I75: 600.71365 | J75: 819.06053 | K75: 737.97474 | L75: 869.42238 | M75: 775.59233 | N75: 863.57721 | O75: 590.81951 | P75: 676.53117 | Q75: 544.30547 | R75: 7303.4615 | S75: =SUMIFS(F75:Q75,$F$2:$Q$2,"是") -> 2983.2134 | T75: 基数 | V75: 基数 | W75: 橱柜经销二部 | X75: 研发费 | Y75: =AE75 -> 0 | Z75: 0 | AA75: 0 | AB75: 0 | AC75: 0 | AD75: 0 | AE75: 0 | AF75: 0 | AG75: 0 | AH75: 0 | AI75: 0 | AJ75: 0 | AK75: 0 | AL75: 0 | AM75: =SUMIFS(Z75:AK75,$Z$2:$AK$2,"是") -> 0 | AO75: TZ0049 | AP75: 69 | AQ75: 融合店其他品类收入(金属门窗) | AR75: =AX75 -> 0 | AS75: 0 | AT75: 0 | AU75: 0 | AV75: 0 | AW75: 0 | AX75: 0 | AY75: 0 | AZ75: 0 | BA75: 0 | BB75: 0 | BC75: 0 | BD75: 0 | BE75: 0 | BF75: =SUMIFS(AS75:BD75,$AS$3:$BD$3,"是") -> 0 | BG75: =BM75 -> 0 | BH75: 0 | BI75: 0 | BJ75: 0 | BK75: 0 | BL75: 0 | BM75: 0 | BN75: 0.3287165 | BO75: 0 | BP75: 3.060958 | BQ75: 0 | BR75: 0.357648 | BS75: 0 | BT75: 3.7473225 | BU75: =SUMIFS(BH75:BS75,$BH$3:$BS$3,"是") -> 0
A76: 橱柜经销二部 | B76: 成本 | C76: 按产品 | D76: 自制烟灶 | E76: =K76 -> 473.48542 | F76: 195.08447 | G76: 69.391408 | H76: 187.10622 | I76: 269.81953 | J76: 317.96995 | K76: 473.48542 | L76: 497.53206 | M76: 494.75409 | N76: 418.00084 | O76: 272.79954 | P76: 312.15197 | Q76: 250.08621 | R76: 3758.1817 | S76: =SUMIFS(F76:Q76,$F$2:$Q$2,"是") -> 1512.857 | T76: 基数 | V76: 基数 | W76: 橱柜经销二部 | X76: 合计 | Y76: =AE76 -> 1137.606 | Z76: 384.10473 | AA76: 97.341491 | AB76: 522.91719 | AC76: 881.22172 | AD76: 1025.7859 | AE76: 1137.606 | AF76: 1018.0426 | AG76: 1077.8268 | AH76: 1072.1461 | AI76: 900.15246 | AJ76: 912.99361 | AK76: 1076.946 | AL76: 10107.085 | AM76: =SUMIFS(Z76:AK76,$Z$2:$AK$2,"是") -> 4048.9771 | AO76: TZ0051 | AP76: 70 | AQ76: 融合店其他品类收入(装甲门) | AR76: =AX76 -> 0 | AS76: 0 | AT76: 0 | AU76: 0 | AV76: 0 | AW76: 0 | AX76: 0 | AY76: 0 | AZ76: 0 | BA76: 0 | BB76: 0 | BC76: 0 | BD76: 0 | BE76: 0 | BF76: =SUMIFS(AS76:BD76,$AS$3:$BD$3,"是") -> 0 | BG76: =BM76 -> 8.182361 | BH76: 0 | BI76: 0 | BJ76: 0 | BK76: 0 | BL76: 0 | BM76: 8.182361 | BN76: 1.539974 | BO76: 5.47428 | BP76: 4.103888 | BQ76: 1.294682 | BR76: 0.902799 | BS76: 0.749577 | BT76: 22.247561 | BU76: =SUMIFS(BH76:BS76,$BH$3:$BS$3,"是") -> 8.182361
A77: 橱柜经销二部 | B77: 成本 | C77: 按产品 | D77: 其他加收 | E77: =K77 -> 0 | F77: 0 | G77: 0 | H77: 0 | I77: 0 | J77: 0 | K77: 0 | L77: 0 | M77: 0 | N77: 0 | O77: 0 | P77: 0 | Q77: 0 | R77: 0 | S77: =SUMIFS(F77:Q77,$F$2:$Q$2,"是") -> 0 | T77: 基数 | V77: 基数 | Y77: =AE77 -> 0 | AM77: =SUMIFS(Z77:AK77,$Z$2:$AK$2,"是") -> 0 | AR77: =AX77 -> 0 | BF77: =SUMIFS(AS77:BD77,$AS$3:$BD$3,"是") -> 0 | BG77: =BM77 -> 0
A78: 橱柜经销二部 | B78: 成本 | C78: 按订单类型 | D78: 常规单 | E78: =K78 -> 3529.2013 | F78: 1578.6017 | G78: 737.28689 | H78: 1951.9954 | I78: 2781.2488 | J78: 3273.5481 | K78: 3529.2013 | L78: 3444.5299 | M78: 3432.4953 | N78: 3686.4933 | O78: 2842.8953 | P78: 3146.9841 | Q78: 2689.3468 | R78: 33094.627 | S78: =SUMIFS(F78:Q78,$F$2:$Q$2,"是") -> 13851.882 | T78: 基数 | V78: 基数 | Y78: =AE78 -> 0 | AM78: =SUMIFS(Z78:AK78,$Z$2:$AK$2,"是") -> 0 | AR78: =AX78 -> 0 | BF78: =SUMIFS(AS78:BD78,$AS$3:$BD$3,"是") -> 0 | BG78: =BM78 -> 0
A79: 橱柜经销二部 | B79: 成本 | C79: 按订单类型 | D79: 家装单 | E79: =K79 -> 547.60414 | F79: 222.57594 | G79: 70.686024 | H79: 327.66384 | I79: 337.17172 | J79: 592.27 | K79: 547.60414 | L79: 659.46984 | M79: 545.14357 | N79: -45.187398 | O79: 510.83741 | P79: 448.44573 | Q79: 500.35329 | R79: 4717.0341 | S79: =SUMIFS(F79:Q79,$F$2:$Q$2,"是") -> 2097.9717 | T79: 基数 | V79: 基数 | W79: 2020年部门名称 | X79: 项目 | Y79: =AE79 -> 6月 | Z79: 1月 | AA79: 2月 | AB79: 3月 | AC79: 4月 | AD79: 5月 | AE79: 6月 | AF79: 7月 | AG79: 8月 | AH79: 9月 | AI79: 10月 | AJ79: 11月 | AK79: 12月 | AL79: 本年累计 | AM79: 同期 | AQ79: 收入调整 | AR79: =AX79 -> 0 | BF79: =SUMIFS(AS79:BD79,$AS$3:$BD$3,"是") -> 0 | BG79: =BM79 -> 19321.227 | BH79: =SUM(BH61:BH76)+BH57 -> 9544.7776 | BI79: =SUM(BI61:BI76)+BI57 -> 3377.1911 | BJ79: =SUM(BJ61:BJ76)+BJ57 -> 12560.083 | BK79: =SUM(BK61:BK76)+BK57 -> 13151.869 | BL79: =SUM(BL61:BL76)+BL57 -> 16471.133 | BM79: =SUM(BM61:BM76)+BM57 -> 19321.227 | BN79: =SUM(BN61:BN76)+BN57 -> 21291.756 | BO79: =SUM(BO61:BO76)+BO57 -> 22795.836 | ... BT79: =SUM(BT61:BT76)+BT57 -> 202458.98 | BU79: =SUMIFS(BH79:BS79,$BH$3:$BS$3,"是") -> 74426.28
A80: 橱柜经销二部 | B80: 成本 | C80: 按订单类型 | D80: 直供单 | E80: =K80 -> 1174.4727 | F80: 468.87079 | G80: 187.43321 | H80: 615.82608 | I80: 733.15778 | J80: 1111.6486 | K80: 1174.4727 | L80: 1033.7331 | M80: 1020.0028 | N80: 1393.268 | O80: 672.03314 | P80: 705.43005 | Q80: 683.33545 | R80: 9799.2117 | S80: =SUMIFS(F80:Q80,$F$2:$Q$2,"是") -> 4291.4091 | T80: 基数 | V80: 基数 | W80: 橱柜经销三分部 | X80: 房租 | Y80: =AE80 -> 1.3640401 | Z80: 1.2629298 | AA80: 1.6716099 | AB80: 0.74875987 | AC80: 2.7373731 | AD80: 2.3383401 | AE80: 1.3640401 | AF80: 5.3480401 | AG80: 3.1718401 | AH80: 2.9560401 | AI80: 7.8347071 | AJ80: 3.7523111 | AK80: 3.7523111 | AL80: 36.938302 | AM80: =SUMIFS(Z80:AK80,$Z$2:$AK$2,"是") -> 10.123053 | AQ80: 成本调整 | AR80: =AX80 -> 0 | BF80: =SUMIFS(AS80:BD80,$AS$3:$BD$3,"是") -> 0 | BG80: =BM80 -> 19325.845 | BH80: =SUM(BH61:BH76)-CB19 -> 9571.6568 | BI80: =SUM(BI61:BI76)-CC19 -> 3389.4892 | BJ80: =SUM(BJ61:BJ76)-CD19 -> 12573.761 | BK80: =SUM(BK61:BK76)-CE19 -> 13161.826 | BL80: =SUM(BL61:BL76)-CF19 -> 16494.502 | BM80: =SUM(BM61:BM76)-CG19 -> 19325.845 | BN80: =SUM(BN61:BN76)-CH19 -> 21313.739 | BO80: =SUM(BO61:BO76)-CI19 -> 22815.397 | ... BT80: =SUM(BT61:BT76)-CN19 -> 202650.66 | BU80: =SUMIFS(BH80:BS80,$BH$3:$BS$3,"是") -> 74517.08
A81: 橱柜经销二部 | B81: 成本 | C81: 按订单类型 | D81: 网销单 | E81: =K81 -> 0 | F81: 0 | G81: 0 | H81: 0 | I81: 0 | J81: 0 | K81: 0 | L81: 0 | M81: 0 | N81: 0 | O81: 0 | P81: 0 | Q81: 0 | R81: 0 | S81: =SUMIFS(F81:Q81,$F$2:$Q$2,"是") -> 0 | T81: 基数 | V81: 基数 | W81: 橱柜经销三分部 | X81: 水费 | Y81: =AE81 -> 0.039852 | Z81: 0.103518 | AA81: 0.04131 | AB81: 0.032562 | AC81: 0.031104 | AD81: 0.035964 | AE81: 0.039852 | AF81: 0.042282 | AG81: 0.042282 | AH81: 0.069498 | AI81: 0.102024 | AJ81: 0.03888 | AK81: 0.070956 | AL81: 0.650232 | AM81: =SUMIFS(Z81:AK81,$Z$2:$AK$2,"是") -> 0.28431 | AQ81: 毛利调整 | AR81: =AX81 -> 0 | BF81: =SUMIFS(AS81:BD81,$AS$3:$BD$3,"是") -> 0 | BG81: =BM81 -> -4.617952 | BH81: =BH79-BH80 -> -26.87921 | BI81: =BI79-BI80 -> -12.298141 | BJ81: =BJ79-BJ80 -> -13.677903 | BK81: =BK79-BK80 -> -9.957358 | BL81: =BL79-BL80 -> -23.369554 | BM81: =BM79-BM80 -> -4.617952 | BN81: =BN79-BN80 -> -21.983313 | BO81: =BO79-BO80 -> -19.560908 | ... BT81: =BT79-BT80 -> -191.68306 | BU81: =SUMIFS(BH81:BS81,$BH$3:$BS$3,"是") -> -90.800118
